Workbook
Name AU_TZ: #REF!

Sheet 00) Due Dates
B1: Bill | C1: Instatution | D1: Cost | E1: May | F1: June | G1: July | H1: August | I1: September | J1: October | K1: November | L1: December
B2: Subscription - Video | C2: Amazon Priome | D2: -15.04 | E2: 45424 | F2: =EDATE(E2,1) -> 45455 | G2: =EDATE(F2,1) -> 45485 | H2: =EDATE(G2,1) -> 45516 | I2: =EDATE(H2,1) -> 45547 | J2: =EDATE(I2,1) -> 45577 | K2: =EDATE(J2,1) -> 45608 | L2: =EDATE(K2,1) -> 45638
B3: Planet Fitness | C3: Planet Fitness | D3: -10 | E3: 45429 | F3: =EDATE(E3,1) -> 45460 | G3: =EDATE(F3,1) -> 45490 | H3: =EDATE(G3,1) -> 45521 | I3: =EDATE(H3,1) -> 45552 | J3: =EDATE(I3,1) -> 45582 | K3: =EDATE(J3,1) -> 45613 | L3: =EDATE(K3,1) -> 45643
B4: US Cellular | C4: US Cellular | D4: -35 | E4: 45434 | F4: =EDATE(E4,1) -> 45465 | G4: =EDATE(F4,1) -> 45495 | H4: =EDATE(G4,1) -> 45526 | I4: =EDATE(H4,1) -> 45557 | J4: =EDATE(I4,1) -> 45587 | K4: =EDATE(J4,1) -> 45618 | L4: =EDATE(K4,1) -> 45648
B5: WPS (Gas Bill) | C5: WPS | D5: -47 | E5: 45434 | F5: =EDATE(E5,1) -> 45465 | G5: =EDATE(F5,1) -> 45495 | H5: =EDATE(G5,1) -> 45526 | I5: =EDATE(H5,1) -> 45557 | J5: =EDATE(I5,1) -> 45587 | K5: =EDATE(J5,1) -> 45618 | L5: =EDATE(K5,1) -> 45648
B6: Subscription - Video | C6: Crunchyroll | D6: -10.49 | E6: 45436 | F6: =EDATE(E6,1) -> 45467 | G6: =EDATE(F6,1) -> 45497 | H6: =EDATE(G6,1) -> 45528 | I6: =EDATE(H6,1) -> 45559 | J6: =EDATE(I6,1) -> 45589 | K6: =EDATE(J6,1) -> 45620 | L6: =EDATE(K6,1) -> 45650
B7: XFinity | C7: XFinity | D7: -80.75 | E7: 45445 | F7: =EDATE(E7,1) -> 45475 | G7: =EDATE(F7,1) -> 45506 | H7: =EDATE(G7,1) -> 45537 | I7: =EDATE(H7,1) -> 45567 | J7: =EDATE(I7,1) -> 45598 | K7: =EDATE(J7,1) -> 45628
B8: MPU (Electric Bill) | C8: MPU | D8: -75 | E8: 45446 | F8: =EDATE(E8,1) -> 45476 | G8: =EDATE(F8,1) -> 45507 | H8: =EDATE(G8,1) -> 45538 | I8: =EDATE(H8,1) -> 45568 | J8: =EDATE(I8,1) -> 45599 | K8: =EDATE(J8,1) -> 45629
B9: Maintenance | C9: GitHub | D9: -10 | E9: 45446 | F9: =EDATE(E9,1) -> 45476 | G9: =EDATE(F9,1) -> 45507 | H9: =EDATE(G9,1) -> 45538 | I9: =EDATE(H9,1) -> 45568 | J9: =EDATE(I9,1) -> 45599 | K9: =EDATE(J9,1) -> 45629
B10: Car Insurance | C10: Geico | D10: -102.35 | E10: 45451 | F10: =EDATE(E10,1) -> 45481 | G10: =EDATE(F10,1) -> 45512 | H10: =EDATE(G10,1) -> 45543 | I10: =EDATE(H10,1) -> 45573 | J10: =EDATE(I10,1) -> 45604 | K10: =EDATE(J10,1) -> 45634
B11: Renter's Insurance | C11: Assurant | D11: -14.59 | E11: 45451 | F11: =EDATE(E11,1) -> 45481 | G11: =EDATE(F11,1) -> 45512 | H11: =EDATE(G11,1) -> 45543 | I11: =EDATE(H11,1) -> 45573 | J11: =EDATE(I11,1) -> 45604 | K11: =EDATE(J11,1) -> 45634
B13: Bill | C13: Instatution | D13: Cost | E13: May | F13: June | G13: July | H13: August | I13: September | J13: October | K13: November | L13: December
B14: Credit Card | C14: Mission Lane | D14: -25 | E14: 45436 | F14: =EDATE(E14,1) -> 45467 | G14: =EDATE(F14,1) -> 45497 | H14: =EDATE(G14,1) -> 45528 | I14: =EDATE(H14,1) -> 45559 | J14: =EDATE(I14,1) -> 45589 | K14: =EDATE(J14,1) -> 45620 | L14: =EDATE(K14,1) -> 45650
B15: Credit Card | C15: Amazon | D15: -36 | E15: 45437 | F15: =EDATE(E15,1) -> 45468 | G15: =EDATE(F15,1) -> 45498 | H15: =EDATE(G15,1) -> 45529 | I15: =EDATE(H15,1) -> 45560 | J15: =EDATE(I15,1) -> 45590 | K15: =EDATE(J15,1) -> 45621 | L15: =EDATE(K15,1) -> 45651
B16: Rent | C16: Chad Mrotek | D16: -875 | E16: 45444 | F16: =EDATE(E16,1) -> 45474 | G16: =EDATE(F16,1) -> 45505 | H16: =EDATE(G16,1) -> 45536 | I16: =EDATE(H16,1) -> 45566 | J16: =EDATE(I16,1) -> 45597 | K16: =EDATE(J16,1) -> 45627
B17: Rent (Water) | C17: Chad Mrotek | D17: -40 | E17: 45444 | F17: =EDATE(E17,1) -> 45474 | G17: =EDATE(F17,1) -> 45505 | H17: =EDATE(G17,1) -> 45536 | I17: =EDATE(H17,1) -> 45566 | J17: =EDATE(I17,1) -> 45597 | K17: =EDATE(J17,1) -> 45627
B18: Car Payment | C18: Bridgecrest | D18: -531 | E18: 45451 | F18: =EDATE(E18,1) -> 45481 | G18: =EDATE(F18,1) -> 45512 | H18: =EDATE(G18,1) -> 45543 | I18: =EDATE(H18,1) -> 45573 | J18: =EDATE(I18,1) -> 45604 | K18: =EDATE(J18,1) -> 45634
B20: Bill | C20: Instatution | D20: Cost | E20: July | F20: August | G20: September | H20: October | I20: November | J20: December
B21: Medication | C21: Hims | D21: -65 | E21: 45479 | F21: =EDATE(E21,1) -> 45510 | G21: =EDATE(F21,1) -> 45541 | H21: =EDATE(G21,1) -> 45571 | I21: =EDATE(H21,1) -> 45602 | J21: =EDATE(I21,1) -> 45632
B23: Direct Witdrawl Bills
B24: Bill | C24: Cost (BiWeekly) | D24: Remaining Cost | E24: Remaining Payments
B25: MDG | C25: 48.47 | D25: 2076.78 | E25: 99
B26: Above Lending | C26: 86.95 | D26: 5191.76 | E26: 84

Sheet 01) Bill Information
A1: Active | B1: Catagory | C1: Keyword | D1: Bill Type | E1: Last Pay Date | F1: Due Date | G1: Amount
A2: FALSE | B2: Rent | D2: Month Set | F2: 1 | G2: -966.39
A3: TRUE | B3: XFinity | D3: Month Set | E3: 45746 | F3: 2 | G3: -112.83
A4: TRUE | B4: MPU (Electric Bill) | D4: 30 Day | E4: 45746 | F4: 3 | G4: -61.91
A5: TRUE | B5: Car Insurance | D5: Month Set | E5: 45723 | F5: 8 | G5: -112.57
A6: TRUE | B6: Credit Cards | C6: Lowes | D6: Month Set | E6: 45726 | F6: 13 | G6: -200
A7: TRUE | B7: Planet Fitness | D7: Month Set | E7: 45733 | F7: 17 | G7: -10
A8: TRUE | B8: WPS (Gas Bill) | D8: 30 Day | E8: 45727 | F8: 20 | G8: -47
A9: TRUE | B9: Credit Cards | C9: Mission Lane | D9: Month Set | E9: 45726 | F9: 24 | G9: -50
A10: TRUE | B10: US Cellular | D10: 30 Day | E10: 45723 | F10: 25 | G10: -92.78
A11: TRUE | B11: Credit Cards | C11: Amazon | D11: Month Set | E11: 45726 | F11: 25 | G11: -50
A12: FALSE | B12: Credit Cards | C12: Care Credit | D12: Month Set | F12: 25 | G12: 0
A13: TRUE | B13: Car Payment | D13: Month Set | E13: 45726 | F13: 28 | G13: -471.27
A14: FALSE | B14: Renter's Insurance | D14: Month Set | G14: 0

Sheet Budget 2025
A1: Bill | B1: Date | C1: Payment
A2: Income: Paycheck | B2: 45667 | C2: 1906.37
A3: Above Lending | B3: 45667 | C3: -86.95
A4: Car Payment | B4: 45667 | C4: -471.27
A5: Credit Cards | B5: 45667 | C5: -200
A6: Credit Cards | B6: 45667 | C6: -50
A7: US Cellular | B7: 45667 | C7: -91.59
A8: Planet Fitness | B8: 45667 | C8: -10
A9: Income: Paycheck | B9: 45681 | C9: 1906.37
A10: Above Lending | B10: 45681 | C10: -86.95
A11: Car Payment | B11: 45681 | C11: -471.27
A12: Credit Cards | B12: 45681 | C12: -200
A13: Credit Cards | B13: 45681 | C13: -50
... A202: Car Payment | B202: 46042 | C202: -471.27

Sheet 01.5) Debt
C1: Updated Date: | D1: 45710
A2: Column 1 | B2: Debt | C2: Amount | D2: Montly Payment | E2: Web Link | F2: Ref. | G2: Left | H2: Due | I2: Total | J2: Frequency | K2: Term | L2: Remaining | M2: First | N2: Final | O2: APR
A3: TRUE | B3: MDG | C3: 1859.79 | D3: =48.47*2 -> 96.94 | E3: MDG | G3: 80 | H3: 48.47 | I3: 2107.35 | J3: Bi-Weekly | K3: =IF(J3="Bi-Weekly", DATEDIF(M3, EDATE($D$1, G3/2), "M") / 12, IF(J3="Monthly", DATEDIF(M3, EDATE($D$1, G3), "M") / 12, "Invalid Frequency")) -> 4.5833333 | L3: 1859.79 | M3: 45229 | N3: =EDATE(M3, K3 * 12) -> 46903 | O3: 0.273
A4: TRUE | B4: Above Lending | C4: 4193.08 | D4: =86.95*2 -> 173.9 | E4: Above Lending | G4: 63 | H4: 86.95 | I4: 6186.15 | J4: Bi-Weekly | K4: =IF(J4="Bi-Weekly", DATEDIF(M4, EDATE($D$1, G4/2), "M") / 12, IF(J4="Monthly", DATEDIF(M4, EDATE($D$1, G4), "M") / 12, "Invalid Frequency")) -> 4.9166667 | L4: 4193.08 | M4: 44839 | N4: =EDATE(M4, K4 * 12) -> 46635 | O4: 0.254417
A5: FALSE | B5: Car Loan | C5: 24494.11 | D5: 471.27 | E5: Genisys | G5: 67 | H5: 471.27 | I5: 26622.13 | J5: Monthly | K5: =IF(J5="Bi-Weekly", DATEDIF(M5, EDATE($D$1, G5/2), "M") / 12, IF(J5="Monthly", DATEDIF(M5, EDATE($D$1, G5), "M") / 12, "Invalid Frequency")) -> 6.0833333 | L5: 24494.11 | M5: 45513 | N5: =EDATE(M5, K5 * 12) -> 47735 | O5: 0.0799
A6: FALSE | B6: Amazon Credit Card | C6: 774.82 | D6: 100 | E6: Amazon | J6: Monthly
A7: TRUE | B7: Mission Lane Credit Card | C7: 2548.82 | D7: 200 | E7: Mission Lane | J7: Monthly
A8: FALSE | B8: Lowes (Washer / Dryer) | C8: 369.31 | D8: 194.7 | E8: Lowes (Loan) | J8: Monthly
A9: FALSE | B9: Lowes Credit Card | C9: 1054 | D9: 194.7 | E9: Lowes (Credit) | J9: Monthly
A10: FALSE | B10: Affirm # 1 | C10: =138.67-6.3 -> 132.37 | D10: 0 | E10: Affirm 1 | J10: Monthly
A11: FALSE | B11: Affirm # 2 | C11: =242.2-11.01 -> 231.19 | D11: 0 | E11: Affirm 2 | J11: Monthly
A12: FALSE | B12: Affirm # 3 | C12: =566.65-23.61-23.61 -> 519.43 | D12: 0 | E12: Affirm 3 | J12: Monthly
A13: FALSE | B13: Affirm # 4 | C13: =1129.34-47.06-47.06 -> 1035.22 | D13: 0 | E13: Affirm 4 | J13: Monthly
A14: FALSE | B14: Affirm # 5 | C14: =1136.36-47.37-47.37 -> 1041.62 | D14: 0 | E14: Affirm 5 | J14: Monthly
A15: FALSE | B15: Aurora Collection 1 | C15: 515 | D15: 0 | E15: EvokePay | F15: 12634667 | J15: Monthly
A16: FALSE | B16: Aurora Collection 2 | C16: 1910 | D16: 0 | E16: Call 1-800-215-8756 | F16: 11946574 | J16: Monthly
A17: FALSE | B17: Milestone Credit Card | C17: 1085.49 | D17: 0 | E17: Credit Corp | F17: 32602628 | J17: Monthly
C19: Total Amount | D19: Total Monthly Payment
C20: =IFERROR(__xludf.DUMMYFUNCTION("IF(COUNTIF(A3:A17, TRUE) = 0, 0, SUM(FILTER(C3:C17, A3:A17 = TRUE))) "),8601.69) -> 8601.69 | D20: =IFERROR(__xludf.DUMMYFUNCTION("IF(COUNTIF(A3:A17, TRUE) = 0, 0, SUM(FILTER(D3:D17, A3:A17 = TRUE))) "),470.84000000000003) -> 470.84

Sheet 02) 2023 Shopping List
B2: Tax | C2: Item | D2: Isle | E2: Category | F2: Amount | G2: Cost of One | H2: Total Cost
B3: FALSE | C3: Milk | D3: A-23 | E3: Groceries | F3: 2 | G3: 2.66 | H3: =IF( B3 = TRUE ,(G3*F3)*0.05+(G3*F3) , G3*F3 ) -> 5.32
B4: TRUE | C4: Toilet Bowl Cleaner | D4: J-11 | E4: Bathroom | F4: 1 | G4: 5.18 | H4: =IF( B4 = TRUE ,(G4*F4)*0.05+(G4*F4) , G4*F4 ) -> 5.439
B5: TRUE | C5: Hand Soap | D5: G-16 | E5: Bathroom | F5: 2 | G5: 2.47 | H5: =IF( B5 = TRUE ,(G5*F5)*0.05+(G5*F5) , G5*F5 ) -> 5.187
B6: TRUE | C6: Toilet Paper | D6: J-07 | E6: Bathroom | F6: 1 | G6: 6.98 | H6: =IF( B6 = TRUE ,(G6*F6)*0.05+(G6*F6) , G6*F6 ) -> 7.329
B7: FALSE | C7: Pop Tarts | D7: A-08 | E7: Groceries | F7: 1 | G7: 4.47 | H7: =IF( B7 = TRUE ,(G7*F7)*0.05+(G7*F7) , G7*F7 ) -> 4.47
B8: FALSE | C8: Zebra Cakes | D8: A-06 | E8: Groceries (Lunch) | F8: 4 | G8: 2.68 | H8: =IF( B8 = TRUE ,(G8*F8)*0.05+(G8*F8) , G8*F8 ) -> 10.72
B9: FALSE | C9: Oreos | D9: A-18 | E9: Groceries | F9: 1 | G9: 4.58 | H9: =IF( B9 = TRUE ,(G9*F9)*0.05+(G9*F9) , G9*F9 ) -> 4.58
B10: FALSE | C10: Soda | D10: A-20 | E10: Groceries | F10: 4 | G10: 3.88 | H10: =IF( B10 = TRUE ,(G10*F10)*0.05+(G10*F10) , G10*F10 ) -> 15.52
B11: FALSE | C11: Pizza | D11: A-04 | E11: Groceries | F11: 2 | G11: 3.98 | H11: =IF( B11 = TRUE ,(G11*F11)*0.05+(G11*F11) , G11*F11 ) -> 7.96
B12: FALSE | C12: Nutter Butters | D12: A-18 | E12: Groceries | F12: 1 | G12: 4.68 | H12: =IF( B12 = TRUE ,(G12*F12)*0.05+(G12*F12) , G12*F12 ) -> 4.68
B13: FALSE | G13: 0 | H13: =IF( B13 = TRUE ,(G13*F13)*0.05+(G13*F13) , G13*F13 ) -> 0
B14: FALSE | G14: 0 | H14: =IF( B14 = TRUE ,(G14*F14)*0.05+(G14*F14) , G14*F14 ) -> 0
B15: FALSE | G15: 0 | H15: =IF( B15 = TRUE ,(G15*F15)*0.05+(G15*F15) , G15*F15 ) -> 0
B16: FALSE | G16: 0 | H16: =IF( B16 = TRUE ,(G16*F16)*0.05+(G16*F16) , G16*F16 ) -> 0
B17: FALSE | G17: 0 | H17: =IF( B17 = TRUE ,(G17*F17)*0.05+(G17*F17) , G17*F17 ) -> 0
B18: FALSE | C18: Hydroxizine | D18: CVS | E18: Medical | F18: 1 | G18: 10 | H18: =IF( B18 = TRUE ,(G18*F18)*0.05+(G18*F18) , G18*F18 ) -> 10
B19: FALSE | C19: Mission Lane Credit Card | F19: 1 | G19: -287.08 | H19: =IF( B19 = TRUE ,(G19*F19)*0.05+(G19*F19) , G19*F19 ) -> -287.08
B20: FALSE | G20: 0 | H20: =IF( B20 = TRUE ,(G20*F20)*0.05+(G20*F20) , G20*F20 ) -> 0
B21: FALSE | G21: 0 | H21: =IF( B21 = TRUE ,(G21*F21)*0.05+(G21*F21) , G21*F21 ) -> 0
B22: FALSE | G22: 0 | H22: =IF( B22 = TRUE ,(G22*F22)*0.05+(G22*F22) , G22*F22 ) -> 0
B23: FALSE | G23: 0 | H23: =IF( B23 = TRUE ,(G23*F23)*0.05+(G23*F23) , G23*F23 ) -> 0
B24: FALSE | G24: 0 | H24: =IF( B24 = TRUE ,(G24*F24)*0.05+(G24*F24) , G24*F24 ) -> 0
B25: FALSE | G25: 0 | H25: =IF( B25 = TRUE ,(G25*F25)*0.05+(G25*F25) , G25*F25 ) -> 0
B26: FALSE | G26: 0 | H26: =IF( B26 = TRUE ,(G26*F26)*0.05+(G26*F26) , G26*F26 ) -> 0
B27: FALSE | G27: 0 | H27: =IF( B27 = TRUE ,(G27*F27)*0.05+(G27*F27) , G27*F27 ) -> 0
B28: FALSE | G28: 0 | H28: =IF( B28 = TRUE ,(G28*F28)*0.05+(G28*F28) , G28*F28 ) -> 0
B29: FALSE | G29: 0 | H29: =IF( B29 = TRUE ,(G29*F29)*0.05+(G29*F29) , G29*F29 ) -> 0
B30: FALSE | G30: 0 | H30: =IF( B30 = TRUE ,(G30*F30)*0.05+(G30*F30) , G30*F30 ) -> 0
B31: FALSE | G31: 0 | H31: =IF( B31 = TRUE ,(G31*F31)*0.05+(G31*F31) , G31*F31 ) -> 0
... B52: FALSE | G52: 0 | H52: =IF( B52 = TRUE ,(G52*F52)*0.05+(G52*F52) , G52*F52 ) -> 0
C53: Total Cost: | H53: =sum(H3:H52) -> -205.875
B54: Remaining Balance: | H54: ='11) 2023 BudgetBill Breakdown'!H273-H53 -> 220.225

Sheet 03) Current YTD Report
J1: DROPDOWN
B2: Income | C2: 2024 YTD Amount | G2: US Cellular | H2: =-I$2/C$33 -> 0.027968977 | I2: =SUMIF('01) BudgetBill Breakdown'!B$1:B37,J$6, '01) BudgetBill Breakdown'!G$1:G37) -> -2833.84 | J2: Income: Paycheck
B3: =J2 -> Income: Paycheck | C3: =SUMIF('01) BudgetBill Breakdown'!B1:B37,B3, '01) BudgetBill Breakdown'!G1:G37) -> 96053.7 | G3: =J$7 -> Rent | H3: =-I$3/C$33 -> 0.26130195 | I3: =SUMIF('01) BudgetBill Breakdown'!B$1:B37,"Rent", '01) BudgetBill Breakdown'!G$1:G37) -> -26475.33 | J3: Income: Lottery
B4: =J4 -> Income: Tax Return | C4: =SUMIF('01) BudgetBill Breakdown'!B$1:B37,B4, '01) BudgetBill Breakdown'!G$1:G37) -> 3973 | G4: ='08) Drop Down Menus'!$A$2 -> Groceries | H4: =-I$4/C$33 -> 0.13088789 | I4: =SUMIF('01) BudgetBill Breakdown'!B$1:B37,J$8, '01) BudgetBill Breakdown'!G$1:G37) -> -13261.67 | J4: Income: Tax Return
B5: =J5 -> Income: Other | C5: =SUMIF('01) BudgetBill Breakdown'!B$1:B37,B5, '01) BudgetBill Breakdown'!G$1:G37) -> 1294.13 | G5: ='08) Drop Down Menus'!$A$3 -> Cigarettes | H5: =-I$5/C$33 -> 0.031539813 | I5: =SUMIF('01) BudgetBill Breakdown'!B$1:B37,J$9, '01) BudgetBill Breakdown'!G$1:G37) -> -3195.64 | J5: Income: Other
G6: ='08) Drop Down Menus'!$A$4 -> Gas | H6: =-I$6/C$33 -> 0.011050048 | I6: =SUMIF('01) BudgetBill Breakdown'!B$1:B37,J$10, '01) BudgetBill Breakdown'!G$1:G37) -> -1119.6 | J6: US Cellular
B7: Expence | C7: YTD Cost | D7: Percentile | E7: Monthly Avg. | G7: ='08) Drop Down Menus'!$A$5 -> Entertainment | H7: =-I$7/C$33 -> 0.051025145 | I7: =SUMIF('01) BudgetBill Breakdown'!B$1:B37,J$11, '01) BudgetBill Breakdown'!G$1:G37) -> -5169.91 | J7: Rent
B8: =G$3 -> Rent | C8: =I$3-935 -> -27410.33 | D8: =H$3 -> 0.26130195 | E8: =C8/H$26 -> -8092.5736 | G8: ='08) Drop Down Menus'!$A$6 -> Medical | H8: =-I$8/C$33 -> 0.012135116 | I8: =SUMIF('01) BudgetBill Breakdown'!B$1:B37,J$12, '01) BudgetBill Breakdown'!G$1:G37) -> -1229.54 | J8: Groceries
B9: =G$4 -> Groceries | C9: =I$4 -> -13261.67 | D9: =H$4 -> 0.13088789 | E9: =C9/H$26 -> -3915.3502 | G9: ='08) Drop Down Menus'!$A$7 -> Vehicle | H9: =-I$9/C$33 -> 0.0078796236 | I9: =SUMIF('01) BudgetBill Breakdown'!B$1:B37,J$13, '01) BudgetBill Breakdown'!G$1:G37) -> -798.37 | J9: Cigarettes
B10: =G$13 -> Car Payment | C10: =I$13-300 -> -12918.59 | D10: =H$13 -> 0.12454093 | E10: =C10/H$26 -> -3814.0599 | G10: ='08) Drop Down Menus'!$A$8 -> Maintenance | H10: =-I$10/C$33 -> 0.024703509 | I10: =SUMIF('01) BudgetBill Breakdown'!B$1:B37,J$14, '01) BudgetBill Breakdown'!G$1:G37) -> -2502.98 | J10: Gas
B11: =G$2 -> US Cellular | C11: =I$2 -> -2833.84 | D11: =H$2 -> 0.027968977 | E11: =C11/H$26 -> -836.65752 | G11: Above Lending | H11: =-I$11/C$33 -> 0.048915411 | I11: =SUMIF('01) BudgetBill Breakdown'!B$1:B37,J$15, '01) BudgetBill Breakdown'!G$1:G37) -> -4956.15 | J11: Entertainment
B12: =G$11 -> Above Lending | C12: =I$11 -> -4956.15 | D12: =H$11 -> 0.048915411 | E12: =C12/H$26 -> -1463.2443 | G12: Planet Fitness | H12: =-I$12/C$33 -> 0.0030497184 | I12: =SUMIF('01) BudgetBill Breakdown'!B$1:B37,J$16, '01) BudgetBill Breakdown'!G$1:G37) -> -309 | J12: Medical
B13: =G$5 -> Cigarettes | C13: =I$5 -> -3195.64 | D13: =H$5 -> 0.031539813 | E13: =C13/H$26 -> -943.47467 | G13: Car Payment | H13: =-I$13/C$33 -> 0.12454093 | I13: =SUMIF('01) BudgetBill Breakdown'!B$1:B37,J$17, '01) BudgetBill Breakdown'!G$1:G37) -> -12618.59 | J13: Vehicle
B14: =G$16 -> XFinity | C14: =I$16 -> -2601.07 | D14: =H$16 -> 0.025671622 | E14: =C14/H$26 -> -767.93495 | G14: WPS (Gas Bill) | H14: =-I$14/C$33 -> 0.014091673 | I14: =SUMIF('01) BudgetBill Breakdown'!B$1:B37,J$18, '01) BudgetBill Breakdown'!G$1:G37) -> -1427.78 | J14: Maintenance
B15: =G$14 -> WPS (Gas Bill) | C15: =I$14 -> -1427.78 | D15: =H$14 -> 0.014091673 | E15: =C15/H$26 -> -421.53505 | G15: Credit Cards | H15: =-I$15/C$33 -> 0.10297132 | I15: =SUMIF('01) BudgetBill Breakdown'!B$1:B37,J$19, '01) BudgetBill Breakdown'!G$1:G37) -> -10433.14 | J15: Above Lending
B16: =G$7 -> Entertainment | C16: =I$7 -> -5169.91 | D16: =H$7 -> 0.051025145 | E16: =C16/H$26 -> -1526.3544 | G16: XFinity | H16: =-I$16/C$33 -> 0.025671622 | I16: =SUMIF('01) BudgetBill Breakdown'!B$1:B37,J$20, '01) BudgetBill Breakdown'!G$1:G37) -> -2601.07 | J16: Planet Fitness
B17: =G$10 -> Maintenance | C17: =I$10 -> -2502.98 | D17: =H$10 -> 0.024703509 | E17: =C17/H$26 -> -738.97505 | G17: Car Insurance | H17: =-I$17/C$33 -> 0.028165383 | I17: =SUMIF('01) BudgetBill Breakdown'!B$1:B37,J$21, '01) BudgetBill Breakdown'!G$1:G37) -> -2853.74 | J17: Car Payment
B18: =G$15 -> Credit Cards | C18: =I$15 -> -10433.14 | D18: =H$15 -> 0.10297132 | E18: =C18/H$26 -> -3080.2604 | G18: Renter's Insurance | H18: =-I$18/C$33 -> 0.0016277995 | I18: =SUMIF('01) BudgetBill Breakdown'!B$1:B37,J$22, '01) BudgetBill Breakdown'!G$1:G37) -> -164.93 | J18: WPS (Gas Bill)
B19: =G$17 -> Car Insurance | C19: =I$17 -> -2853.74 | D19: =H$17 -> 0.028165383 | E19: =C19/H$26 -> -842.53276 | G19: Subscription - Video | H19: =-I$19/C$33 -> 0.0063419338 | I19: =SUMIF('01) BudgetBill Breakdown'!B$1:B37,J$23, '01) BudgetBill Breakdown'!G$1:G37) -> -642.57 | J19: Credit Cards
B20: =G$9 -> Vehicle | C20: =I$9 -> -798.37 | D20: =H$9 -> 0.0078796236 | E20: =C20/H$26 -> -235.70924 | G20: Subscription - Game | H20: =-I$20/C$33 -> 0.0013532262 | I20: =SUMIF('01) BudgetBill Breakdown'!B$1:B37,J$24, '01) BudgetBill Breakdown'!G$1:G37) -> -137.11 | J20: XFinity
B21: =G$21 -> MPU (Electric Bill) | C21: =I$21 -> -2424.41 | D21: =H$21 -> 0.023928051 | E21: =C21/H$26 -> -715.77819 | G21: MPU (Electric Bill) | H21: =-I$21/C$33 -> 0.023928051 | I21: =SUMIF('01) BudgetBill Breakdown'!B$1:B37,J$25, '01) BudgetBill Breakdown'!G$1:G37) -> -2424.41 | J21: Car Insurance
B22: =G$22 -> Debt | C22: =I$22 -> -4471.64 | D22: =H$22 -> 0.044133472 | E22: =C22/H$26 -> -1320.1985 | G22: Debt | H22: =-I$22/C$33 -> 0.044133472 | I22: =SUMIF('01) BudgetBill Breakdown'!B$1:B37,J$26, '01) BudgetBill Breakdown'!G$1:G37) -> -4471.64 | J22: Renter's Insurance
B23: =G$6 -> Gas | C23: =I$6 -> -1119.6 | D23: =H$6 -> 0.011050048 | E23: =C23/H$26 -> -330.54857 | G23: Holiday Gifts | H23: =-I$23/C$33 -> 0.0043158944 | I23: =SUMIF('01) BudgetBill Breakdown'!B$1:B37,J$27, '01) BudgetBill Breakdown'!G$1:G37) -> -437.29 | J23: Subscription - Video
B24: =G$8 -> Medical | C24: =I$8 -> -1229.54 | D24: =H$8 -> 0.012135116 | E24: =C24/H$26 -> -363.00705 | G24: Haircut | H24: =-I$24/C$33 -> 0.0034566436 | I24: =SUMIF('01) BudgetBill Breakdown'!B$1:B37,J$28, '01) BudgetBill Breakdown'!G$1:G37) -> -350.23 | J24: Subscription - Game
B25: =G$19 -> Subscription - Video | C25: =I$19 -> -642.57 | D25: =H$19 -> 0.0063419338 | E25: =C25/H$26 -> -189.71114 | J25: MPU (Electric Bill)
B26: =G$18 -> Renter's Insurance | C26: =I$18 -> -164.93 | D26: =H$18 -> 0.0016277995 | E26: =C26/H$26 -> -48.693619 | G26: Month + Day | H26: =H27+(H28/H30) -> 3.3870968 | J26: Debt
B27: =G$12 -> Planet Fitness | C27: =I$12 -> -309 | D27: =H$12 -> 0.0030497184 | E27: =C27/H$26 -> -91.228571 | G27: Current Month | H27: =Month(NOW()) -> 3 | J27: Holiday Gifts
B28: Holiday Gifts | C28: =I$23 -> -437.29 | D28: =H$23 -> 0.0043158944 | E28: =C28/H$26 -> -129.10467 | G28: Current Day | H28: =DAY(NOW()) -> 12 | J28: Haircut
B29: Haircut | C29: =I$24 -> -350.23 | D29: =H$24 -> 0.0034566436 | E29: =C29/H$26 -> -103.40124
B30: =G$20 -> Subscription - Game | C30: =I$20 -> -137.11 | D30: =H$20 -> 0.0013532262 | E30: =C30/H$26 -> -40.480095 | G30: Last Day | H30: =DAY(EOMONTH(TODAY(),0)) -> 31
G31: Year | H31: =YEAR(TODAY()) -> 2026
B32: YTD Total Spent | C32: =sum(I2:I22) -> -99627.01
B33: YTD Total Earned | C33: =sum(C3:C5) -> 101320.83
B34: Difference | C34: =C33+C32 -> 1693.82
B35: % Profit | C35: =C34/C33 -> 0.016717392
B36: Possible Monthly Savings | C36: =-(E11+E9+E23+30+200) -> 4852.5563
B37: * Paycheck YTD is Gross not Net | E37: ="Report Date : " & $H$27 & "/" & $H$28 & "/" & $H$31 -> Report Date : 3/12/2026

Sheet 04) 2023 Rent Schedule
A1: Date | B1: Amount | C1: Description | D1: Extra
A2: 44741 | B2: 100 | C2: Cash Down/July Rent | E2: Total Rent Paid : | F2: =sum(B2:B22)-F3-F4 -> 8950
A3: 44743 | B3: 795 | C3: Remaining July Rent | E3: Total Water Paid : | F3: =29.88+28.8+34.81+24.81+42.62+28.1+24.54+52.52 -> 266.08
A4: 44757 | B4: 671.25 | C4: 1st Half August | D4: 1/4 Sec. Dep ($223.75) | E4: Security Deposit : | F4: 895
A5: 44774 | B5: 671.25 | C5: 2nd Half August | D5: 1/4 Sec. Dep ($223.75)
A6: 44785 | B6: 671.25 | C6: 1st Half September | D6: 1/4 Sec. Dep ($223.75)
A7: 44799 | B7: 671.25 | C7: 2nd Half September | D7: 1/4 Sec. Dep ($223.75)
A8: 44813 | B8: 477.38 | C8: 1st Half October | D8: July Water ($29.88)
A9: 44830 | B9: 447.5 | C9: 2nd Half October | D9: Only Rent
A10: 44841 | B10: 447.5 | C10: 1st Half November | D10: Only Rent
A11: 44855 | B11: 476.3 | C11: 2nd Half November | D11: August Water ($28.80)
A12: 44869 | B12: 482.31 | C12: 1st Half December | D12: September Water ($34.81)
A13: 44883 | B13: 447.5 | C13: 2nd Half December | D13: Only Rent
A14: 44897 | B14: 472.31 | C14: 1st Half January | D14: October Water ($24.81)
A15: 44911 | B15: 447.5 | C15: 2nd Half January | D15: Only Rent
A16: 44929 | B16: 42.62 | C16: Water Only | D16: November Water ($42.62)
A17: 44944 | B17: 0
A18: 44953 | B18: 923.1 | C18: February Rent | D18: December Water ($28.10)
A19: 44967 | B19: 0
A20: 44981 | B20: 919.54 | C20: March Rent | D20: January Water ($24.54)
A21: 44995
A22: 45009 | B22: =447.5*2+52.52 -> 947.52 | C22: April Rent | D22: February Water ($52.52)
A23: 45023
A24: 45037 | B24: =447.5*2 -> 895 | C24: May Rent | D24: March Water
A25: 45051 | B25: 447.5 | C25: 1st Half June | D25: Only Rent
A26: 45065 | C26: 2nd Half June | D26: April Water
A27: 45079 | B27: 447.5 | C27: 1st Half July | D27: Only Rent
A28: 45093 | C28: 2nd Half July | D28: May Water
A29: End of 1 Year Lease
A30: 45107 | B30: 0 | C30: NOTHING | D30: NOTHING
A31: 45121 | C31: 1st Half August | D31: June Water
A32: 45135 | B32: 447.5 | C32: 2nd Half August | D32: Only Rent
A33: 45149 | C33: 1st Half September | D33: July Water
A34: 45163 | B34: 447.5 | C34: 2nd Half September | D34: Only Rent
A35: 45177 | C35: 1st Half October | D35: August Water
A36: 45191 | B36: 447.5 | C36: 2nd Half October | D36: Only Rent
A37: 45205 | C37: 1st Half November | D37: September Water
A38: 45219 | B38: 447.5 | C38: 2nd Half November | D38: Only Rent
A39: 45233 | C39: 1st Half December | D39: October Water
A40: 45247 | B40: 447.5 | C40: 2nd Half December | D40: Only Rent
A41: 45261 | C41: 1st Half January | D41: November Water
A42: 45275 | B42: 447.5 | C42: 2nd Half January | D42: Only Rent
A43: 45289 | C43: WATER ONLY | D43: Water Only

Sheet 05) Paycheck Calculator
C2: Rate | D2: Hours | E2: Earned | G2: Taxes | I2: % | L2: Week 1
B3: Normal Time | C3: 18.03 | D3: 80 | E3: =C3*D3 -> 1442.4 | G3: Federal | H3: =E7*I3 -> 159.05278 | I3: 0.063918123 | L3: Sunday | M3: Monday | N3: Tuesday | O3: Wednesday | P3: Thursday | Q3: Friday | R3: Saturday
B4: Shift Premium | C4: 3 | D4: =D3 -> 80 | E4: =C4*D4 -> 240 | G4: Social Security | H4: =E7*I4 -> 157.66469 | I4: 0.063360292 | K4: Date: | L4: 45368 | M4: =L4+1 -> 45369 | N4: =M4+1 -> 45370 | O4: =N4+1 -> 45371 | P4: =O4+1 -> 45372 | Q4: =P4+1 -> 45373 | R4: =Q4+1 -> 45374
B5: Overtime | C5: =C3*1.5+C4 -> 30.045 | D5: =L7+L14 -> 32 | E5: =C5*D5 -> 961.44 | G5: Medicare | H5: =E7*I5 -> 36.880967 | I5: 0.014821257 | K5: Hours: | L5: 11 | M5: =8.5+2.5 -> 11 | N5: 12 | O5: 12 | P5: 12 | Q5: =8.5+3 -> 11.5 | R5: 0
B6: Total Earned : | E6: =SUM(E3:E5) -> 2643.84 | G6: WI State | H6: =E7*I6 -> 88.626139 | I6: 0.035615953 | K6: Total Hours: | L6: =L5 -> 11 | M6: =L6+M5 -> 22 | N6: =M6+N5 -> 34 | O6: =N6+O5 -> 46 | P6: =O6+P5 -> 58 | Q6: =P6+Q5 -> 69.5 | R6: =Q6+R5 -> 69.5
B7: Taxable Income : | E7: =E6-H18 -> 2488.3832 | G7: Total Taxes | H7: =SUM(H3:H6) -> 442.22457 | K7: Total O.T.: | L7: =MAX(0,sum(L5:R5)-40) -> 29.5
B9: Tax Rate | G9: Benefits | L9: Week 2
B10: =H7/E7 -> 0.17771562 | G10: Add Vision | H10: 3.35 | L10: Sunday | M10: Monday | N10: Tuesday | O10: Wednesday | P10: Thursday | Q10: Friday | R10: Saturday
G11: Flex | H11: 19.23 | K11: Date: | L11: =R4+1 -> 45375 | M11: =L11+1 -> 45376 | N11: =M11+1 -> 45377 | O11: =N11+1 -> 45378 | P11: =O11+1 -> 45379 | Q11: =P11+1 -> 45380 | R11: =Q11+1 -> 45381
B12: Take Home | G12: Life & Disability | H12: 2 | K12: Hours: | L12: 0 | M12: 8.5 | N12: 8.5 | O12: 8.5 | P12: 8.5 | Q12: 8.5 | R12: 0
B13: =E6-(E7*B10)-H18-H16 -> 2036.9686 | G13: Seos 4000 | H13: 75 | K13: Total Hours: | L13: =R6+L12 -> 69.5 | M13: =L13+M12 -> 78 | N13: =M13+N12 -> 86.5 | O13: =N13+O12 -> 95 | P13: =O13+P12 -> 103.5 | Q13: =P13+Q12 -> 112 | R13: =Q13+R12 -> 112
G14: Sing Dental | H14: 3 | K14: Total O.T.: | L14: =MAX(0,sum(L12:R12)-40) -> 2.5
G15: 401K | H15: =E6*2% -> 52.8768
G16: Additional Life | H16: 9.19
G17: Total Benefits | H17: =sum(H10:H16) -> 164.6468
G18: Non Tax Benefits | H18: =sum(H10:I15) -> 155.4568
G19: Benefit % | H19: =1-(E7/E6) -> 0.058799625

Sheet 06) Med Counter
B1: 45067
B2: Medication | C2: Amount | D2: Per Day | E2: Days Left | F2: Months Left | G2: Refill Date
B3: Venlafaxine | C3: 41 | D3: 1 | E3: =C3/D3 -> 41 | F3: =E3/31 -> 1.3225806 | G3: =B$1+E3-5 -> 45103
B4: Vyvanse | C4: 15 | D4: 1 | E4: =C4/D4 -> 15 | F4: =E4/31 -> 0.48387097 | G4: =B$1+E4-5 -> 45077
B5: Hydroxyzine | C5: =27+14 -> 41 | D5: 2 | E5: =C5/D5 -> 20.5 | F5: =E5/31 -> 0.66129032 | G5: =B$1+E5-5 -> 45082.5
B6: Prazosin | C6: 262 | D6: 2 | E6: =C6/D6 -> 131 | F6: =E6/31 -> 4.2258065 | G6: =B$1+E6-5 -> 45193
B7: Omeprazole | C7: 19 | D7: 1 | E7: =C7/D7 -> 19 | F7: =E7/31 -> 0.61290323 | G7: =B$1+E7-5 -> 45081
B8: Diphenhydramine | C8: 98 | D8: 2 | E8: =C8/D8 -> 49 | F8: =E8/31 -> 1.5806452 | G8: =B$1+E8-5 -> 45111

Sheet 06) W@H Timecard
B2: MTM Application Time Card - John Koll
B3: Date Range - 12/04/2023 to 12/10/2023
B5: Date | C5: Start | D5: Stop | E5: Worked On | F5: Total
B6: 45264 | C6: 0.83333333 | D6: 0.91666667 | E6: Started: Main Screen UI Design & Coding | F6: =D6-C6 -> 0.083333333
B7: 45265 | C7: 0.58333333 | D7: 0.95833333 | E7: Started: Waitlist Component Design & Coding Continued: Main Screen UI Design & Coding | F7: =D7-C7 -> 0.375
B8: 45266 | C8: 0.58333333 | D8: 0.83333333 | E8: Started: Waitlist Request-Bar Component Design and Coding Started: Waitlist Side-Bar Component Design and Coding Continued: Main Screen UI Design and Coding Continued: Waitlist Component Design and Coding | F8: =D8-C8 -> 0.25
B9: 45267 | C9: 0.66666667 | D9: 0.95833333 | E9: Started: Waitlist Side-Bar Component Design and Coding Continued: Waitlist Component Design and Coding Created: This Spreadsheet | F9: =D9-C9 -> 0.29166667
B10: 45269 | C10: 0.66666667 | D10: 0.85416667 | E10: Continued: Coding Waitlist viewer component. | F10: =D10-C10 -> 0.1875
F11: =D11-C11 -> 0
F12: =D12-C12 -> 0
F13: =D13-C13 -> 0
F14: =D14-C14 -> 0
F15: =D15-C15 -> 0
F16: =D16-C16 -> 0
F17: =D17-C17 -> 0
F18: =D18-C18 -> 0
B20: Total time worked: | C20: =SUM(F6:F18) -> 1.1875

Sheet 07) Car Loan Calculator
B2: Period | C2: Date | D2: Monthly Payment | E2: Interest Payment | F2: Principal Payment | G2: Loan Balance | I2: Principal amount | J2: Interest Rate
B3: 0 | C3: =J5 -> 44273 | D3: 0 | E3: 0 | F3: 0 | G3: =I3 -> 13424.38 | I3: 13424.38 | J3: 0.164
B4: =B3+1 -> 1 | C4: =DATE(YEAR(C3),MONTH(C3)+1,Day(C3)) -> 44304 | D4: -298.96 | E4: =IPMT($J$3/12, B4, $I$5*12,$I$3) -> -183.46653 | F4: =D4-E4 -> -115.49347 | G4: =F4+G3 -> 13308.887 | I4: Term (in years) | J4: Starting Date
B5: =B4+1 -> 2 | C5: =DATE(YEAR(C4),MONTH(C4)+1,Day(C4)) -> 44334 | D5: -298.96 | E5: =IPMT($J$3/12, B5, $I$5*12,$I$3) -> -181.95366 | F5: =D5-E5 -> -117.00634 | G5: =F5+G4 -> 13191.88 | I5: 6 | J5: 44273
B6: =B5+1 -> 3 | C6: =DATE(YEAR(C5),MONTH(C5)+1,Day(C5)) -> 44365 | D6: -298.96 | E6: =IPMT($J$3/12, B6, $I$5*12,$I$3) -> -180.42012 | F6: =D6-E6 -> -118.53988 | G6: =F6+G5 -> 13073.34 | I6: Pay More
B7: =B6+1 -> 4 | C7: =DATE(YEAR(C6),MONTH(C6)+1,Day(C6)) -> 44395 | D7: -298.96 | E7: =IPMT($J$3/12, B7, $I$5*12,$I$3) -> -178.86562 | F7: =D7-E7 -> -120.09438 | G7: =F7+G6 -> 12953.246 | I7: 0
B8: =B7+1 -> 5 | C8: =DATE(YEAR(C7),MONTH(C7)+1,Day(C7)) -> 44426 | D8: -298.96 | E8: =IPMT($J$3/12, B8, $I$5*12,$I$3) -> -177.28988 | F8: =D8-E8 -> -121.67012 | G8: =F8+G7 -> 12831.576
B9: =B8+1 -> 6 | C9: =DATE(YEAR(C8),MONTH(C8)+1,Day(C8)) -> 44457 | D9: -298.96 | E9: =IPMT($J$3/12, B9, $I$5*12,$I$3) -> -175.6926 | F9: =D9-E9 -> -123.2674 | G9: =F9+G8 -> 12708.308 | I9: Last Pay Date | J9: 46464
B10: =B9+1 -> 7 | C10: =DATE(YEAR(C9),MONTH(C9)+1,Day(C9)) -> 44487 | D10: -298.96 | E10: =IPMT($J$3/12, B10, $I$5*12,$I$3) -> -174.07349 | F10: =D10-E10 -> -124.88651 | G10: =F10+G9 -> 12583.422 | I10: Months Remaining | J10: =DATEDIF(NOW(), J9,"M") -> 12
B11: =B10+1 -> 8 | C11: =DATE(YEAR(C10),MONTH(C10)+1,Day(C10)) -> 44518 | D11: -298.96 | E11: =IPMT($J$3/12, B11, $I$5*12,$I$3) -> -172.43225 | F11: =D11-E11 -> -126.52775 | G11: =F11+G10 -> 12456.894 | I11: Months Total | J11: =72 -> 72
B12: =B11+1 -> 9 | C12: =DATE(YEAR(C11),MONTH(C11)+1,Day(C11)) -> 44548 | D12: -298.96 | E12: =IPMT($J$3/12, B12, $I$5*12,$I$3) -> -170.76859 | F12: =D12-E12 -> -128.19141 | G12: =F12+G11 -> 12328.703 | I12: Percent Complete | J12: =1 - (DATEDIF(NOW(), J9,"M") / 72) -> 0.83333333
B13: =B12+1 -> 10 | C13: =DATE(YEAR(C12),MONTH(C12)+1,Day(C12)) -> 44579 | D13: -298.96 | E13: =IPMT($J$3/12, B13, $I$5*12,$I$3) -> -169.08218 | F13: =D13-E13 -> -129.87782 | G13: =F13+G12 -> 12198.825
B14: =B13+1 -> 11 | C14: =DATE(YEAR(C13),MONTH(C13)+1,Day(C13)) -> 44610 | D14: -298.96 | E14: =IPMT($J$3/12, B14, $I$5*12,$I$3) -> -167.37273 | F14: =D14-E14 -> -131.58727 | G14: =F14+G13 -> 12067.238
B15: =B14+1 -> 12 | C15: =DATE(YEAR(C14),MONTH(C14)+1,Day(C14)) -> 44638 | D15: -298.96 | E15: =IPMT($J$3/12, B15, $I$5*12,$I$3) -> -165.63992 | F15: =D15-E15 -> -133.32008 | G15: =F15+G14 -> 11933.918
B16: =B15+1 -> 13 | C16: =DATE(YEAR(C15),MONTH(C15)+1,Day(C15)) -> 44669 | D16: -298.96 | E16: =IPMT($J$3/12, B16, $I$5*12,$I$3) -> -163.88342 | F16: =D16-E16 -> -135.07658 | G16: =F16+G15 -> 11798.841
B17: =B16+1 -> 14 | C17: =DATE(YEAR(C16),MONTH(C16)+1,Day(C16)) -> 44699 | D17: -298.96 | E17: =IPMT($J$3/12, B17, $I$5*12,$I$3) -> -162.10292 | F17: =D17-E17 -> -136.85708 | G17: =F17+G16 -> 11661.984
B18: =B17+1 -> 15 | C18: =DATE(YEAR(C17),MONTH(C17)+1,Day(C17)) -> 44730 | D18: -298.96 | E18: =IPMT($J$3/12, B18, $I$5*12,$I$3) -> -160.29809 | F18: =D18-E18 -> -138.66191 | G18: =F18+G17 -> 11523.322
B19: =B18+1 -> 16 | C19: =DATE(YEAR(C18),MONTH(C18)+1,Day(C18)) -> 44760 | D19: -298.96 | E19: =IPMT($J$3/12, B19, $I$5*12,$I$3) -> -158.46859 | F19: =D19-E19 -> -140.49141 | G19: =F19+G18 -> 11382.831
B20: =B19+1 -> 17 | C20: =DATE(YEAR(C19),MONTH(C19)+1,Day(C19)) -> 44791 | D20: -298.96 | E20: =IPMT($J$3/12, B20, $I$5*12,$I$3) -> -156.61409 | F20: =D20-E20 -> -142.34591 | G20: =F20+G19 -> 11240.485
B21: =B20+1 -> 18 | C21: =DATE(YEAR(C20),MONTH(C20)+1,Day(C20)) -> 44822 | D21: -298.96 | E21: =IPMT($J$3/12, B21, $I$5*12,$I$3) -> -154.73424 | F21: =D21-E21 -> -144.22576 | G21: =F21+G20 -> 11096.259
B22: =B21+1 -> 19 | C22: =DATE(YEAR(C21),MONTH(C21)+1,Day(C21)) -> 44852 | D22: -298.96 | E22: =IPMT($J$3/12, B22, $I$5*12,$I$3) -> -152.8287 | F22: =D22-E22 -> -146.1313 | G22: =F22+G21 -> 10950.128
B23: =B22+1 -> 20 | C23: =DATE(YEAR(C22),MONTH(C22)+1,Day(C22)) -> 44883 | D23: -298.96 | E23: =IPMT($J$3/12, B23, $I$5*12,$I$3) -> -150.89712 | F23: =D23-E23 -> -148.06288 | G23: =F23+G22 -> 10802.065
B24: =B23+1 -> 21 | C24: =DATE(YEAR(C23),MONTH(C23)+1,Day(C23)) -> 44913 | D24: -298.96 | E24: =IPMT($J$3/12, B24, $I$5*12,$I$3) -> -148.93914 | F24: =D24-E24 -> -150.02086 | G24: =F24+G23 -> 10652.044
... B35: =B34+1 -> 32 | C35: =DATE(YEAR(C34),MONTH(C34)+1,Day(C34)) -> 45248 | D35: -298.96 | E35: =IPMT($J$3/12, B35, $I$5*12,$I$3) -> -125.55227 | F35: =D35-E35 -> -173.40773 | G35: =F35+G34 -> 8864.6665
B36: =B35+1 -> 33 | C36: =DATE(YEAR(C35),MONTH(C35)+1,Day(C35)) -> 45278 | D36: -298.96 | E36: =IPMT($J$3/12, B36, $I$5*12,$I$3) -> -123.24791 | F36: =D36-E36 -> -175.71209 | G36: 8906.17
B37: =B36+1 -> 34 | C37: =DATE(YEAR(C36),MONTH(C36)+1,Day(C36)) -> 45309 | D37: -298.96 | E37: =IPMT($J$3/12, B37, $I$5*12,$I$3) -> -120.91206 | F37: =D37-E37 -> -178.04794 | G37: =F37+G36 -> 8728.1221
B38: =B37+1 -> 35 | C38: =DATE(YEAR(C37),MONTH(C37)+1,Day(C37)) -> 45340 | D38: -298.96 | E38: =IPMT($J$3/12, B38, $I$5*12,$I$3) -> -118.54428 | F38: =D38-E38 -> -180.41572 | G38: =F38+G37 -> 8547.7063
B39: =B38+1 -> 36 | C39: =DATE(YEAR(C38),MONTH(C38)+1,Day(C38)) -> 45369 | D39: -298.96 | E39: =IPMT($J$3/12, B39, $I$5*12,$I$3) -> -116.14415 | F39: =D39-E39 -> -182.81585 | G39: =F39+G38 -> 8364.8905
B40: =B39+1 -> 37 | C40: =DATE(YEAR(C39),MONTH(C39)+1,Day(C39)) -> 45400 | D40: -298.96 | E40: =IPMT($J$3/12, B40, $I$5*12,$I$3) -> -113.71121 | F40: =D40-E40 -> -185.24879 | G40: =F40+G39 -> 8179.6417
B41: =B40+1 -> 38 | C41: =DATE(YEAR(C40),MONTH(C40)+1,Day(C40)) -> 45430 | D41: -298.96 | E41: =IPMT($J$3/12, B41, $I$5*12,$I$3) -> -111.24502 | F41: =D41-E41 -> -187.71498 | G41: =F41+G40 -> 7991.9267
B42: =B41+1 -> 39 | C42: =DATE(YEAR(C41),MONTH(C41)+1,Day(C41)) -> 45461 | D42: -298.96 | E42: =IPMT($J$3/12, B42, $I$5*12,$I$3) -> -108.74513 | F42: =D42-E42 -> -190.21487 | G42: =F42+G41 -> 7801.7118
B43: =B42+1 -> 40 | C43: =DATE(YEAR(C42),MONTH(C42)+1,Day(C42)) -> 45491 | D43: -298.96 | E43: =IPMT($J$3/12, B43, $I$5*12,$I$3) -> -106.21107 | F43: =D43-E43 -> -192.74893 | G43: =F43+G42 -> 7608.9629
B44: =B43+1 -> 41 | C44: =DATE(YEAR(C43),MONTH(C43)+1,Day(C43)) -> 45522 | D44: -298.96 | E44: =IPMT($J$3/12, B44, $I$5*12,$I$3) -> -103.64238 | F44: =D44-E44 -> -195.31762 | G44: =F44+G43 -> 7413.6453
B45: =B44+1 -> 42 | C45: =DATE(YEAR(C44),MONTH(C44)+1,Day(C44)) -> 45553 | D45: -298.96 | E45: =IPMT($J$3/12, B45, $I$5*12,$I$3) -> -101.03859 | F45: =D45-E45 -> -197.92141 | G45: =F45+G44 -> 7215.7239
B46: =B45+1 -> 43 | C46: =DATE(YEAR(C45),MONTH(C45)+1,Day(C45)) -> 45583 | D46: -298.96 | E46: =IPMT($J$3/12, B46, $I$5*12,$I$3) -> -98.399207 | F46: =D46-E46 -> -200.56079 | G46: =F46+G45 -> 7015.1631
B47: =B46+1 -> 44 | C47: =DATE(YEAR(C46),MONTH(C46)+1,Day(C46)) -> 45614 | D47: -298.96 | E47: =IPMT($J$3/12, B47, $I$5*12,$I$3) -> -95.723756 | F47: =D47-E47 -> -203.23624 | G47: =F47+G46 -> 6811.9268
B48: =B47+1 -> 45 | C48: =DATE(YEAR(C47),MONTH(C47)+1,Day(C47)) -> 45644 | D48: -298.96 | E48: =IPMT($J$3/12, B48, $I$5*12,$I$3) -> -93.01174 | F48: =D48-E48 -> -205.94826 | G48: =F48+G47 -> 6605.9786
... B75: =B74+1 -> 72 | C75: =DATE(YEAR(C74),MONTH(C74)+1,Day(C74)) -> 46464 | D75: -298.96 | E75: =IPMT($J$3/12, B75, $I$5*12,$I$3) -> -3.9660383 | F75: =D75-E75 -> -294.99396 | G75: =F75+G74 -> -128.09929

Sheet 08) Drop Down Menus
A1: Expence Catagories | B1: Shopping Catagories
A2: Groceries | B2: Groceries | D2: Current Time | E2: Current Date
A3: Cigarettes | B3: Living Room | D3: =TEXT(TIME(VALUE(TEXT(NOW(), "H")), VALUE(TEXT(NOW(), "MM")+25), VALUE(TEXT(NOW(), "SS"))), "H:MM AM/PM") -> 5:28 PM | E3: =TEXT(TODAY(), "MM/DD/YYYY") -> 03/12/2026
A4: Gas | B4: Kitchen
A5: Entertainment | B5: Bathroom
A6: Medical | B6: Bedroom
A7: Vehicle | B7: Entertainment
A8: Maintenance | B8: Cleaning Supplies
A9: Debt | B9: Maintenance
A10: Holiday Gifts | B10: Outdoors
A11: Haircut | B11: Vehicle
A12: Subscription - Video | B12: Groceries (Lunch)
A13: Subscription - Game | B13: Cigarettes
A14: Credit Cards | B14: Medical
B15: Other
B16: Office

Sheet 09) Affirm Payoff Schedule
A1: Affirm Payoff Schedule / Phone Number to Call : 1-855-423-3729
B2: Payment | C2: Date | D2: Amount | E2: Remaining | H2: Payment | I2: Date | J2: Amount | K2: Remaining | N2: Affirm | O2: Loan Code | P2: Total Owed | Q2: Percentage
A3: 44951 | B3: WalMart 1 | C3: 44960 | D3: 47.35 | E3: =P3-D3 -> 1088.99 | G3: 45041 | H3: WalMart 1- | I3: =C28+14 -> 45037 | J3: 47.35 | K3: =E28-J3 -> 946.94 | N3: WalMart 1 | O3: 40M4-D7QC | P3: 1136.34 | Q3: =P3/P8 -> 0.34987776
B4: WalMart 2 | C4: 44960 | D4: 47.06 | E4: =P4-D4 -> 1082.28 | H4: WalMart 2- | I4: =C29+14 -> 45037 | J4: 47.06 | K4: =E29-J4 -> 941.1 | N4: WalMart 2 | O4: 3DXV-RNTY | P4: 1129.34 | Q4: =P4/P8 -> 0.34772247
B5: NewEgg | C5: 44960 | D5: 23.61 | E5: =P5-D5 -> 543.04 | H5: NewEgg- | I5: =C30+14 -> 45037 | J5: 23.61 | K5: =E30-J5 -> 472.21 | N5: NewEgg | O5: 4WY1-RWEJ | P5: 566.65 | Q5: =P5/P8 -> 0.17447088
B6: WalMart 3 | C6: 44960 | D6: 6.3 | E6: =P6-D6 -> 144.97 | H6: WalMart 3- | I6: =C31+14 -> 45037 | J6: 6.3 | K6: =E31-J6 -> 126.07 | N6: WalMart 3 | O6: 4BY2-JGPS | P6: 151.27 | Q6: =P6/P8 -> 0.046575857
B7: WalMart 4 | C7: 44960 | D7: 11.01 | E7: =P7-D7 -> 253.21 | H7: WalMart 4- | I7: =C32+14 -> 45037 | J7: 11.01 | K7: =E32-J7 -> 220.18 | N7: WalMart 4 | O7: QUNW-WR5S | P7: 264.22 | Q7: =P7/P8 -> 0.081353031
A8: 44982 | B8: WalMart 1 | C8: 44967 | D8: 47.35 | E8: =E3-D8 -> 1041.64 | G8: 45071 | H8: WalMart 1- | I8: =I3+14 -> 45051 | J8: 47.35 | K8: =K3-J8 -> 899.59 | N8: Total : | P8: =SUM(P3:P7) -> 3247.82
B9: WalMart 2 | C9: 44967 | D9: 47.06 | E9: =E4-D9 -> 1035.22 | H9: WalMart 2- | I9: =I4+14 -> 45051 | J9: 47.06 | K9: =K4-J9 -> 894.04 | N9: Remaining : | P9: =P8-(P8-sum(P22:P26)) -> 2977.1683
B10: NewEgg | C10: 44967 | D10: 23.61 | E10: =E5-D10 -> 519.43 | H10: NewEgg- | I10: =I5+14 -> 45051 | J10: 23.61 | K10: =K5-J10 -> 448.6 | N10: Paid : | P10: =P8-sum(P22:P26) -> 270.65167
B11: WalMart 3 | C11: 44967 | D11: 6.3 | E11: =E6-D11 -> 138.67 | H11: WalMart 3- | I11: =I6+14 -> 45051 | J11: 6.3 | K11: =K6-J11 -> 119.77
B12: WalMart 4 | C12: 44967 | D12: 11.01 | E12: =E7-D12 -> 242.2 | H12: WalMart 4- | I12: =I7+14 -> 45051 | J12: 11.01 | K12: =K7-J12 -> 209.17 | N12: Per Month | P12: Per Paycheck
A13: Skipped | B13: Skipped | G13: 45102 | H13: WalMart 1- | I13: =I8+14 -> 45065 | J13: 47.35 | K13: =K8-J13 -> 852.24 | N13: =N19*Q3 -> 94.695 | P13: =P19*Q3 -> 47.3475
H14: WalMart 2- | I14: =I9+14 -> 45065 | J14: 47.06 | K14: =K9-J14 -> 846.98 | N14: =N19*Q4 -> 94.111667 | P14: =P19*Q4 -> 47.055833
H15: NewEgg- | I15: =I10+14 -> 45065 | J15: 23.61 | K15: =K10-J15 -> 424.99 | N15: =N19*Q5 -> 47.220833 | P15: =P19*Q5 -> 23.610417
H16: WalMart 3- | I16: =I11+14 -> 45065 | J16: 6.3 | K16: =K11-J16 -> 113.47 | N16: =N19*Q6 -> 12.605833 | P16: =P19*Q6 -> 6.3029167
H17: WalMart 4- | I17: =I12+14 -> 45065 | J17: 11.01 | K17: =K12-J17 -> 198.16 | N17: =N19*Q7 -> 22.018333 | P17: =P19*Q7 -> 11.009167
A18: Skipped | B18: Skipped | G18: 45132 | H18: WalMart 1- | I18: =I13+14 -> 45079 | J18: 47.35 | K18: =K13-J18 -> 804.89 | N18: TOTAL
H19: WalMart 2- | I19: =I14+14 -> 45079 | J19: 47.06 | K19: =K14-J19 -> 799.92 | N19: =P8/12 -> 270.65167 | P19: =N19/2 -> 135.32583
H20: NewEgg- | I20: =I15+14 -> 45079 | J20: 23.61 | K20: =K15-J20 -> 401.38
H21: WalMart 3- | I21: =I16+14 -> 45079 | J21: 6.3 | K21: =K16-J21 -> 107.17 | N21: Paid | P21: Remaining
H22: WalMart 4- | I22: =I17+14 -> 45079 | J22: 11.01 | K22: =K17-J22 -> 187.15 | N22: =countif(B$3:B$66,"WalMart 1") -> 2 | P22: =P3-N22*P13 -> 1041.645
A23: Skipped | B23: Skipped | G23: 45163 | H23: WalMart 1- | I23: =I18+14 -> 45093 | J23: 47.35 | K23: =K18-J23 -> 757.54 | N23: =countif(B$3:B$66,"WalMart 2") -> 2 | P23: =P4-N23*P14 -> 1035.2283
H24: WalMart 2- | I24: =I19+14 -> 45093 | J24: 47.06 | K24: =K19-J24 -> 752.86 | N24: =countif(B$3:B$66,"NewEgg") -> 2 | P24: =P5-N24*P15 -> 519.42917
H25: NewEgg- | I25: =I20+14 -> 45093 | J25: 23.61 | K25: =K20-J25 -> 377.77 | N25: =countif(B$3:B$66,"WalMart 3") -> 2 | P25: =P6-N25*P16 -> 138.66417
H26: WalMart 3- | I26: =I21+14 -> 45093 | J26: 6.3 | K26: =K21-J26 -> 100.87 | N26: =countif(B$3:B$66,"WalMart 4") -> 2 | P26: =P7-N26*P17 -> 242.20167
H27: WalMart 4- | I27: =I22+14 -> 45093 | J27: 11.01 | K27: =K22-J27 -> 176.14 | N27: ="$" & text(sum(P22:P26),"0.00") & " Remaining" -> $2977.17 Remaining
A28: 45010 | B28: WalMart 1- | C28: 45023 | D28: 47.35 | E28: =E8-D28 -> 994.29 | G28: 45194 | H28: WalMart 1- | I28: =I23+14 -> 45107 | J28: 47.35 | K28: =K23-J28 -> 710.19 | N28: Updated : 02/23/2023
B29: WalMart 2- | C29: 45023 | D29: 47.06 | E29: =E9-D29 -> 988.16 | H29: WalMart 2- | I29: =I24+14 -> 45107 | J29: 47.06 | K29: =K24-J29 -> 705.8
B30: NewEgg- | C30: 45023 | D30: 23.61 | E30: =E10-D30 -> 495.82 | H30: NewEgg- | I30: =I25+14 -> 45107 | J30: 23.61 | K30: =K25-J30 -> 354.16
B31: WalMart 3- | C31: 45023 | D31: 6.3 | E31: =E11-D31 -> 132.37 | H31: WalMart 3- | I31: =I26+14 -> 45107 | J31: 6.3 | K31: =K26-J31 -> 94.57
B32: WalMart 4- | C32: 45023 | D32: 11.01 | E32: =E12-D32 -> 231.19 | H32: WalMart 4- | I32: =I27+14 -> 45107 | J32: 11.01 | K32: =K27-J32 -> 165.13
A34: Affirm Payoff Schedule / Phone Number to Call : 1-855-423-3729
B35: Payment | C35: Date | D35: Amount | E35: Remaining | H35: Payment | I35: Date | J35: Amount | K35: Remaining | N35: Payment | O35: Date | P35: Amount | Q35: Remaining
A36: 45224 | B36: WalMart 1- | C36: =I28+14 -> 45121 | D36: 47.35 | E36: =K28-D36 -> 662.84 | G36: 16/25 | H36: WalMart 1- | I36: =C61+14 -> 45205 | J36: 47.35 | K36: =E61-J36 -> 378.74 | M36: 22/25 | N36: WalMart 1- | O36: =I61+14 -> 45289 | P36: =47.29+0.06 -> 47.35 | Q36: =K61-P36 -> 94.7
B37: WalMart 2- | C37: =I29+14 -> 45121 | D37: 47.06 | E37: =K29-D37 -> 658.74 | H37: WalMart 2- | I37: =C62+14 -> 45205 | J37: 47.06 | K37: =E62-J37 -> 376.38 | N37: WalMart 2- | O37: =I62+14 -> 45289 | P37: =46.96+0.1 -> 47.06 | Q37: =K62-P37 -> 94.12
B38: NewEgg- | C38: =I30+14 -> 45121 | D38: 23.61 | E38: =K30-D38 -> 330.55 | H38: NewEgg- | I38: =C63+14 -> 45205 | J38: 23.61 | K38: =E63-J38 -> 188.89 | N38: NewEgg- | O38: =I63+14 -> 45289 | P38: =23.62-0.01 -> 23.61 | Q38: =K63-P38 -> 47.22
B39: WalMart 3- | C39: =I31+14 -> 45121 | D39: 6.3 | E39: =K31-D39 -> 88.27 | H39: WalMart 3- | I39: =C64+14 -> 45205 | J39: 6.3 | K39: =E64-J39 -> 50.47 | N39: WalMart 3- | O39: =I64+14 -> 45289 | P39: =6.37-0.07 -> 6.3 | Q39: =K64-P39 -> 12.6
B40: WalMart 4- | C40: =I32+14 -> 45121 | D40: 11.01 | E40: =K32-D40 -> 154.12 | H40: WalMart 4- | I40: =C65+14 -> 45205 | J40: 11.01 | K40: =E65-J40 -> 88.06 | N40: WalMart 4- | O40: =I65+14 -> 45289 | P40: =10.99+0.02 -> 11.01 | Q40: =K65-P40 -> 22.02
A41: 45255 | B41: WalMart 1- | C41: =C36+14 -> 45135 | D41: 47.35 | E41: =E36-D41 -> 615.49 | G41: 17/25 | H41: WalMart 1- | I41: =I36+14 -> 45219 | J41: 47.35 | K41: =K36-J41 -> 331.39 | M41: 23/25 | N41: WalMart 1- | O41: =O36+14 -> 45303 | P41: =47.29+0.06 -> 47.35 | Q41: =Q36-P41 -> 47.35
B42: WalMart 2- | C42: =C37+14 -> 45135 | D42: 47.06 | E42: =E37-D42 -> 611.68 | H42: WalMart 2- | I42: =I37+14 -> 45219 | J42: 47.06 | K42: =K37-J42 -> 329.32 | N42: WalMart 2- | O42: =O37+14 -> 45303 | P42: =46.96+0.1 -> 47.06 | Q42: =Q37-P42 -> 47.06
B43: NewEgg- | C43: =C38+14 -> 45135 | D43: 23.61 | E43: =E38-D43 -> 306.94 | H43: NewEgg- | I43: =I38+14 -> 45219 | J43: 23.61 | K43: =K38-J43 -> 165.28 | N43: NewEgg- | O43: =O38+14 -> 45303 | P43: =23.62-0.01 -> 23.61 | Q43: =Q38-P43 -> 23.61
B44: WalMart 3- | C44: =C39+14 -> 45135 | D44: 6.3 | E44: =E39-D44 -> 81.97 | H44: WalMart 3- | I44: =I39+14 -> 45219 | J44: 6.3 | K44: =K39-J44 -> 44.17 | N44: WalMart 3- | O44: =O39+14 -> 45303 | P44: =6.37-0.07 -> 6.3 | Q44: =Q39-P44 -> 6.3
B45: WalMart 4- | C45: =C40+14 -> 45135 | D45: 11.01 | E45: =E40-D45 -> 143.11 | H45: WalMart 4- | I45: =I40+14 -> 45219 | J45: 11.01 | K45: =K40-J45 -> 77.05 | N45: WalMart 4- | O45: =O40+14 -> 45303 | P45: =10.99+0.02 -> 11.01 | Q45: =Q40-P45 -> 11.01
A46: 45285 | B46: WalMart 1- | C46: =C41+14 -> 45149 | D46: 47.35 | E46: =E41-D46 -> 568.14 | G46: 18/25 | H46: WalMart 1- | I46: =I41+14 -> 45233 | J46: 47.35 | K46: =K41-J46 -> 284.04 | M46: 24/25 | N46: WalMart 1- | O46: =O41+14 -> 45317 | P46: =47.29+0.06 -> 47.35 | Q46: 0
B47: WalMart 2- | C47: =C42+14 -> 45149 | D47: 47.06 | E47: =E42-D47 -> 564.62 | H47: WalMart 2- | I47: =I42+14 -> 45233 | J47: 47.06 | K47: =K42-J47 -> 282.26 | N47: WalMart 2- | O47: =O42+14 -> 45317 | P47: =46.96+0.1 -> 47.06 | Q47: 0
B48: NewEgg- | C48: =C43+14 -> 45149 | D48: 23.61 | E48: =E43-D48 -> 283.33 | H48: NewEgg- | I48: =I43+14 -> 45233 | J48: 23.61 | K48: =K43-J48 -> 141.67 | N48: NewEgg- | O48: =O43+14 -> 45317 | P48: =23.62-0.01 -> 23.61 | Q48: 0
B49: WalMart 3- | C49: =C44+14 -> 45149 | D49: 6.3 | E49: =E44-D49 -> 75.67 | H49: WalMart 3- | I49: =I44+14 -> 45233 | J49: 6.3 | K49: =K44-J49 -> 37.87 | N49: WalMart 3- | O49: =O44+14 -> 45317 | P49: =6.37-0.07 -> 6.3 | Q49: 0
B50: WalMart 4- | C50: =C45+14 -> 45149 | D50: 11.01 | E50: =E45-D50 -> 132.1 | H50: WalMart 4- | I50: =I45+14 -> 45233 | J50: 11.01 | K50: =K45-J50 -> 66.04 | N50: WalMart 4- | O50: =O45+14 -> 45317 | P50: =10.99+0.02 -> 11.01 | Q50: 0
A51: 13/25 | B51: WalMart 1- | C51: =C46+14 -> 45163 | D51: 47.35 | E51: =E46-D51 -> 520.79 | G51: 19/25 | H51: WalMart 1- | I51: =I46+14 -> 45247 | J51: 47.35 | K51: =K46-J51 -> 236.69
B52: WalMart 2- | C52: =C47+14 -> 45163 | D52: 47.06 | E52: =E47-D52 -> 517.56 | H52: WalMart 2- | I52: =I47+14 -> 45247 | J52: 47.06 | K52: =K47-J52 -> 235.2
B53: NewEgg- | C53: =C48+14 -> 45163 | D53: 23.61 | E53: =E48-D53 -> 259.72 | H53: NewEgg- | I53: =I48+14 -> 45247 | J53: 23.61 | K53: =K48-J53 -> 118.06
B54: WalMart 3- | C54: =C49+14 -> 45163 | D54: 6.3 | E54: =E49-D54 -> 69.37 | H54: WalMart 3- | I54: =I49+14 -> 45247 | J54: 6.3 | K54: =K49-J54 -> 31.57
B55: WalMart 4- | C55: =C50+14 -> 45163 | D55: 11.01 | E55: =E50-D55 -> 121.09 | H55: WalMart 4- | I55: =I50+14 -> 45247 | J55: 11.01 | K55: =K50-J55 -> 55.03
A56: 14/25 | B56: WalMart 1- | C56: =C51+14 -> 45177 | D56: 47.35 | E56: =E51-D56 -> 473.44 | G56: 20/25 | H56: WalMart 1- | I56: =I51+14 -> 45261 | J56: 47.35 | K56: =K51-J56 -> 189.34
B57: WalMart 2- | C57: =C52+14 -> 45177 | D57: 47.06 | E57: =E52-D57 -> 470.5 | H57: WalMart 2- | I57: =I52+14 -> 45261 | J57: 47.06 | K57: =K52-J57 -> 188.14
B58: NewEgg- | C58: =C53+14 -> 45177 | D58: 23.61 | E58: =E53-D58 -> 236.11 | H58: NewEgg- | I58: =I53+14 -> 45261 | J58: 23.61 | K58: =K53-J58 -> 94.45
B59: WalMart 3- | C59: =C54+14 -> 45177 | D59: 6.3 | E59: =E54-D59 -> 63.07 | H59: WalMart 3- | I59: =I54+14 -> 45261 | J59: 6.3 | K59: =K54-J59 -> 25.27
B60: WalMart 4- | C60: =C55+14 -> 45177 | D60: 11.01 | E60: =E55-D60 -> 110.08 | H60: WalMart 4- | I60: =I55+14 -> 45261 | J60: 11.01 | K60: =K55-J60 -> 44.02
A61: 15/25 | B61: WalMart 1- | C61: =C56+14 -> 45191 | D61: 47.35 | E61: =E56-D61 -> 426.09 | G61: 21/25 | H61: WalMart 1- | I61: =I56+14 -> 45275 | J61: 47.29 | K61: =K56-J61 -> 142.05
B62: WalMart 2- | C62: =C57+14 -> 45191 | D62: 47.06 | E62: =E57-D62 -> 423.44 | H62: WalMart 2- | I62: =I57+14 -> 45275 | J62: 46.96 | K62: =K57-J62 -> 141.18
B63: NewEgg- | C63: =C58+14 -> 45191 | D63: 23.61 | E63: =E58-D63 -> 212.5 | H63: NewEgg- | I63: =I58+14 -> 45275 | J63: 23.62 | K63: =K58-J63 -> 70.83
B64: WalMart 3- | C64: =C59+14 -> 45191 | D64: 6.3 | E64: =E59-D64 -> 56.77 | H64: WalMart 3- | I64: =I59+14 -> 45275 | J64: 6.37 | K64: =K59-J64 -> 18.9
B65: WalMart 4- | C65: =C60+14 -> 45191 | D65: 11.01 | E65: =E60-D65 -> 99.07 | H65: WalMart 4- | I65: =I60+14 -> 45275 | J65: 10.99 | K65: =K60-J65 -> 33.03

Sheet 10) 2022 BudgetBill Breakdown
B1: Bills | C1: Pay Date | D1: Minimum Due | E1: Remaining / Notes | F1: Check Balance | G1: Checking Balance
A2: TRUE | B2: Paycheck MTM | C2: 44869 | D2: 1193.12 | F2: =D2 -> 1193.12 | G2: =D2+4.33 -> 1197.45
A3: TRUE | B3: Overtime | C3: 44869 | D3: 78.49 | F3: =D3+F2 -> 1271.61 | G3: =G2+D3 -> 1275.94
A4: TRUE | B4: ='2022 Expences - 11042022'!$I$4 -> Groceries | C4: N/A | D4: =-'2022 Expences - 11042022'!$J$4 -> -218.62 | F4: =D4+F3 -> 1052.99 | G4: =G3+D4 -> 1057.32
A5: TRUE | B5: ='2022 Expences - 11042022'!$I$5 -> Cigarettes | C5: N/A | D5: =-'2022 Expences - 11042022'!$J$5 -> -53.43 | F5: =D5+F4 -> 999.56 | G5: =G4+D5 -> 1003.89
A6: TRUE | B6: ='2022 Expences - 11042022'!$I$6 -> Gas | C6: N/A | D6: =-'2022 Expences - 11042022'!$J$6 -> 0 | F6: =D6+F5 -> 999.56 | G6: =G5+D6 -> 1003.89
A7: TRUE | B7: ='2022 Expences - 11042022'!$I$7 -> Entertainment | C7: N/A | D7: =-'2022 Expences - 11042022'!$J$7 -> -20.49 | F7: =D7+F6 -> 979.07 | G7: =G6+D7 -> 983.4
A8: TRUE | B8: ='2022 Expences - 11042022'!$I$8 -> Medical | C8: N/A | D8: =-'2022 Expences - 11042022'!$J$8 -> -5.25 | F8: =D8+F7 -> 973.82 | G8: =G7+D8 -> 978.15
A9: TRUE | B9: ='08) Drop Down Menus'!A8 -> Maintenance | C9: N/A | D9: =-'2022 Expences - 11042022'!J10 -> -155.7 | F9: =F8+D9 -> 818.12 | G9: =G8+D9 -> 822.45
A10: TRUE | B10: ='2022 Expences - 11042022'!$I$9 -> Vehicle | C10: N/A | D10: =-'2022 Expences - 11042022'!$J$9 -> 0 | F10: =F9+D10 -> 818.12 | G10: =G9+D10 -> 822.45
A11: TRUE | B11: Half Rent | C11: 44869 | D11: =-447.5-34.81 -> -482.31 | E11: Rent - 1st Half December + Water | F11: =D11+F10 -> 335.81 | G11: =G10+D11 -> 340.14
A12: TRUE | B12: Car Insurance | C12: 44869 | D12: -64.71 | F12: =D12+F11 -> 271.1 | G12: =G11+D12 -> 275.43
A13: TRUE | B13: US Cellular - Bill | C13: 44869 | D13: =-92.13-29.11+16.84 -> -104.4 | E13: Early Pay | F13: =F12+D13 -> 166.7 | G13: =G12+D13 -> 171.03
A14: TRUE | B14: US Cellular - Phone | C14: 44869 | D14: -46.66 | E14: Payment 23 / 30 | F14: =F13+D14 -> 120.04 | G14: =G13+D14 -> 124.37
A15: TRUE | B15: Renter's Insurance | C15: 44869 | D15: -11.85 | F15: =F14+D15 -> 108.19 | G15: =G14+D15 -> 112.52
A16: TRUE | B16: Above Lending | C16: 44872 | D16: -86.95 | E16: 6511.74 | F16: =F15+D16 -> 21.24 | G16: =G15+D16 -> 25.57
A17: TRUE | B17: Planet Fitness | C17: 44878 | D17: -10 | F17: =F16+D17 -> 11.24 | G17: =G16+D17 -> 15.57
A18: TRUE | B18: Affirm (Walmart - $1336.14) | C18: 44882 | D18: -58.1 | E18: =1336.14+D18 -> 1278.04 | F18: =F17+D18 -> -46.86 | G18: =G17+D18 -> -42.53
A19: TRUE | B19: Affirm (Walmart - $1328.18) | C19: 44882 | D19: -57.74 | E19: =1328.18+D19 -> 1270.44 | F19: =F18+D19 -> -104.6 | G19: =G18+D19 -> -100.27
A20: TRUE | B20: Affirm (Walmart - $264.22) | C20: 44882 | D20: -29.36 | E20: =264.22+D20 -> 234.86 | F20: =F19+D20 -> -133.96 | G20: =G19+D20 -> -129.63
A21: TRUE | B21: Affirm (Walmart - $151.27) | C21: 44882 | D21: -16.81 | E21: =151.27+D21 -> 134.46 | F21: =F20+D21 -> -150.77 | G21: =G20+D21 -> -146.44
B22: 11/04/2022 - 11/17/2022 | E22: Extra Money Left Over : | F22: =G17 -> 15.57
A23: TRUE | B23: Paycheck MTM | C23: 44883 | D23: 1208.58 | F23: =D23 -> 1208.58 | G23: =D23+F22 -> 1224.15
A24: TRUE | B24: Overtime | C24: 44883 | D24: 0 | F24: =D24+F23 -> 1208.58 | G24: =G23+D24 -> 1224.15
A25: TRUE | B25: ='2022 Expences - 11182022'!$I$4 -> Groceries | C25: N/A | D25: =-'2022 Expences - 11182022'!$J$4 -> -106.91 | F25: =D25+F24 -> 1101.67 | G25: =G24+D25 -> 1117.24
A26: TRUE | B26: ='2022 Expences - 11182022'!$I$5 -> Cigarettes | C26: N/A | D26: =-'2022 Expences - 11182022'!$J$5 -> -77.19 | F26: =D26+F25 -> 1024.48 | G26: =G25+D26 -> 1040.05
A27: TRUE | B27: ='2022 Expences - 11182022'!$I$6 -> Gas | C27: N/A | D27: =-'2022 Expences - 11182022'!$J$6 -> -32.8 | F27: =D27+F26 -> 991.68 | G27: =G26+D27 -> 1007.25
A28: TRUE | B28: ='2022 Expences - 11182022'!$I$7 -> Entertainment | C28: N/A | D28: =-'2022 Expences - 11182022'!$J$7 -> -7.24 | F28: =D28+F27 -> 984.44 | G28: =G27+D28 -> 1000.01
A29: TRUE | B29: ='2022 Expences - 11182022'!$I$8 -> Medical | C29: N/A | D29: =-'2022 Expences - 11182022'!$J$8 -> -30 | F29: =D29+F28 -> 954.44 | G29: =G28+D29 -> 970.01
A30: TRUE | B30: ='08) Drop Down Menus'!A8 -> Maintenance | C30: N/A | D30: =-'2022 Expences - 11182022'!J10 -> -23.43 | F30: =D30+F29 -> 931.01 | G30: =G29+D30 -> 946.58
A31: TRUE | B31: ='2022 Expences - 11182022'!$I$9 -> Vehicle | C31: N/A | D31: =-'2022 Expences - 11182022'!$J$9 -> 0 | F31: =D31+F30 -> 931.01 | G31: =G30+D31 -> 946.58
A32: TRUE | B32: Half Rent | C32: 44883 | D32: =-447.5 -> -447.5 | E32: Rent - 2nd Half December | F32: =D32+F31 -> 483.51 | G32: =G31+D32 -> 499.08
A33: TRUE | B33: Car Payment | C33: 44883 | D33: =-315-4.95 -> -319.95 | E33: November Car Payment | F33: =D33+F32 -> 163.56 | G33: =G32+D33 -> 179.13
A34: TRUE | B34: Above Lending | C34: 44886 | D34: -86.95 | E34: 0 | F34: =D34+F33 -> 76.61 | G34: =G33+D34 -> 92.18
A35: TRUE | B35: Credit Cards | C35: 44883 | D35: -29 | F35: =D35+F34 -> 47.61 | G35: =G34+D35 -> 63.18
A36: TRUE | B36: WPS - Gas | C36: 44883 | D36: -62 | F36: =D36+F35 -> -14.39 | G36: =G35+D36 -> 1.18
A37: TRUE | B37: Affirm (NewEgg - $566.65) | C37: 44883 | D37: 0 | E37: 113.34 | F37: =D37+F36 -> -14.39 | G37: =G36+D37 -> 1.18
B38: 11/18/2022 - 12/01/2022 | E38: Extra Money Left Over : | F38: $ 0.18
A39: TRUE | B39: Paycheck MTM | C39: 44897 | D39: =1166.82-D40 -> 1020.84 | F39: =D39 -> 1020.84 | G39: =D39+F38 -> 1021.02
A40: TRUE | B40: Overtime | C40: 44897 | D40: 145.98 | F40: =D40+F39 -> 1166.82 | G40: =G39+D40 -> 1167
A41: TRUE | B41: ='2022 Expences - 12022022'!$I$4 -> Groceries | C41: N/A | D41: =-'2022 Expences - 12022022'!$J$4 -> -232.14 | F41: =D41+F40 -> 934.68 | G41: =G40+D41 -> 934.86
A42: TRUE | B42: ='2022 Expences - 12022022'!$I$5 -> Cigarettes | C42: N/A | D42: =-'2022 Expences - 12022022'!$J$5 -> -38.71 | F42: =D42+F41 -> 895.97 | G42: =G41+D42 -> 896.15
A43: TRUE | B43: ='2022 Expences - 12022022'!$I$6 -> Gas | C43: N/A | D43: =-'2022 Expences - 12022022'!$J$6 -> 0 | F43: =D43+F42 -> 895.97 | G43: =G42+D43 -> 896.15
A44: TRUE | B44: ='2022 Expences - 12022022'!$I$7 -> Entertainment | C44: N/A | D44: =-'2022 Expences - 12022022'!$J$7 -> -14.99 | F44: =D44+F43 -> 880.98 | G44: =G43+D44 -> 881.16
A45: TRUE | B45: ='2022 Expences - 12022022'!$I$8 -> Medical | C45: N/A | D45: =-'2022 Expences - 12022022'!$J$8 -> -15.25 | F45: =D45+F44 -> 865.73 | G45: =G44+D45 -> 865.91
A46: TRUE | B46: ='08) Drop Down Menus'!A8 -> Maintenance | C46: N/A | D46: =-'2022 Expences - 12022022'!J26 -> 0 | F46: =D46+F45 -> 865.73 | G46: =G45+D46 -> 865.91
A47: TRUE | B47: ='2022 Expences - 12022022'!$I$9 -> Vehicle | C47: N/A | D47: =-'2022 Expences - 12022022'!$J$9 -> 0 | F47: =D47+F46 -> 865.73 | G47: =G46+D47 -> 865.91
A48: TRUE | B48: Half Rent | C48: 44897 | D48: =-447.5-24.81 -> -472.31 | E48: Rent - 1st Half January + Water | F48: =D48+F47 -> 393.42 | G48: =G47+D48 -> 393.6
A49: TRUE | B49: Above Lending | C49: 44900 | D49: -86.95 | E49: 6463.17 | F49: =D49+F48 -> 306.47 | G49: =G48+D49 -> 306.65
A50: TRUE | B50: XFinity | C50: 44897 | D50: -74.7 | F50: =D50+F49 -> 231.77 | G50: =G49+D50 -> 231.95
A51: TRUE | B51: Car Insurance | C51: 44897 | D51: -80.01 | F51: =D51+F50 -> 151.76 | G51: =G50+D51 -> 151.94
A52: TRUE | B52: Renter's Insurance | C52: 44897 | D52: -28.18 | F52: =D52+F51 -> 123.58 | G52: =G51+D52 -> 123.76
A53: TRUE | B53: MPU - Electric | C53: 44901 | D53: -60.73 | F53: =D53+F52 -> 62.85 | G53: =G52+D53 -> 63.03
B54: 12/02/2022 - 12/15/2022 | E54: Extra Money Left Over : | F54: =G53 -> 63.03
A55: TRUE | B55: Paycheck MTM | C55: 44911 | D55: =1253.92-D56 -> 1107.94 | F55: =D55 -> 1107.94 | G55: =D55+F54 -> 1170.97
A56: TRUE | B56: Overtime | C56: 44911 | D56: 145.98 | F56: =D56+F55 -> 1253.92 | G56: =G55+D56 -> 1316.95
A57: TRUE | B57: ='2022 Expences - 12162022'!$I$4 -> Groceries | C57: N/A | D57: =-'2022 Expences - 12162022'!$J$4 -> -53.37 | F57: =D57+F56 -> 1200.55 | G57: =G56+D57 -> 1263.58
A58: TRUE | B58: ='2022 Expences - 12162022'!$I$5 -> Cigarettes | C58: N/A | D58: =-'2022 Expences - 12162022'!$J$5 -> -32.76 | F58: =D58+F57 -> 1167.79 | G58: =G57+D58 -> 1230.82
A59: TRUE | B59: ='2022 Expences - 12162022'!$I$6 -> Gas | C59: N/A | D59: =-'2022 Expences - 12162022'!$J$6 -> -23.05 | F59: =D59+F58 -> 1144.74 | G59: =G58+D59 -> 1207.77
A60: TRUE | B60: ='2022 Expences - 12162022'!$I$7 -> Entertainment | C60: N/A | D60: =-'2022 Expences - 12162022'!$J$7 -> -52.49 | F60: =D60+F59 -> 1092.25 | G60: =G59+D60 -> 1155.28
A61: TRUE | B61: ='2022 Expences - 12162022'!$I$8 -> Medical | C61: N/A | D61: =-'2022 Expences - 12162022'!$J$8 -> -9.56 | F61: =D61+F60 -> 1082.69 | G61: =G60+D61 -> 1145.72
A62: TRUE | B62: ='08) Drop Down Menus'!A8 -> Maintenance | C62: N/A | D62: =-'2022 Expences - 12162022'!$J$9 -> 0 | F62: =D62+F61 -> 1082.69 | G62: =G61+D62 -> 1145.72
A63: TRUE | B63: ='2022 Expences - 12162022'!$I$9 -> Vehicle | C63: N/A | D63: =-'2022 Expences - 12162022'!$J$10 -> -8.95 | F63: =D63+F62 -> 1073.74 | G63: =G62+D63 -> 1136.77
A64: TRUE | B64: Half Rent | C64: 44911 | D64: =-447.5 -> -447.5 | E64: Rent - 2nd Half January | F64: =D64+F63 -> 626.24 | G64: =G63+D64 -> 689.27
A65: TRUE | B65: Above Lending | C65: 44914 | D65: -86.95 | E65: 0 | F65: =F64+D65 -> 539.29 | G65: =G64+D65 -> 602.32
A66: TRUE | B66: US Cellular - Bill | C66: 44918 | D66: =-180.45+46.66 -> -133.79 | F66: =F65+D66 -> 405.5 | G66: =G65+D66 -> 468.53
A67: TRUE | B67: US Cellular - Phone | C67: 44918 | D67: -46.66 | E67: Payment 24 / 30 | F67: =D67+F66 -> 358.84 | G67: =G66+D67 -> 421.87
A68: TRUE | B68: Car Payment | C68: 44913 | D68: -315 | E68: December Car Payment | F68: =F67+D68 -> 43.84 | G68: =G67+D68 -> 106.87
A69: TRUE | B69: WPS - Gas | C69: 44917 | D69: -62 | F69: =F68+D69 -> -18.16 | G69: =G68+D69 -> 44.87
A70: TRUE | B70: Credit Cards | C70: 44920 | D70: -29 | E70: 408.4 | F70: =F69+D70 -> -47.16 | G70: =G69+D70 -> 15.87
A71: TRUE | B71: Planet Fitness | C71: 44912 | D71: -10 | F71: =D71+F70 -> -57.16 | G71: =G70+D71 -> 5.87
B72: 12/16/2022 - 12/29/2022 | E72: Extra Money Left Over : | F72: $ 0.63
A73: TRUE | B73: Paycheck MTM | C73: 44925 | D73: =1145.8-D74 -> 999.82 | F73: =D73 -> 999.82 | G73: =D73+F72 -> 1000.45
A74: TRUE | B74: Overtime | C74: 44925 | D74: 145.98 | F74: =D74+F73 -> 1145.8 | G74: 1146.43
A75: TRUE | B75: ='08) Drop Down Menus'!$A$2 -> Groceries | C75: N/A | D75: =-'2022 Expences - 12302022'!$J$4 -> -296.55 | F75: =D75+F74 -> 849.25 | G75: =G74+D75 -> 849.88
A76: TRUE | B76: ='08) Drop Down Menus'!$A$3 -> Cigarettes | C76: N/A | D76: =-'2022 Expences - 12302022'!$J$5 -> -45.49 | F76: =D76+F75 -> 803.76 | G76: =G75+D76 -> 804.39
A77: TRUE | B77: ='08) Drop Down Menus'!$A$4 -> Gas | C77: N/A | D77: =-'2022 Expences - 12302022'!$J$6 -> -53.57 | F77: =D77+F76 -> 750.19 | G77: =G76+D77 -> 750.82
A78: TRUE | B78: ='08) Drop Down Menus'!$A$5 -> Entertainment | C78: N/A | D78: =-'2022 Expences - 12302022'!$J$7 -> -227.38 | F78: =D78+F77 -> 522.81 | G78: =G77+D78 -> 523.44
A79: TRUE | B79: ='08) Drop Down Menus'!$A$6 -> Medical | C79: N/A | D79: =-'2022 Expences - 12302022'!$J$8 -> -35.25 | F79: =D79+F78 -> 487.56 | G79: =G78+D79 -> 488.19
A80: TRUE | B80: ='08) Drop Down Menus'!$A$7 -> Vehicle | C80: N/A | D80: =-'2022 Expences - 12302022'!$J$9 -> -12 | F80: =D80+F79 -> 475.56 | G80: =G79+D80 -> 476.19
A81: TRUE | B81: ='08) Drop Down Menus'!$A$8 -> Maintenance | C81: N/A | D81: =-'2022 Expences - 12302022'!$J$10 -> -18.1 | F81: =D81+F80 -> 457.46 | G81: =G80+D81 -> 458.09
A82: TRUE | B82: Rent Paid - Just Water | C82: 44929 | D82: -42.61 | F82: =F81+D82 -> 414.85 | G82: =G81+D82 -> 415.48
A83: TRUE | B83: Above Lending | C83: 44929 | D83: -86.95 | F83: =F82+D83 -> 327.9 | G83: =G82+D83 -> 328.53
A84: TRUE | B84: Subscription - Video | C84: 44927 | D84: -15.04 | F84: =F83+D84 -> 312.86 | G84: =G83+D84 -> 313.49
A85: TRUE | B85: XFinity | C85: 44925 | D85: -84.33 | F85: =F84+D85 -> 228.53 | G85: =G84+D85 -> 229.16
A86: TRUE | B86: Car Insurance | C86: 44925 | D86: -80.05 | F86: =D86+F85 -> 148.48 | G86: =G85+D86 -> 149.11
A87: TRUE | B87: Renter's Insurance | C87: 44925 | D87: -19.09 | F87: =F86+D87 -> 129.39 | G87: =G86+D87 -> 130.02
A88: TRUE | B88: MPU - Electric | C88: 44925 | D88: -47.58 | F88: =D88+F87 -> 81.81 | G88: =G87+D88 -> 82.44
B89: 12/30/2022 - 1/13/2022 | E89: Extra Money Left Over : | F89: =G88 -> 82.44

Sheet 11) 2023 BudgetBill Breakdown
B1: Bill | C1: Description | D1: Withdrawl Date | E1: Withdrawl Date | F1: Minimum Due | G1: Check Balance | H1: Checking Balance
B2: Income: Paycheck | C2: RECIEVED | D2: 44939 | E2: 44939 | F2: 1052.15 | G2: =F2 -> 1052.15 | H2: ='10) 2022 BudgetBill Breakdown'!F89+G2 -> 1134.59
B3: Groceries | F3: =-'2023 Expences - 01132023'!$J$4 -> -27.14 | G3: =G2+F3 -> 1025.01 | H3: =H2+F3 -> 1107.45
B4: Cigarettes | F4: =-'2023 Expences - 01132023'!$J$5 -> -23.15 | G4: =G3+F4 -> 1001.86 | H4: =H3+F4 -> 1084.3
B5: Gas | F5: =-'2023 Expences - 01132023'!$J$6 -> 0 | G5: =G4+F5 -> 1001.86 | H5: =H4+F5 -> 1084.3
B6: Entertainment | F6: =-'2023 Expences - 01132023'!$J$7 -> -5.76 | G6: =G5+F6 -> 996.1 | H6: =H5+F6 -> 1078.54
B7: Medical | C7: Vyvanse / Prozasin Refills | F7: =-'2023 Expences - 01132023'!$J$8 -> 0 | G7: =G6+F7 -> 996.1 | H7: =H6+F7 -> 1078.54
B8: Vehicle | C8: Oil Change | F8: =-'2023 Expences - 01132023'!$J$9 -> -216.68 | G8: =G7+F8 -> 779.42 | H8: =H7+F8 -> 861.86
B9: Maintenance | C9: Phone Screen Repair | F9: =-'2023 Expences - 01132023'!$J$10 -> -26.26 | G9: =G8+F9 -> 753.16 | H9: =H8+F9 -> 835.6
B10: Above Lending | D10: 44943 | E10: 44943 | F10: -86.96 | G10: =G9+F10 -> 666.2 | H10: =H9+F10 -> 748.64
B11: Planet Fitness | D11: 44943 | E11: 44943 | F11: -10 | G11: =G10+F11 -> 656.2 | H11: =H10+F11 -> 738.64
B12: Car Payment | C12: Half January Payment | D12: 44943 | E12: 44943 | F12: =-315/2 -> -157.5 | G12: =G11+F12 -> 498.7 | H12: =H11+F12 -> 581.14
B13: WPS (Gas Bill) | D13: 44943 | E13: 44943 | F13: -62 | G13: =G12+F13 -> 436.7 | H13: =H12+F13 -> 519.14
B14: US Cellular | C14: Half January Payment | D14: 44940 | E14: 44940 | F14: =-161.57/2 -> -80.785 | G14: =G13+F14 -> 355.915 | H14: =H13+F14 -> 438.355
B15: Credit Cards | D15: 44943 | E15: 44943 | F15: -30 | G15: =G14+F15 -> 325.915 | H15: =H14+F15 -> 408.355
B16: 1/13/2023 - 1/26/2023 | C16: Extra Money Left Over : | H16: =H15+F16 -> 408.355
B17: Income: Paycheck | C17: RECIEVED | D17: =D2+14 -> 44953 | E17: =E2+14 -> 44953 | F17: 1305.26 | G17: =F17 -> 1305.26 | H17: 1456.93
B18: Tax Return (State) | C18: State Tax Return | D18: =D2+21 -> 44960 | E18: =E2+21 -> 44960 | F18: 504 | G18: =G17+F18 -> 1809.26 | H18: =H17+F18 -> 1960.93
B19: Groceries | F19: =-'2023 Expences - 01272023'!$K$3 -> -179.3 | G19: =G18+F19 -> 1629.96 | H19: =H18+F19 -> 1781.63
B20: Cigarettes | F20: =-'2023 Expences - 01272023'!$K$4 -> -29.38 | G20: =G19+F20 -> 1600.58 | H20: =H19+F20 -> 1752.25
B21: Gas | F21: =-'2023 Expences - 01272023'!$K$5 -> -67.87 | G21: =G20+F21 -> 1532.71 | H21: =H20+F21 -> 1684.38
B22: Entertainment | F22: =-'2023 Expences - 01272023'!$K$6 -> -10.49 | G22: =G21+F22 -> 1522.22 | H22: =H21+F22 -> 1673.89
B23: Medical | F23: =-'2023 Expences - 01272023'!$K$7 -> 0 | G23: =G22+F23 -> 1522.22 | H23: =H22+F23 -> 1673.89
B24: Vehicle | F24: =-'2023 Expences - 01272023'!$K$8 -> -12 | G24: =G23+F24 -> 1510.22 | H24: =H23+F24 -> 1661.89
B25: Maintenance | F25: =-'2023 Expences - 01272023'!$K$9 -> 0 | G25: =G24+F25 -> 1510.22 | H25: =H24+F25 -> 1661.89
B26: Debt | C26: Affirm Payments | F26: =-'2023 Expences - 01272023'!$K$10 -> -135.35 | G26: =G25+F26 -> 1374.87 | H26: =H25+F26 -> 1526.54
B27: Rent | D27: 44953 | E27: 44953 | F27: -923.1 | G27: =G26+F27 -> 451.77 | H27: =H26+F27 -> 603.44
B28: Car Payment | C28: 2nd Half January Payment | D28: 44954 | E28: 44954 | F28: =-315/2 -> -157.5 | G28: =G27+F28 -> 294.27 | H28: =H27+F28 -> 445.94
B29: XFinity | D29: 44954 | E29: 44954 | F29: -75.75 | G29: =G28+F29 -> 218.52 | H29: =H28+F29 -> 370.19
B30: US Cellular | C30: 2nd Half January Payment | D30: 44954 | E30: 44954 | F30: -67.44 | G30: =G29+F30 -> 151.08 | H30: =H29+F30 -> 302.75
B31: Car Insurance | D31: 44954 | E31: 44954 | F31: -60.95 | G31: =G30+F31 -> 90.13 | H31: =H30+F31 -> 241.8
B32: Renter's Insurance | D32: 44954 | E32: 44954 | F32: -13.65 | G32: =G31+F32 -> 76.48 | H32: =H31+F32 -> 228.15
B33: Above Lending | D33: 44956 | E33: 44956 | F33: -86.95 | G33: =G32+F33 -> -10.47 | H33: =H32+F33 -> 141.2
B34: Subscription - Video | C34: (Includes HIDive Sub) | D34: 44957 | E34: 44957 | F34: -20.28 | G34: =G33+F34 -> -30.75 | H34: =H33+F34 -> 120.92
B35: Subscription - Game | D35: 44963 | E35: 44963 | F35: -14.99 | G35: =G34+F35 -> -45.74 | H35: =H34+F35 -> 105.93
B36: 1/27/2023 - 2/09/2023 | C36: Extra Money Left Over : | H36: =H35 -> 105.93
B37: Income: Paycheck | C37: RECIEVED | D37: =D17+14 -> 44967 | E37: =E17+14 -> 44967 | F37: 1477.33 | G37: =F37 -> 1477.33 | H37: 1583.08
B38: Groceries | F38: =-'2023 Expences - 02102023'!$K$3 -> -232.71 | G38: =G37+F38 -> 1244.62 | H38: =H37+F38 -> 1350.37
B39: Cigarettes | F39: =-'2023 Expences - 02102023'!$K$4 -> -46.81 | G39: =G38+F39 -> 1197.81 | H39: =H38+F39 -> 1303.56
B40: Gas | F40: =-'2023 Expences - 02102023'!$K$5 -> 0 | G40: =G39+F40 -> 1197.81 | H40: =H39+F40 -> 1303.56
B41: Entertainment | F41: =-'2023 Expences - 02102023'!$K$6 -> -262.06 | G41: =G40+F41 -> 935.75 | H41: =H40+F41 -> 1041.5
B42: Medical | F42: =-'2023 Expences - 02102023'!$K$7 -> -10 | G42: =G41+F42 -> 925.75 | H42: =H41+F42 -> 1031.5
B43: Vehicle | C43: Oil Change / Cabin Filter / Engine Cleaning | F43: =-'2023 Expences - 02102023'!$K$8 -> -103.47 | G43: =G42+F43 -> 822.28 | H43: =H42+F43 -> 928.03
B44: Maintenance | F44: =-'2023 Expences - 02102023'!$K$9 -> -59.94 | G44: =G43+F44 -> 762.34 | H44: =H43+F44 -> 868.09
B45: Debt | C45: Affirm Payments | F45: =-'2023 Expences - 02102023'!$K$10 -> -144.3 | G45: =G44+F45 -> 618.04 | H45: =H44+F45 -> 723.79
B46: Car Payment | D46: 44968 | E46: 44968 | F46: =-298.96-4.95 -> -303.91 | G46: =G45+F46 -> 314.13 | H46: =H45+F46 -> 419.88
B47: US Cellular | D47: 44968 | E47: 44968 | F47: -171.7 | G47: =G46+F47 -> 142.43 | H47: =H46+F47 -> 248.18
B48: MPU (Electric Bill) | D48: 44968 | E48: 44968 | F48: -57.61 | G48: =G47+F48 -> 84.82 | H48: =H47+F48 -> 190.57
B49: Above Lending | D49: 44971 | E49: 44971 | F49: -86.95 | G49: =G48+F49 -> -2.13 | H49: =H48+F49 -> 103.62
B50: WPS (Gas Bill) | D50: 44971 | E50: 44971 | F50: -62 | G50: =G49+F50 -> -64.13 | H50: =H49+F50 -> 41.62
B51: Credit Cards | D51: 44971 | E51: 44971 | F51: -30 | G51: =G50+F51 -> -94.13 | H51: =H50+F51 -> 11.62
B52: Planet Fitness | D52: 44974 | E52: 44974 | F52: -10 | G52: =G51+F52 -> -104.13 | H52: =H51+F52 -> 1.62
B53: 2/10/2023 - 2/23/2023 | C53: Extra Money Left Over : | H53: =H52 -> 1.62
B54: Income: Paycheck | C54: RECIEVED | D54: =D37+14 -> 44981 | E54: =E37+14 -> 44981 | F54: 1415.1 | G54: =F54 -> 1415.1 | H54: =H52+G54 -> 1416.72
B55: Groceries | F55: =-'2023 Expences - 02242023'!$K$3 -> -118.08 | G55: =G54+F55 -> 1297.02 | H55: =H54+F55 -> 1298.64
B56: Cigarettes | F56: =-'2023 Expences - 02242023'!$K$4 -> -58.85 | G56: =G55+F56 -> 1238.17 | H56: =H55+F56 -> 1239.79
B57: Gas | F57: =-'2023 Expences - 02242023'!$K$5 -> -34.4 | G57: =G56+F57 -> 1203.77 | H57: =H56+F57 -> 1205.39
B58: Entertainment | F58: =-'2023 Expences - 02242023'!$K$6 -> -4.95 | G58: =G57+F58 -> 1198.82 | H58: =H57+F58 -> 1200.44
B59: Medical | F59: =-'2023 Expences - 02242023'!$K$7 -> -40 | G59: =G58+F59 -> 1158.82 | H59: =H58+F59 -> 1160.44
B60: Vehicle | F60: =-'2023 Expences - 02242023'!$K$8 -> 0 | G60: =G59+F60 -> 1158.82 | H60: =H59+F60 -> 1160.44
B61: Maintenance | F61: =-'2023 Expences - 02242023'!$K$9 -> -12.09 | G61: =G60+F61 -> 1146.73 | H61: =H60+F61 -> 1148.35
B62: Debt | C62: Affirm Payments (Skip) | F62: =-'2023 Expences - 02242023'!$K$10 -> 0 | G62: =G61+F62 -> 1146.73 | H62: =H61+F62 -> 1148.35
B63: Renter's Insurance | D63: 44981 | E63: 44981 | F63: -13.65 | G63: =G62+F63 -> 1133.08 | H63: =H62+F63 -> 1134.7
B64: ='03) Current YTD Report'!G$3 -> Rent | C64: Water Included | D64: 44984 | E64: 44984 | F64: -919.54 | G64: =G63+F64 -> 213.54 | H64: =H63+F64 -> 215.16
B65: Above Lending | D65: 44984 | E65: 44984 | F65: -86.95 | G65: =G64+F65 -> 126.59 | H65: =H64+F65 -> 128.21
B66: Subscription - Video | D66: 44986 | E66: 44986 | F66: -15.04 | G66: =G65+F66 -> 111.55 | H66: =H65+F66 -> 113.17
B67: 2/24/2023 - 3/09/2023 | C67: Extra Money Left Over : | H67: $ 2.15
B68: Income: Paycheck | C68: RECIEVED | D68: =D54+14 -> 44995 | E68: =E54+14 -> 44995 | F68: 1262.28 | G68: =F68 -> 1262.28 | H68: =H67+F68 -> 1264.43
B69: Groceries | F69: =-'2023 Expences - 03102023'!$K$3 -> -128.92 | G69: =G68+F69 -> 1133.36 | H69: =H68+F69 -> 1135.51
B70: Cigarettes | F70: =-'2023 Expences - 03102023'!$K$4 -> -46.85 | G70: =G69+F70 -> 1086.51 | H70: =H69+F70 -> 1088.66
B71: Gas | F71: =-'2023 Expences - 03102023'!$K$5 -> -26.24 | G71: =G70+F71 -> 1060.27 | H71: =H70+F71 -> 1062.42
B72: Entertainment | F72: =-'2023 Expences - 03102023'!$K$6 -> -30.89 | G72: =G71+F72 -> 1029.38 | H72: =H71+F72 -> 1031.53
B73: Medical | F73: =-'2023 Expences - 03102023'!$K$7 -> 0 | G73: =G72+F73 -> 1029.38 | H73: =H72+F73 -> 1031.53
B74: Vehicle | F74: =-'2023 Expences - 03102023'!$K$8 -> 0 | G74: =G73+F74 -> 1029.38 | H74: =H73+F74 -> 1031.53
B75: Maintenance | F75: =-'2023 Expences - 03102023'!$K$9 -> 0 | G75: =G74+F75 -> 1029.38 | H75: =H74+F75 -> 1031.53
B76: Debt | F76: =-'2023 Expences - 03102023'!$K$10 -> -8.95 | G76: =G75+F76 -> 1020.43 | H76: =H75+F76 -> 1022.58
B77: XFinity | D77: 44995 | E77: 44995 | F77: -94.45 | G77: =G76+F77 -> 925.98 | H77: =H76+F77 -> 928.13
B78: Car Insurance | D78: 44995 | E78: 44995 | F78: -60.95 | G78: =G77+F78 -> 865.03 | H78: =H77+F78 -> 867.18
B79: MPU (Electric Bill) | D79: 44995 | E79: 44995 | F79: -52.58 | G79: =G78+F79 -> 812.45 | H79: =H78+F79 -> 814.6
B80: US Cellular | D80: 44997 | E80: 44997 | F80: -238.14 | G80: =G79+F80 -> 574.31 | H80: =H79+F80 -> 576.46
B81: Car Payment | D81: 44999 | E81: 44999 | F81: -298.96 | G81: =G80+F81 -> 275.35 | H81: =H80+F81 -> 277.5
B82: Above Lending | D82: 44999 | E82: 44999 | F82: -86.95 | G82: =G81+F82 -> 188.4 | H82: =H81+F82 -> 190.55
B83: WPS (Gas Bill) | D83: 44999 | E83: 44999 | F83: -62 | G83: =G82+F83 -> 126.4 | H83: =H82+F83 -> 128.55
B84: Credit Cards | D84: 44999 | E84: 44999 | F84: -29 | G84: =G83+F84 -> 97.4 | H84: =H83+F84 -> 99.55
B85: Planet Fitness | D85: 45002 | E85: 45002 | F85: -10 | G85: =G84+F85 -> 87.4 | H85: =H84+F85 -> 89.55
B86: 3/10/2023 - 3/23/2023 | C86: Extra Money Left Over : | H86: =H85+F86 -> 89.55
B87: Income: Paycheck | C87: RECIEVED | D87: =D68+14 -> 45009 | E87: =E68+14 -> 45009 | F87: 1462.86 | G87: =F87 -> 1462.86 | H87: =H85+G87 -> 1552.41
B88: Groceries | F88: =-'2023 Expences - 03242023'!K3 -> -195.9 | G88: =G87+F88 -> 1266.96 | H88: =H87+F88 -> 1356.51
B89: Cigarettes | F89: =-'2023 Expences - 03242023'!K4 -> -58.64 | G89: =G88+F89 -> 1208.32 | H89: =H88+F89 -> 1297.87
B90: Gas | F90: =-'2023 Expences - 03242023'!K5 -> -33.88 | G90: =G89+F90 -> 1174.44 | H90: =H89+F90 -> 1263.99
B91: Entertainment | F91: =-'2023 Expences - 03242023'!K6 -> -4.95 | G91: =G90+F91 -> 1169.49 | H91: =H90+F91 -> 1259.04
B92: Medical | F92: =-'2023 Expences - 03242023'!K7 -> -70 | G92: =G91+F92 -> 1099.49 | H92: =H91+F92 -> 1189.04
B93: Vehicle | F93: =-'2023 Expences - 03242023'!K8 -> 0 | G93: =G92+F93 -> 1099.49 | H93: =H92+F93 -> 1189.04
B94: Maintenance | F94: =-'2023 Expences - 03242023'!K9 -> 0 | G94: =G93+F94 -> 1099.49 | H94: =H93+F94 -> 1189.04
B95: Debt | F95: =-'2023 Expences - 03242023'!K10 -> 0 | G95: =G94+F95 -> 1099.49 | H95: =H94+F95 -> 1189.04
B96: XFinity | D96: 45011 | E96: 45011 | F96: -85.75 | G96: =G95+F96 -> 1013.74 | H96: =H95+F96 -> 1103.29
B97: MPU (Electric Bill) | D97: 45011 | E97: 45011 | F97: -62.35 | G97: =G96+F97 -> 951.39 | H97: =H96+F97 -> 1040.94
B98: ='03) Current YTD Report'!G$3 -> Rent | C98: Includes $52.52 Water Bill | D98: 45012 | E98: 45012 | F98: -947.52 | G98: =G97+F98 -> 3.87 | H98: =H97+F98 -> 93.42
B99: Above Lending | D99: 45013 | E99: 45013 | F99: -86.95 | G99: =G98+F99 -> -83.08 | H99: =H98+F99 -> 6.47
B100: Subscription - Video | D100: 45016 | E100: 45016 | F100: 0 | G100: =G99+F100 -> -83.08 | H100: =H99+F100 -> 6.47
...

Sheet 11) 2023 YTD Report
J1: DROPDOWN
B2: Income | C2: 2023 YTD Amount | G2: US Cellular | H2: =-I$2/C$33 -> 0.059075708 | I2: =SUMIF('11) 2023 BudgetBill Breakdown'!B$1:B37,J$5, '11) 2023 BudgetBill Breakdown'!F$1:F37) -> -2092.715 | J2: Income: Paycheck
B3: Income: Paycheck | C3: =SUMIF('11) 2023 BudgetBill Breakdown'!B1:B37,B3, '11) 2023 BudgetBill Breakdown'!F1:F37) -> 33987.69 | G3: =J$6 -> Rent | H3: =-I$3/C$33 -> 0.31436989 | I3: =SUMIF('11) 2023 BudgetBill Breakdown'!B$1:B37,"Rent", '11) 2023 BudgetBill Breakdown'!F$1:F37) -> -11136.33 | J3: Tax Return (State)
B4: Tax Return (State) | C4: =SUMIF('11) 2023 BudgetBill Breakdown'!B$1:B37,B4, '11) 2023 BudgetBill Breakdown'!F$1:F37) -> 504 | G4: ='08) Drop Down Menus'!$A$2 -> Groceries | H4: =-I$4/C$33 -> 0.14468208 | I4: =SUMIF('11) 2023 BudgetBill Breakdown'!B$1:B37,J$7, '11) 2023 BudgetBill Breakdown'!F$1:F37) -> -5125.26 | J4: Beyond Finance Return
B5: Beyond Finance Return | C5: =SUMIF('11) 2023 BudgetBill Breakdown'!B$1:B37,B5, '11) 2023 BudgetBill Breakdown'!F$1:F37) -> 932.6 | G5: ='08) Drop Down Menus'!$A$3 -> Cigarettes | H5: =-I$5/C$33 -> 0.036822192 | I5: =SUMIF('11) 2023 BudgetBill Breakdown'!B$1:B37,J$8, '11) 2023 BudgetBill Breakdown'!F$1:F37) -> -1304.4 | J5: US Cellular
G6: ='08) Drop Down Menus'!$A$4 -> Gas | H6: =-I$6/C$33 -> 0.014090614 | I6: =SUMIF('11) 2023 BudgetBill Breakdown'!B$1:B37,J$9, '11) 2023 BudgetBill Breakdown'!F$1:F37) -> -499.15 | J6: Rent
B7: Expence | C7: YTD Cost | D7: Percentile | E7: Monthly Avg. | G7: ='08) Drop Down Menus'!$A$5 -> Entertainment | H7: =-I$7/C$33 -> 0.024633945 | I7: =SUMIF('11) 2023 BudgetBill Breakdown'!B$1:B37,J$10, '11) 2023 BudgetBill Breakdown'!F$1:F37) -> -872.64 | J7: Groceries
B8: =G$3 -> Rent | C8: =I$3 -> -11136.33 | D8: =H$3 -> 0.31436989 | E8: =C8/H$26 -> -3287.8689 | G8: ='08) Drop Down Menus'!$A$6 -> Medical | H8: =-I$8/C$33 -> 0.020695404 | I8: =SUMIF('11) 2023 BudgetBill Breakdown'!B$1:B37,J$11, '11) 2023 BudgetBill Breakdown'!F$1:F37) -> -733.12 | J8: Cigarettes
B9: =G$4 -> Groceries | C9: =I$4 -> -5125.26 | D9: =H$4 -> 0.14468208 | E9: =C9/H$26 -> -1513.172 | G9: ='08) Drop Down Menus'!$A$7 -> Vehicle | H9: =-I$9/C$33 -> 0.014015807 | I9: =SUMIF('11) 2023 BudgetBill Breakdown'!B$1:B37,J$12, '11) 2023 BudgetBill Breakdown'!F$1:F37) -> -496.5 | J9: Gas
B10: =G$13 -> Car Payment | C10: =I$13 -> -3613.46 | D10: =H$13 -> 0.10200515 | E10: =C10/H$26 -> -1066.831 | G10: ='08) Drop Down Menus'!$A$8 -> Maintenance | H10: =-I$10/C$33 -> 0.028747789 | I10: =SUMIF('11) 2023 BudgetBill Breakdown'!B$1:B37,J$13, '11) 2023 BudgetBill Breakdown'!F$1:F37) -> -1018.37 | J10: Entertainment
B11: =G$11 -> Above Lending | C11: =I$11 -> -2262.41 | D11: =H$11 -> 0.063866065 | E11: =C11/H$26 -> -667.94962 | G11: Above Lending | H11: =-I$11/C$33 -> 0.063866065 | I11: =SUMIF('11) 2023 BudgetBill Breakdown'!B$1:B37,J$14, '11) 2023 BudgetBill Breakdown'!F$1:F37) -> -2262.41 | J11: Medical
B12: =G$2 -> US Cellular | C12: =I$2 -> -2092.715 | D12: =H$2 -> 0.059075708 | E12: =C12/H$26 -> -617.84919 | G12: Planet Fitness | H12: =-I$12/C$33 -> 0.0035026814 | I12: =SUMIF('11) 2023 BudgetBill Breakdown'!B$1:B37,J$15, '11) 2023 BudgetBill Breakdown'!F$1:F37) -> -124.08 | J12: Vehicle
B13: =G$5 -> Cigarettes | C13: =I$5 -> -1304.4 | D13: =H$5 -> 0.036822192 | E13: =C13/H$26 -> -385.10857 | G13: Car Payment | H13: =-I$13/C$33 -> 0.10200515 | I13: =SUMIF('11) 2023 BudgetBill Breakdown'!B$1:B37,J$16, '11) 2023 BudgetBill Breakdown'!F$1:F37) -> -3613.46 | J13: Maintenance
B14: =G$10 -> Maintenance | C14: =I$10 -> -1018.37 | D14: =H$10 -> 0.028747789 | E14: =C14/H$26 -> -300.66162 | G14: WPS (Gas Bill) | H14: =-I$14/C$33 -> 0.022413999 | I14: =SUMIF('11) 2023 BudgetBill Breakdown'!B$1:B37,J$17, '11) 2023 BudgetBill Breakdown'!F$1:F37) -> -794 | J14: Above Lending
B15: =G$21 -> MPU (Electric Bill) | C15: =I$21 -> -968.24 | D15: =H$21 -> 0.027332658 | E15: =C15/H$26 -> -285.86133 | G15: Credit Cards | H15: =-I$15/C$33 -> 0.018444971 | I15: =SUMIF('11) 2023 BudgetBill Breakdown'!B$1:B37,J$18, '11) 2023 BudgetBill Breakdown'!F$1:F37) -> -653.4 | J15: Planet Fitness
B16: =G$16 -> XFinity | C16: =I$16 -> -958.04 | D16: =H$16 -> 0.02704472 | E16: =C16/H$26 -> -282.8499 | G16: XFinity | H16: =-I$16/C$33 -> 0.02704472 | I16: =SUMIF('11) 2023 BudgetBill Breakdown'!B$1:B37,J$19, '11) 2023 BudgetBill Breakdown'!F$1:F37) -> -958.04 | J16: Car Payment
B17: =G$7 -> Entertainment | C17: =I$7 -> -872.64 | D17: =H$7 -> 0.024633945 | E17: =C17/H$26 -> -257.63657 | G17: Car Insurance | H17: =-I$17/C$33 -> 0.022695444 | I17: =SUMIF('11) 2023 BudgetBill Breakdown'!B$1:B37,J$20, '11) 2023 BudgetBill Breakdown'!F$1:F37) -> -803.97 | J17: WPS (Gas Bill)
B18: =G$17 -> Car Insurance | C18: =I$17 -> -803.97 | D18: =H$17 -> 0.022695444 | E18: =C18/H$26 -> -237.36257 | G18: Renter's Insurance | H18: =-I$18/C$33 -> 0.0044209778 | I18: =SUMIF('11) 2023 BudgetBill Breakdown'!B$1:B37,J$21, '11) 2023 BudgetBill Breakdown'!F$1:F37) -> -156.61 | J18: Credit Cards
B19: =G$14 -> WPS (Gas Bill) | C19: =I$14 -> -794 | D19: =H$14 -> 0.022413999 | E19: =C19/H$26 -> -234.41905 | G19: Subscription - Video | H19: =-I$19/C$33 -> 0.0037242807 | I19: =SUMIF('11) 2023 BudgetBill Breakdown'!B$1:B37,J$22, '11) 2023 BudgetBill Breakdown'!F$1:F37) -> -131.93 | J19: XFinity
B20: =G$8 -> Medical | C20: =I$8 -> -733.12 | D20: =H$8 -> 0.020695404 | E20: =C20/H$26 -> -216.44495 | G20: Subscription - Game | H20: =-I$20/C$33 -> 0.0035393793 | I20: =SUMIF('11) 2023 BudgetBill Breakdown'!B$1:B37,J$23, '11) 2023 BudgetBill Breakdown'!F$1:F37) -> -125.38 | J20: Car Insurance
B21: =G$22 -> Debt | C21: =I$22 -> -673.69 | D21: =H$22 -> 0.019017742 | E21: =C21/H$26 -> -198.89895 | G21: MPU (Electric Bill) | H21: =-I$21/C$33 -> 0.027332658 | I21: =SUMIF('11) 2023 BudgetBill Breakdown'!B$1:B37,J$24, '11) 2023 BudgetBill Breakdown'!F$1:F37) -> -968.24 | J21: Renter's Insurance
B22: =G$15 -> Credit Cards | C22: =I$15 -> -653.4 | D22: =H$15 -> 0.018444971 | E22: =C22/H$26 -> -192.90857 | G22: Debt | H22: =-I$22/C$33 -> 0.019017742 | I22: =SUMIF('11) 2023 BudgetBill Breakdown'!B$1:B37,J$25, '11) 2023 BudgetBill Breakdown'!F$1:F37) -> -673.69 | J22: Subscription - Video
B23: =G$9 -> Vehicle | C23: =I$9 -> -496.5 | D23: =H$9 -> 0.014015807 | E23: =C23/H$26 -> -146.58571 | G23: Holiday Gifts | H23: =-I$23/C$33 -> 0.012966527 | I23: =SUMIF('11) 2023 BudgetBill Breakdown'!B$1:B37,J$26, '11) 2023 BudgetBill Breakdown'!F$1:F37) -> -459.33 | J23: Subscription - Game
B24: =G$6 -> Gas | C24: =I$6 -> -499.15 | D24: =H$6 -> 0.014090614 | E24: =C24/H$26 -> -147.3681 | G24: Haircut | H24: =-I$24/C$33 -> 0.00071335234 | I24: =SUMIF('11) 2023 BudgetBill Breakdown'!B$1:B37,J$27, '11) 2023 BudgetBill Breakdown'!F$1:F37) -> -25.27 | J24: MPU (Electric Bill)
B25: Holiday Gifts | C25: =I$23 -> -459.33 | D25: =H$23 -> 0.012966527 | E25: =C25/H$26 -> -135.61171 | J25: Debt
B26: =G$18 -> Renter's Insurance | C26: =I$18 -> -156.61 | D26: =H$18 -> 0.0044209778 | E26: =C26/H$26 -> -46.237238 | G26: Month + Day | H26: =H27+(H28/H30) -> 3.3870968 | J26: Holiday Gifts
B27: =G$20 -> Subscription - Game | C27: =I$20 -> -125.38 | D27: =H$20 -> 0.0035393793 | E27: =C27/H$26 -> -37.016952 | G27: Current Month | H27: =Month(NOW()) -> 3 | J27: Haircut
B28: =G$12 -> Planet Fitness | C28: =I$12 -> -124.08 | D28: =H$12 -> 0.0035026814 | E28: =C28/H$26 -> -36.633143 | G28: Current Day | H28: =DAY(NOW()) -> 12
B29: =G$19 -> Subscription - Video | C29: =I$19 -> -131.93 | D29: =H$19 -> 0.0037242807 | E29: =C29/H$26 -> -38.950762
B30: Haircut | C30: =I$24 -> -25.27 | D30: =H$24 -> 0.00071335234 | E30: =C30/H$26 -> -7.4606667 | G30: Last Day | H30: =DAY(EOMONTH(TODAY(),0)) -> 31
G31: Year | H31: =YEAR(TODAY()) -> 2026
B32: YTD Total Spent | C32: =sum(I2:I22) -> -34543.695
B33: YTD Total Earned | C33: =sum(C3:C5) -> 35424.29
B34: Difference | C34: =C33+C32 -> 880.595
B35: % Profit | C35: =C34/C33 -> 0.024858508
B37: * Paycheck YTD is Gross not Net | E37: ="Report Date : " & $H$27 & "/" & $H$28 & "/" & $H$31 -> Report Date : 3/12/2026

Sheet 2022 Expences - 07292022
B2: Expences for Paycheck 7/29/2022
B3: Expence | E3: Cost | F3: Total | G3: Notes
B4: Walmart | E4: 76.42 | F4: =E4 -> 76.42
E5: 0 | F5: =F4+E5 -> 76.42
E6: 0 | F6: =F5+E6 -> 76.42
E7: 0 | F7: =F6+E7 -> 76.42
E8: 0 | F8: =F7+E8 -> 76.42
E9: 0 | F9: =F8+E9 -> 76.42
E10: 0 | F10: =F9+E10 -> 76.42
E11: 0 | F11: =F10+E11 -> 76.42
E12: 0 | F12: =F11+E12 -> 76.42
E13: 0 | F13: =F12+E13 -> 76.42
E14: 0 | F14: =F13+E14 -> 76.42
E15: 0 | F15: =F14+E15 -> 76.42
E16: 0 | F16: =F15+E16 -> 76.42
... E23: 0 | F23: =F22+E23 -> 76.42
B24: Expence Grand Total | E24: =F22 -> 76.42

Sheet 2022 Expences - 08122022
B2: Expences for Paycheck 8/12/2022
B3: Expence | E3: Cost | F3: Total | G3: Notes
B4: Cash On Hand | E4: 0 | F4: =E4 -> 0
B5: Change On Hand | E5: 0 | F5: =F4+E5 -> 0
B6: Payment for Parent's Back Padio | E6: 0 | F6: =F5+E6 -> 0
B7: Groceries | E7: =86.24+58 -> 144.24 | F7: =F6+E7 -> 144.24
B8: Cigarettes | E8: =19.19+28.54 -> 47.73 | F8: =F7+E8 -> 191.97
B9: Gas | E9: 0 | F9: =F8+E9 -> 191.97
E10: 0 | F10: =F9+E10 -> 191.97
E11: 0 | F11: =F10+E11 -> 191.97
E12: 0 | F12: =F11+E12 -> 191.97
E13: 0 | F13: =F12+E13 -> 191.97
E14: 0 | F14: =F13+E14 -> 191.97
E15: 0 | F15: =F14+E15 -> 191.97
E16: 0 | F16: =F15+E16 -> 191.97
E17: 0 | F17: =F16+E17 -> 191.97
E18: 0 | F18: =F17+E18 -> 191.97
E19: 0 | F19: =F18+E19 -> 191.97
E20: 0 | F20: =F19+E20 -> 191.97
E21: 0 | F21: =F20+E21 -> 191.97
... E23: 0 | F23: =F22+E23 -> 191.97
B24: Total (Not Including Purlple Items) | E24: =F22-SUM(E7:E9) -> 0

Sheet 2022 Expences - 08262022
B2: Expences for Paycheck 8/26/2022
B3: Expence | E3: Cost | F3: Total | G3: Notes
B4: Cash On Hand | E4: 0 | F4: =E4 -> 0
B5: Change On Hand | E5: 0 | F5: =F4+E5 -> 0
B6: Payment for Parent's Back Padio | E6: 0 | F6: =F5+E6 -> 0
B7: Groceries / Other | E7: =3.39+56.27+112.82 -> 172.48 | F7: =F6+E7 -> 172.48 | G7: 1.Harbor Freight ($3.39) 2.Steam ($56.27) 3.Wal-Mart ($112.82)
B8: Cigarettes | E8: 25.07 | F8: =F7+E8 -> 197.55 | G8: 1.Quik Trip ($25.07)
B9: Gas | E9: 7.02 | F9: =F8+E9 -> 204.57 | G9: 1.Quik Trip ($7.02)
E10: 0 | F10: =F9+E10 -> 204.57
E11: 0 | F11: =F10+E11 -> 204.57
E12: 0 | F12: =F11+E12 -> 204.57
E13: 0 | F13: =F12+E13 -> 204.57
E14: 0 | F14: =F13+E14 -> 204.57
E15: 0 | F15: =F14+E15 -> 204.57
E16: 0 | F16: =F15+E16 -> 204.57
E17: 0 | F17: =F16+E17 -> 204.57
E18: 0 | F18: =F17+E18 -> 204.57
E19: 0 | F19: =F18+E19 -> 204.57
E20: 0 | F20: =F19+E20 -> 204.57
E21: 0 | F21: =F20+E21 -> 204.57
... E23: 0 | F23: =F22+E23 -> 204.57
B24: Expence Grand Total | E24: =F23-SUM(E7:E9) -> 0

Sheet 2022 Expences - 09092022
B2: Expences for Paycheck 9/9/2022
B3: Expence | E3: Cost | F3: Total | G3: Notes
B4: Cash On Hand | E4: 0 | F4: =E4 -> 0
B5: Change On Hand | E5: 0 | F5: =F4+E5 -> 0
B6: Payment for Parent's Back Padio | E6: 0 | F6: =F5+E6 -> 0
B7: Gift / Debit Cards On Hand | E7: 0 | F7: =F6+E7 -> 0
B8: Groceries / Other | E8: =50.36+15 -> 65.36 | F8: =F7+E8 -> 65.36
B9: Cigarettes | E9: =29.9+18.99+2.51+28.73 -> 80.13 | F9: =F8+E9 -> 145.49
B10: Gas | E10: 0 | F10: =F9+E10 -> 145.49
E11: 0 | F11: =F10+E11 -> 145.49
E12: 0 | F12: =F11+E12 -> 145.49
E13: 0 | F13: =F12+E13 -> 145.49
E14: 0 | F14: =F13+E14 -> 145.49
E15: 0 | F15: =F14+E15 -> 145.49
E16: 0 | F16: =F15+E16 -> 145.49
E17: 0 | F17: =F16+E17 -> 145.49
E18: 0 | F18: =F17+E18 -> 145.49
E19: 0 | F19: =F18+E19 -> 145.49
E20: 0 | F20: =F19+E20 -> 145.49
E21: 0 | F21: =F20+E21 -> 145.49
E22: 0 | F22: =F21+E22 -> 145.49
E23: 0 | F23: =F22+E23 -> 145.49
B24: Expence Grand Total | E24: =F23-SUM(E8:E10) -> 0

Sheet 2022 Expences - 09232022
B2: Expences for Paycheck 9/23/2022
B3: Expence | E3: Cost | F3: Total | G3: Notes
B4: Cash On Hand | E4: 0 | F4: =E4 -> 0
B5: Change On Hand | E5: 0 | F5: =F4+E5 -> 0
B6: Payment for Parent's Back Padio | E6: 0 | F6: =F5+E6 -> 0
B7: Gift / Debit Cards On Hand | E7: 0 | F7: =F6+E7 -> 0
B8: Groceries / Other | E8: =51.44+120.88 -> 172.32 | F8: =F7+E8 -> 172.32
B9: Cigarettes | E9: 0 | F9: =F8+E9 -> 172.32
B10: Gas | E10: 0 | F10: =F9+E10 -> 172.32
E11: 0 | F11: =F10+E11 -> 172.32
E12: 0 | F12: =F11+E12 -> 172.32
E13: 0 | F13: =F12+E13 -> 172.32
E14: 0 | F14: =F13+E14 -> 172.32
E15: 0 | F15: =F14+E15 -> 172.32
E16: 0 | F16: =F15+E16 -> 172.32
E17: 0 | F17: =F16+E17 -> 172.32
E18: 0 | F18: =F17+E18 -> 172.32
E19: 0 | F19: =F18+E19 -> 172.32
E20: 0 | F20: =F19+E20 -> 172.32
E21: 0 | F21: =F20+E21 -> 172.32
E22: 0 | F22: =F21+E22 -> 172.32
E23: 0 | F23: =F22+E23 -> 172.32
B24: Expence Grand Total | E24: =F23-SUM(E8:E10) -> 0

Sheet 2022 Expences - 10072022
B2: Expences for Paycheck 10/7/2022
B3: Expence | E3: Catagory | F3: Cost | G3: Total | I3: Catagory Totals
B4: Walgreens | E4: Medical | F4: =9.44+8.95-0.04 -> 18.35 | G4: =F4 -> 18.35 | I4: ='08) Drop Down Menus'!A2 -> Groceries | J4: =SUMIF($E$4:$E$19,$I4,$F$4:$F$19) -> 190.64
B5: Wal-Mart | E5: Groceries | F5: 190.64 | G5: =G4+F5 -> 208.99 | I5: ='08) Drop Down Menus'!A3 -> Cigarettes | J5: =SUMIF($E$4:$E$19,$I5,$F$4:$F$19) -> 28.73
B6: Steam | E6: Entertainment | F6: 26.24 | G6: =G5+F6 -> 235.23 | I6: ='08) Drop Down Menus'!A4 -> Gas | J6: =SUMIF($E$4:$E$19,$I6,$F$4:$F$19) -> 0
B7: Kwik-Trip | E7: Cigarettes | F7: 28.73 | G7: =G6+F7 -> 263.96 | I7: ='08) Drop Down Menus'!A5 -> Entertainment | J7: =SUMIF($E$4:$E$19,$I7,$F$4:$F$19) -> 26.24
F8: 0 | G8: =G7+F8 -> 263.96 | I8: ='08) Drop Down Menus'!A6 -> Medical | J8: =SUMIF($E$4:$E$19,$I8,$F$4:$F$19) -> 18.35
F9: 0 | G9: =G8+F9 -> 263.96 | I9: ='08) Drop Down Menus'!A7 -> Vehicle | J9: =SUMIF($E$4:$E$19,$I9,$F$4:$F$19) -> 0
F10: 0 | G10: =G9+F10 -> 263.96
F11: 0 | G11: =G10+F11 -> 263.96
F12: 0 | G12: =G11+F12 -> 263.96
F13: 0 | G13: =G12+F13 -> 263.96
F14: 0 | G14: =G13+F14 -> 263.96
F15: 0 | G15: =G14+F15 -> 263.96
F16: 0 | G16: =G15+F16 -> 263.96
F17: 0 | G17: =G16+F17 -> 263.96
F18: 0 | G18: =G17+F18 -> 263.96
F19: 0 | G19: =G18+F19 -> 263.96
B20: Expence Grand Total | F20: =G19-SUM(F4:F6) -> 28.73

Sheet 2022 Expences - 11042022
B2: Expences for Paycheck 10/7/2022
B3: Expence | E3: Catagory | F3: Cost | G3: Total | I3: Catagory Totals
B4: Quik-Trip | E4: Cigarettes | F4: 24.39 | G4: =F4 -> 24.39 | I4: ='08) Drop Down Menus'!A2 -> Groceries | J4: =SUMIF($E$4:$E$19,$I4,$F$4:$F$19) -> 218.62
B5: CVS Care Pass | E5: Medical | F5: 5.25 | G5: =G4+F5 -> 29.64 | I5: ='08) Drop Down Menus'!A3 -> Cigarettes | J5: =SUMIF($E$4:$E$19,$I5,$F$4:$F$19) -> 53.43
B6: Walmart | E6: Groceries | F6: 133.02 | G6: =G5+F6 -> 162.66 | I6: ='08) Drop Down Menus'!A4 -> Gas | J6: =SUMIF($E$4:$E$19,$I6,$F$4:$F$19) -> 0
B7: Lowes | E7: Maintenance | F7: 43.93 | G7: =G6+F7 -> 206.59 | I7: ='08) Drop Down Menus'!A5 -> Entertainment | J7: =SUMIF($E$4:$E$19,$I7,$F$4:$F$19) -> 20.49
B8: Steam | E8: Entertainment | F8: 10.49 | G8: =G7+F8 -> 217.08 | I8: ='08) Drop Down Menus'!A6 -> Medical | J8: =SUMIF($E$4:$E$19,$I8,$F$4:$F$19) -> 5.25
B9: Great Clips | E9: Maintenance | F9: 23 | G9: =G8+F9 -> 240.08 | I9: ='08) Drop Down Menus'!A7 -> Vehicle | J9: =SUMIF($E$4:$E$19,$I9,$F$4:$F$19) -> 0
B10: Harbor Freight | E10: Maintenance | F10: 38.77 | G10: =G9+F10 -> 278.85 | I10: ='08) Drop Down Menus'!A8 -> Maintenance | J10: =SUMIF($E$4:$E$19,$I10,$F$4:$F$19) -> 155.7
B11: Goodwill | E11: Maintenance | F11: 50 | G11: =G10+F11 -> 328.85
B12: Lotto | E12: Entertainment | F12: 10 | G12: =G11+F12 -> 338.85
B13: Cigarettes | E13: Cigarettes | F13: 29.04 | G13: =G12+F13 -> 367.89
B14: Vending | E14: Groceries | F14: 10 | G14: =G13+F14 -> 377.89
B15: Kwik Trip | E15: Groceries | F15: =1.25+8.59+2.09+2.61 -> 14.54 | G15: =G14+F15 -> 392.43
B16: Walmart | E16: Groceries | F16: 61.06 | G16: =G15+F16 -> 453.49
G17: =G16+F17 -> 453.49
F18: 0 | G18: =G17+F18 -> 453.49
F19: 0 | G19: =G18+F19 -> 453.49
B20: Expence Grand Total | F20: =G19-SUM(F4:F6) -> 290.83

Sheet 2022 Expences - 11182022
B2: Expences for Paycheck 11/18/2022
B3: Expence | E3: Catagory | F3: Cost | G3: Total | I3: Catagory Totals
B4: Walmart (Shovel / Salt / Gloves) | E4: Maintenance | F4: 44.47 | G4: =F4 -> 44.47 | I4: ='08) Drop Down Menus'!A2 -> Groceries | J4: =SUMIF($E$4:$E$19,$I4,$F$4:$F$19) -> 106.91
B5: MDG | E5: Maintenance | F5: 8.95 | G5: =G4+F5 -> 53.42 | I5: ='08) Drop Down Menus'!A3 -> Cigarettes | J5: =SUMIF($E$4:$E$19,$I5,$F$4:$F$19) -> 77.19
B6: Stadia Return (Not sure How, but Free $) | E6: Maintenance | F6: -29.99 | G6: =G5+F6 -> 23.43 | I6: ='08) Drop Down Menus'!A4 -> Gas | J6: =SUMIF($E$4:$E$19,$I6,$F$4:$F$19) -> 32.8
B7: Kwik-Trip (2 Packs) | E7: Cigarettes | F7: 19.09 | G7: =G6+F7 -> 42.52 | I7: ='08) Drop Down Menus'!A5 -> Entertainment | J7: =SUMIF($E$4:$E$19,$I7,$F$4:$F$19) -> 7.24
B8: Kwik-Trip (Coffee) | E8: Groceries | F8: =20.4-F7 -> 1.31 | G8: =G7+F8 -> 43.83 | I8: ='08) Drop Down Menus'!A6 -> Medical | J8: =SUMIF($E$4:$E$19,$I8,$F$4:$F$19) -> 30
B9: Walmart (Groceries) | E9: Groceries | F9: 105.6 | G9: =G8+F9 -> 149.43 | I9: ='08) Drop Down Menus'!A7 -> Vehicle | J9: =SUMIF($E$4:$E$19,$I9,$F$4:$F$19) -> 0
B10: Amazone Prime / HIDive | E10: Entertainment | F10: 7.24 | G10: =G9+F10 -> 156.67 | I10: ='08) Drop Down Menus'!A8 -> Maintenance | J10: =SUMIF($E$4:$E$19,$I10,$F$4:$F$19) -> 23.43
B11: Gas | E11: Gas | F11: 32.8 | G11: =G10+F11 -> 189.47
B12: Kwik-Trip (Cigarettes) | E12: Cigarettes | F12: 25.4 | G12: =G11+F12 -> 214.87
B13: CVS (Vyvanse) | E13: Medical | F13: 30 | G13: =G12+F13 -> 244.87
B14: Kwik-Trip (Cigarettes) | E14: Cigarettes | F14: =33.08-0.18-0.8+0.6 -> 32.7 | G14: =G13+F14 -> 277.57
F15: 0 | G15: =G14+F15 -> 277.57
F16: 0 | G16: =G15+F16 -> 277.57
F17: 0 | G17: =G16+F17 -> 277.57
F18: 0 | G18: =G17+F18 -> 277.57
F19: 0 | G19: =G18+F19 -> 277.57
B20: Expence Grand Total | F20: =G19-SUM(F4:F6) -> 254.14

Sheet 2022 Expences - 12022022
B2: Expences for Paycheck 12/2/2022
B3: Expence | E3: Catagory | F3: Cost | G3: Total | I3: Catagory Totals
B4: Cigarettes | E4: Cigarettes | F4: 21.45 | G4: =F4 -> 21.45 | I4: ='08) Drop Down Menus'!A2 -> Groceries | J4: =SUMIF($E$4:$E$19,$I4,$F$4:$F$19) -> 232.14
B5: CVS Carepass | E5: Medical | F5: 5.25 | G5: =G4+F5 -> 26.7 | I5: ='08) Drop Down Menus'!A3 -> Cigarettes | J5: =SUMIF($E$4:$E$19,$I5,$F$4:$F$19) -> 38.71
B6: Wal-Mart | E6: Groceries | F6: 201.55 | G6: =G5+F6 -> 228.25 | I6: ='08) Drop Down Menus'!A4 -> Gas | J6: =SUMIF($E$4:$E$19,$I6,$F$4:$F$19) -> 0
B7: CVS (Hydroxyzine Refill) | E7: Medical | F7: 10 | G7: =G6+F7 -> 238.25 | I7: ='08) Drop Down Menus'!A5 -> Entertainment | J7: =SUMIF($E$4:$E$19,$I7,$F$4:$F$19) -> 14.99
B8: Battle.net (WoW Sub) | E8: Entertainment | F8: 14.99 | G8: =G7+F8 -> 253.24 | I8: ='08) Drop Down Menus'!A6 -> Medical | J8: =SUMIF($E$4:$E$19,$I8,$F$4:$F$19) -> 15.25
B9: Quik Trip | E9: Cigarettes | F9: 17.26 | G9: =G8+F9 -> 270.5 | I9: ='08) Drop Down Menus'!A7 -> Vehicle | J9: =SUMIF($E$4:$E$19,$I9,$F$4:$F$19) -> 0
B10: Wal-Mart | E10: Groceries | F10: 23.07 | G10: =G9+F10 -> 293.57 | I10: ='08) Drop Down Menus'!A8 -> Maintenance | J10: =SUMIF($E$4:$E$19,$I10,$F$4:$F$19) -> 0
B11: Quik Trip (Coffee) | E11: Groceries | F11: 2.09 | G11: =G10+F11 -> 295.66 | I11: Total : | J11: =sum(J4:J10) -> 301.09
B12: Quik Trip (Coffee) | E12: Groceries | F12: 2.09 | G12: =G11+F12 -> 297.75
B13: Quik Trip (Coffee) | E13: Groceries | F13: 3.34 | G13: =G12+F13 -> 301.09
F14: 0 | G14: =G13+F14 -> 301.09
F15: 0 | G15: =G14+F15 -> 301.09
F16: 0 | G16: =G15+F16 -> 301.09
F17: 0 | G17: =G16+F17 -> 301.09
F18: 0 | G18: =G17+F18 -> 301.09
F19: 0 | G19: =G18+F19 -> 301.09
B20: Expence Grand Total | F20: =G19 -> 301.09

Sheet 2022 Expences - 12162022
B2: Expences for Paycheck 12/16/2022
B3: Expence | E3: Catagory | F3: Cost | G3: Total | I3: Catagory Totals
B4: Wal-Mart | E4: Groceries | F4: 46.38 | G4: =F4 -> 46.38 | I4: ='08) Drop Down Menus'!A2 -> Groceries | J4: =SUMIF($E$4:$E$19,$I4,$F$4:$F$19) -> 53.37
B5: Kwik Trip | E5: Gas | F5: 23.05 | G5: =G4+F5 -> 69.43 | I5: ='08) Drop Down Menus'!A3 -> Cigarettes | J5: =SUMIF($E$4:$E$19,$I5,$F$4:$F$19) -> 32.76
B6: Vending Machine | E6: Groceries | F6: 3.99 | G6: =G5+F6 -> 73.42 | I6: ='08) Drop Down Menus'!A4 -> Gas | J6: =SUMIF($E$4:$E$19,$I6,$F$4:$F$19) -> 23.05
B7: MDG | E7: Maintenance | F7: 8.95 | G7: =G6+F7 -> 82.37 | I7: ='08) Drop Down Menus'!A5 -> Entertainment | J7: =SUMIF($E$4:$E$19,$I7,$F$4:$F$19) -> 52.49
B8: Kwik Trip | E8: Cigarettes | F8: 20.6 | G8: =G7+F8 -> 102.97 | I8: ='08) Drop Down Menus'!A6 -> Medical | J8: =SUMIF($E$4:$E$19,$I8,$F$4:$F$19) -> 9.56
B9: XMas Mom | E9: Maintenance | F9: 0 | G9: =G8+F9 -> 102.97 | I9: ='08) Drop Down Menus'!A7 -> Vehicle | J9: =SUMIF($E$4:$E$19,$I9,$F$4:$F$19) -> 0
B10: XMas Grandpa | E10: Maintenance | F10: 0 | G10: =G9+F10 -> 102.97 | I10: ='08) Drop Down Menus'!A8 -> Maintenance | J10: =SUMIF($E$4:$E$19,$I10,$F$4:$F$19) -> 8.95
B11: Battle.net (WoW Upgrade) | E11: Entertainment | F11: 52.49 | G11: =G10+F11 -> 155.46 | I11: Total : | J11: =sum(J4:J10) -> 180.18
B12: Scott's Vending | E12: Groceries | F12: 3 | G12: =G11+F12 -> 158.46
B13: Walmart | E13: Medical | F13: 9.56 | G13: =G12+F13 -> 168.02
B14: Kwik Trip | E14: Cigarettes | F14: 12.16 | G14: =G13+F14 -> 180.18
F15: 0 | G15: =G14+F15 -> 180.18
F16: 0 | G16: =G15+F16 -> 180.18
F17: 0 | G17: =G16+F17 -> 180.18
F18: 0 | G18: =G17+F18 -> 180.18
F19: 0 | G19: =G18+F19 -> 180.18
B20: Expence Grand Total | F20: =SUM(F4:F19) -> 180.18

Sheet 2022 Expences - 12302022
B2: Expences for Paycheck 12/30/2022
B3: Expence | E3: Catagory | F3: Cost | G3: Total | I3: Catagory Totals
B4: Walmart | E4: Groceries | F4: 165.54 | G4: =F4 -> 165.54 | I4: ='08) Drop Down Menus'!A2 -> Groceries | J4: =SUMIF($E$4:$E$19,$I4,$F$4:$F$19) -> 296.55
B5: Kwik-Trip | E5: Cigarettes | F5: 19.77 | G5: =G4+F5 -> 185.31 | I5: ='08) Drop Down Menus'!A3 -> Cigarettes | J5: =SUMIF($E$4:$E$19,$I5,$F$4:$F$19) -> 45.49
B6: Epic Games Store | E6: Entertainment | F6: 23.61 | G6: =G5+F6 -> 208.92 | I6: ='08) Drop Down Menus'!A4 -> Gas | J6: =SUMIF($E$4:$E$19,$I6,$F$4:$F$19) -> 53.57
B7: Walmart | E7: Entertainment | F7: 203.77 | G7: =G6+F7 -> 412.69 | I7: ='08) Drop Down Menus'!A5 -> Entertainment | J7: =SUMIF($E$4:$E$19,$I7,$F$4:$F$19) -> 227.38
B8: CVS (Venlafaxine) | E8: Medical | F8: 30 | G8: =G7+F8 -> 442.69 | I8: ='08) Drop Down Menus'!A6 -> Medical | J8: =SUMIF($E$4:$E$19,$I8,$F$4:$F$19) -> 35.25
B9: Kwik-Trip | E9: Gas | F9: 24.04 | G9: =G8+F9 -> 466.73 | I9: ='08) Drop Down Menus'!A7 -> Vehicle | J9: =SUMIF($E$4:$E$19,$I9,$F$4:$F$19) -> 12
B10: CVS Carepass | E10: Medical | F10: 5.25 | G10: =G9+F10 -> 471.98 | I10: ='08) Drop Down Menus'!A8 -> Maintenance | J10: =SUMIF($E$4:$E$19,$I10,$F$4:$F$19) -> 18.1
B11: Walmart | E11: Groceries | F11: 127.67 | G11: =G10+F11 -> 599.65
B12: Citco | E12: Gas | F12: 29.53 | G12: =G11+F12 -> 629.18
B13: Citco | E13: Cigarettes | F13: 25.72 | G13: =G12+F13 -> 654.9
B14: Harbor-Freight | E14: Maintenance | F14: 18.1 | G14: =G13+F14 -> 673
B15: Kwik-Trip | E15: Vehicle | F15: 12 | G15: =G14+F15 -> 685
B16: Kwik-Trip | E16: Groceries | F16: 3.34 | G16: =G15+F16 -> 688.34
F17: 0 | G17: =G16+F17 -> 688.34
F18: 0 | G18: =G17+F18 -> 688.34
F19: 0 | G19: =G18+F19 -> 688.34
B20: Expence Grand Total | F20: =SUM(F3:F19) -> 688.34

Sheet 2023 Expences - 01132023
B2: Expences for Paycheck 1/13/2023 | I2: Catagory Totals
B3: Expence | E3: Catagory | F3: Cost | G3: Total | I3: ='08) Drop Down Menus'!A2 -> Groceries | J3: =SUMIF($E$4:$E$19,$I3,$F$4:$F$19) -> 231.85
B4: Kwik Trip | E4: Cigarettes | F4: 27.14 | G4: =F4 -> 27.14 | I4: ='08) Drop Down Menus'!A3 -> Cigarettes | J4: =SUMIF($E$4:$E$19,$I4,$F$4:$F$19) -> 27.14
B5: MDG | E5: Debt | F5: 8.95 | G5: =G4+F5 -> 36.09 | I5: ='08) Drop Down Menus'!A4 -> Gas | J5: =SUMIF($E$4:$E$19,$I5,$F$4:$F$19) -> 23.15
B6: =CONCATENATE("Affirm " , '09) Affirm Payoff Schedule'!N5) -> Affirm NewEgg | E6: Debt | F6: 6.3 | G6: =G5+F6 -> 42.39 | I6: ='08) Drop Down Menus'!A5 -> Entertainment | J6: =SUMIF($E$4:$E$19,$I6,$F$4:$F$19) -> 0
B7: =CONCATENATE("Affirm " , '09) Affirm Payoff Schedule'!N6) -> Affirm WalMart 3 | E7: Debt | F7: 11.01 | G7: =G6+F7 -> 53.4 | I7: ='08) Drop Down Menus'!A6 -> Medical | J7: =SUMIF($E$4:$E$19,$I7,$F$4:$F$19) -> 5.76
B8: Kwik Trip | E8: Gas | F8: 23.15 | G8: =G7+F8 -> 76.55 | I8: ='08) Drop Down Menus'!A7 -> Vehicle | J8: =SUMIF($E$4:$E$19,$I8,$F$4:$F$19) -> 0
B9: Wal-Mart | E9: Groceries | F9: 48.53 | G9: =G8+F9 -> 125.08 | I9: ='08) Drop Down Menus'!A8 -> Maintenance | J9: =SUMIF($E$4:$E$19,$I9,$F$4:$F$19) -> 216.68
B10: Wal-Mart | E10: Groceries | F10: 183.32 | G10: =G9+F10 -> 308.4 | I10: ='08) Drop Down Menus'!A9 -> Debt | J10: =SUMIF($E$4:$E$19,$I10,$F$4:$F$19) -> 26.26
B11: Asurion Wireless (Phone Screen) | E11: Maintenance | F11: 30.6 | G11: =G10+F11 -> 339
B12: Cash Withdrawl | E12: Maintenance | F12: =400-(F10+F11) -> 186.08 | G12: =G11+F12 -> 525.08 | I12: Catagory YTD Totals
B13: Wal-Greens | E13: Medical | F13: 5.76 | G13: =G12+F13 -> 530.84 | I13: ='08) Drop Down Menus'!A2 -> Groceries | J13: =J3 -> 231.85
F14: 0 | G14: =G13+F14 -> 530.84 | I14: ='08) Drop Down Menus'!A3 -> Cigarettes | J14: =J4 -> 27.14
F15: 0 | G15: =G14+F15 -> 530.84 | I15: ='08) Drop Down Menus'!A4 -> Gas | J15: =J5 -> 23.15
F16: 0 | G16: =G15+F16 -> 530.84 | I16: ='08) Drop Down Menus'!A5 -> Entertainment | J16: =J6 -> 0
F17: 0 | G17: =G16+F17 -> 530.84 | I17: ='08) Drop Down Menus'!A6 -> Medical | J17: =J7 -> 5.76
F18: 0 | G18: =G17+F18 -> 530.84 | I18: ='08) Drop Down Menus'!A7 -> Vehicle | J18: =J8 -> 0
F19: 0 | G19: =G18+F19 -> 530.84 | I19: ='08) Drop Down Menus'!A8 -> Maintenance | J19: =J9 -> 216.68
B20: Expence Grand Total | F20: =SUM(F3:F19) -> 530.84 | I20: ='08) Drop Down Menus'!A9 -> Debt | J20: =J10 -> 26.26

Sheet 2023 Expences - 01272023
B2: Expences for Paycheck 1/27/2023 | J2: Catagory Totals
B3: Expence | E3: Date | F3: Catagory | G3: Cost | H3: Total | J3: ='08) Drop Down Menus'!A2 -> Groceries | K3: =SUMIF($F$4:$F$19,$J3,$G$4:$G$19) -> 179.3
B4: =CONCATENATE("Affirm " , '09) Affirm Payoff Schedule'!N3) -> Affirm WalMart 1 | E4: 44960 | F4: Debt | G4: 47.37 | H4: =G4 -> 47.37 | J4: ='08) Drop Down Menus'!A3 -> Cigarettes | K4: =SUMIF($F$4:$F$19,$J4,$G$4:$G$19) -> 29.38
B5: =CONCATENATE("Affirm " , '09) Affirm Payoff Schedule'!N4) -> Affirm WalMart 2 | E5: 44960 | F5: Debt | G5: 47.06 | H5: =H4+G5 -> 94.43 | J5: ='08) Drop Down Menus'!A4 -> Gas | K5: =SUMIF($F$4:$F$19,$J5,$G$4:$G$19) -> 67.87
B6: =CONCATENATE("Affirm " , '09) Affirm Payoff Schedule'!N5) -> Affirm NewEgg | E6: 44960 | F6: Debt | G6: 23.61 | H6: =H5+G6 -> 118.04 | J6: ='08) Drop Down Menus'!A5 -> Entertainment | K6: =SUMIF($F$4:$F$19,$J6,$G$4:$G$19) -> 10.49
B7: =CONCATENATE("Affirm " , '09) Affirm Payoff Schedule'!N6) -> Affirm WalMart 3 | E7: 44960 | F7: Debt | G7: 6.3 | H7: =H6+G7 -> 124.34 | J7: ='08) Drop Down Menus'!A6 -> Medical | K7: =SUMIF($F$4:$F$19,$J7,$G$4:$G$19) -> 0
B8: =CONCATENATE("Affirm " , '09) Affirm Payoff Schedule'!N7) -> Affirm WalMart 4 | E8: 44960 | F8: Debt | G8: 11.01 | H8: =H7+G8 -> 135.35 | J8: ='08) Drop Down Menus'!A7 -> Vehicle | K8: =SUMIF($F$4:$F$19,$J8,$G$4:$G$19) -> 12
B9: Kwik-Trip | E9: 44960 | F9: Gas | G9: 29.31 | H9: =H8+G9 -> 164.66 | J9: ='08) Drop Down Menus'!A8 -> Maintenance | K9: =SUMIF($F$4:$F$19,$J9,$G$4:$G$19) -> 0
B10: Oculus Store | E10: 44961 | F10: Entertainment | G10: 10.49 | H10: =H9+G10 -> 175.15 | J10: ='08) Drop Down Menus'!A9 -> Debt | K10: =SUMIF($F$4:$F$19,$J10,$G$4:$G$19) -> 135.35
B11: Kwik-Trip (Doughnuts) | E11: 44962 | F11: Groceries | G11: 5.28 | H11: =H10+G11 -> 180.43
B12: Kwik-Trip (Gas + Car Wash) | E12: 44962 | F12: Gas | G12: 38.56 | H12: =H11+G12 -> 218.99 | J12: Catagory YTD Totals | L12: Average (02/26)
B13: Kwik-Trip | E13: 44962 | F13: Cigarettes | G13: 29.38 | H13: =H12+G13 -> 248.37 | J13: ='08) Drop Down Menus'!A2 -> Groceries | K13: =K3+'2023 Expences - 01132023'!J13 -> 411.15 | L13: =K13/2 -> 205.575
B14: Wal-Mart | E14: 44962 | F14: Groceries | G14: 174.02 | H14: =H13+G14 -> 422.39 | J14: ='08) Drop Down Menus'!A3 -> Cigarettes | K14: =K4+'2023 Expences - 01132023'!J14 -> 56.52 | L14: =K14/2 -> 28.26
B15: Kwik-Trip (Car Wash - Wrong Code Used) | E15: 44962 | F15: Vehicle | G15: 12 | H15: =H14+G15 -> 434.39 | J15: ='08) Drop Down Menus'!A4 -> Gas | K15: =K5+'2023 Expences - 01132023'!J15 -> 91.02 | L15: =K15/2 -> 45.51
G16: 0 | H16: =H15+G16 -> 434.39 | J16: ='08) Drop Down Menus'!A5 -> Entertainment | K16: =K6+'2023 Expences - 01132023'!J16 -> 10.49 | L16: =K16/2 -> 5.245
G17: 0 | H17: =H16+G17 -> 434.39 | J17: ='08) Drop Down Menus'!A6 -> Medical | K17: =K7+'2023 Expences - 01132023'!J17 -> 5.76 | L17: =K17/2 -> 2.88
G18: 0 | H18: =H17+G18 -> 434.39 | J18: ='08) Drop Down Menus'!A7 -> Vehicle | K18: =K8+'2023 Expences - 01132023'!J18 -> 12 | L18: =K18/2 -> 6
G19: 0 | H19: =H18+G19 -> 434.39 | J19: ='08) Drop Down Menus'!A8 -> Maintenance | K19: =K9+'2023 Expences - 01132023'!J19 -> 216.68 | L19: =K19/2 -> 108.34
B20: Expence Grand Total | G20: =sum(G4:G19) -> 434.39 | J20: ='08) Drop Down Menus'!A9 -> Debt | K20: =K10+'2023 Expences - 01132023'!J20 -> 161.61 | L20: =K20/2 -> 80.805

Sheet 2023 Expences - 02102023
B2: Expences for Paycheck 2/10/2023 | J2: Catagory Totals
B3: Expence | E3: Date | F3: Catagory | G3: Cost | H3: Total | J3: ='08) Drop Down Menus'!A2 -> Groceries | K3: =SUMIF($F$4:$F$24,$J3,$G$4:$G$24) -> 232.71
B4: Kwik-Trip | E4: 44971 | F4: Cigarettes | G4: 28.38 | H4: =G4 -> 28.38 | J4: ='08) Drop Down Menus'!A3 -> Cigarettes | K4: =SUMIF($F$4:$F$24,$J4,$G$4:$G$24) -> 46.81
B5: Kwik-Trip | E5: 44976 | F5: Cigarettes | G5: 18.43 | H5: =H4+G5 -> 46.81 | J5: ='08) Drop Down Menus'!A4 -> Gas | K5: =SUMIF($F$4:$F$24,$J5,$G$4:$G$24) -> 0
B6: MDG | E6: 44967 | F6: Debt | G6: 8.95 | H6: =H5+G6 -> 55.76 | J6: ='08) Drop Down Menus'!A5 -> Entertainment | K6: =SUMIF($F$4:$F$24,$J6,$G$4:$G$24) -> 262.06
B7: =CONCATENATE("Affirm " , '09) Affirm Payoff Schedule'!N3) -> Affirm WalMart 1 | E7: 44968 | F7: Debt | G7: 47.37 | H7: =H6+G7 -> 103.13 | J7: ='08) Drop Down Menus'!A6 -> Medical | K7: =SUMIF($F$4:$F$24,$J7,$G$4:$G$24) -> 10
B8: =CONCATENATE("Affirm " , '09) Affirm Payoff Schedule'!N4) -> Affirm WalMart 2 | E8: 44968 | F8: Debt | G8: 47.06 | H8: =H7+G8 -> 150.19 | J8: ='08) Drop Down Menus'!A7 -> Vehicle | K8: =SUMIF($F$4:$F$24,$J8,$G$4:$G$24) -> 103.47
B9: =CONCATENATE("Affirm " , '09) Affirm Payoff Schedule'!N5) -> Affirm NewEgg | E9: 44968 | F9: Debt | G9: 23.61 | H9: =H8+G9 -> 173.8 | J9: ='08) Drop Down Menus'!A8 -> Maintenance | K9: =SUMIF($F$4:$F$24,$J9,$G$4:$G$24) -> 59.94
B10: =CONCATENATE("Affirm " , '09) Affirm Payoff Schedule'!N6) -> Affirm WalMart 3 | E10: 44968 | F10: Debt | G10: 6.3 | H10: =H9+G10 -> 180.1 | J10: ='08) Drop Down Menus'!A9 -> Debt | K10: =SUMIF($F$4:$F$24,$J10,$G$4:$G$24) -> 144.3
B11: =CONCATENATE("Affirm " , '09) Affirm Payoff Schedule'!N7) -> Affirm WalMart 4 | E11: 44968 | F11: Debt | G11: 11.01 | H11: =H10+G11 -> 191.11
B12: Steam (Cyberpunk 2077) | E12: 44967 | F12: Entertainment | G12: 62.99 | H12: =H11+G12 -> 254.1 | J12: Catagory YTD Totals | L12: Average (03/26)
B13: Mega (Download Service) | E13: 44967 | F13: Entertainment | G13: 10.78 | H13: =H12+G13 -> 264.88 | J13: ='08) Drop Down Menus'!A2 -> Groceries | K13: =K3+'2023 Expences - 01272023'!K13 -> 643.86 | L13: =K13/3 -> 214.62
B14: US Cellular (Tablet Tax) | E14: 44972 | F14: Entertainment | G14: 54.97 | H14: =H13+G14 -> 319.85 | J14: ='08) Drop Down Menus'!A3 -> Cigarettes | K14: =K4+'2023 Expences - 01272023'!K14 -> 103.33 | L14: =K14/3 -> 34.443333
B15: Amazon (S8+ Case) | E15: 44972 | F15: Entertainment | G15: 71.33 | H15: =H14+G15 -> 391.18 | J15: ='08) Drop Down Menus'!A4 -> Gas | K15: =K5+'2023 Expences - 01272023'!K15 -> 91.02 | L15: =K15/3 -> 30.34
B16: Game Stop (PS5 Controler) | E16: 44976 | F16: Entertainment | G16: 61.99 | H16: =H15+G16 -> 453.17 | J16: ='08) Drop Down Menus'!A5 -> Entertainment | K16: =K6+'2023 Expences - 01272023'!K16 -> 272.55 | L16: =K16/3 -> 90.85
B17: Wal-Mart | E17: 44969 | F17: Groceries | G17: 162.16 | H17: =H16+G17 -> 615.33 | J17: ='08) Drop Down Menus'!A6 -> Medical | K17: =K7+'2023 Expences - 01272023'!K17 -> 15.76 | L17: =K17/3 -> 5.2533333
B18: Wal-Mart | E18: 44975 | F18: Groceries | G18: 70.55 | H18: =H17+G18 -> 685.88 | J18: ='08) Drop Down Menus'!A7 -> Vehicle | K18: =K8+'2023 Expences - 01272023'!K18 -> 115.47 | L18: =K18/3 -> 38.49
B19: Cash Withdrawl (Laundry) | E19: 44968 | F19: Maintenance | G19: 20 | H19: =H18+G19 -> 705.88 | J19: ='08) Drop Down Menus'!A8 -> Maintenance | K19: =K9+'2023 Expences - 01272023'!K19 -> 276.62 | L19: =K19/3 -> 92.206667
B20: Smart Style (Haircut) | E20: 44969 | F20: Maintenance | G20: 25.26 | H20: =H19+G20 -> 731.14
B21: Good Will | E21: 44975 | F21: Maintenance | G21: 14.68 | H21: =H20+G21 -> 745.82
B22: CVS (Anxiety Meds) | E22: 44969 | F22: Medical | G22: 10 | H22: =H21+G22 -> 755.82
B23: Oil Change (Oil, Cabin Filter, Engine Clean) | E23: 44969 | F23: Vehicle | G23: 103.47 | H23: =H22+G23 -> 859.29
G24: 0 | H24: =H23+G24 -> 859.29
B25: Expence Grand Total | G25: =SUM(G3:G24) -> 859.29 | J25: ='08) Drop Down Menus'!A9 -> Debt | K25: =K10+'2023 Expences - 01272023'!K20 -> 305.91 | L25: =K25/3 -> 101.97

Sheet 2023 Expences - 02242023
B2: Expences for Paycheck 2/24/2023 | J2: Catagory Totals
B3: Expence | E3: Date | F3: Catagory | G3: Cost | H3: Total | J3: ='08) Drop Down Menus'!A2 -> Groceries | K3: =SUMIF($F$4:$F$19,$J3,$G$4:$G$19) -> 118.08
B4: Kwik-Trip | E4: 44982 | F4: Maintenance | G4: 12.09 | H4: =G4 -> 12.09 | J4: ='08) Drop Down Menus'!A3 -> Cigarettes | K4: =SUMIF($F$4:$F$19,$J4,$G$4:$G$19) -> 58.85
B5: Kwik-Trip | E5: 44982 | F5: Cigarettes | G5: 29.42 | H5: =H4+G5 -> 41.51 | J5: ='08) Drop Down Menus'!A4 -> Gas | K5: =SUMIF($F$4:$F$19,$J5,$G$4:$G$19) -> 34.4
B6: Wal-Mart | E6: 44982 | F6: Groceries | G6: 112.35 | H6: =H5+G6 -> 153.86 | J6: ='08) Drop Down Menus'!A5 -> Entertainment | K6: =SUMIF($F$4:$F$19,$J6,$G$4:$G$19) -> 4.95
B7: CVS (Prozasin) | E7: 44984 | F7: Medical | G7: 10 | H7: =H6+G7 -> 163.86 | J7: ='08) Drop Down Menus'!A6 -> Medical | K7: =SUMIF($F$4:$F$19,$J7,$G$4:$G$19) -> 40
B8: CVS (Vyvanse) | E8: 44984 | F8: Medical | G8: 30 | H8: =H7+G8 -> 193.86 | J8: ='08) Drop Down Menus'!A7 -> Vehicle | K8: =SUMIF($F$4:$F$19,$J8,$G$4:$G$19) -> 0
B9: Scott's Vending | E9: 44986 | F9: Groceries | G9: 5.73 | H9: =H8+G9 -> 199.59 | J9: ='08) Drop Down Menus'!A8 -> Maintenance | K9: =SUMIF($F$4:$F$19,$J9,$G$4:$G$19) -> 12.09
B10: Kwik-Trip | E10: 44987 | F10: Cigarettes | G10: 29.43 | H10: =H9+G10 -> 229.02 | J10: ='08) Drop Down Menus'!A9 -> Debt | K10: =SUMIF($F$4:$F$19,$J10,$G$4:$G$19) -> 0
B11: Kwik-Trip | E11: 44987 | F11: Gas | G11: 34.4 | H11: =H10+G11 -> 263.42
B12: Albion Online | E12: 44990 | F12: Entertainment | G12: 4.95 | H12: =H11+G12 -> 268.37 | J12: Catagory YTD Totals | L12: Average (04/26)
G13: 0 | H13: =H12+G13 -> 268.37 | J13: ='08) Drop Down Menus'!A2 -> Groceries | K13: =K3+'2023 Expences - 02102023'!K13 -> 761.94 | L13: =K13/4 -> 190.485
G14: 0 | H14: =H13+G14 -> 268.37 | J14: ='08) Drop Down Menus'!A3 -> Cigarettes | K14: =K4+'2023 Expences - 02102023'!K14 -> 162.18 | L14: =K14/4 -> 40.545
G15: 0 | H15: =H14+G15 -> 268.37 | J15: ='08) Drop Down Menus'!A4 -> Gas | K15: =K5+'2023 Expences - 02102023'!K15 -> 125.42 | L15: =K15/4 -> 31.355
G16: 0 | H16: =H15+G16 -> 268.37 | J16: ='08) Drop Down Menus'!A5 -> Entertainment | K16: =K6+'2023 Expences - 02102023'!K16 -> 277.5 | L16: =K16/4 -> 69.375
G17: 0 | H17: =H16+G17 -> 268.37 | J17: ='08) Drop Down Menus'!A6 -> Medical | K17: =K7+'2023 Expences - 02102023'!K17 -> 55.76 | L17: =K17/4 -> 13.94
G18: 0 | H18: =H17+G18 -> 268.37 | J18: ='08) Drop Down Menus'!A7 -> Vehicle | K18: =K8+'2023 Expences - 02102023'!K18 -> 115.47 | L18: =K18/4 -> 28.8675
G19: 0 | H19: =H18+G19 -> 268.37 | J19: ='08) Drop Down Menus'!A8 -> Maintenance | K19: =K9+'2023 Expences - 02102023'!K19 -> 288.71 | L19: =K19/4 -> 72.1775
B20: Expence Grand Total | G20: =H19 -> 268.37 | J20: ='08) Drop Down Menus'!A9 -> Debt | K20: =K10+'2023 Expences - 02102023'!K25 -> 305.91 | L20: =K20/4 -> 76.4775

Sheet 2023 Expences - 03102023
B2: Expences for Paycheck 3/10/2023 | J2: Catagory Totals
B3: Expence | E3: Date | F3: Catagory | G3: Cost | H3: Total | J3: ='08) Drop Down Menus'!A2 -> Groceries | K3: =SUMIF($F$4:$F$19,$J3,$G$4:$G$19) -> 128.92
B4: Kwik-Trip | E4: 44996 | F4: Cigarettes | G4: 28.38 | H4: =G4 -> 28.38 | J4: ='08) Drop Down Menus'!A3 -> Cigarettes | K4: =SUMIF($F$4:$F$19,$J4,$G$4:$G$19) -> 46.85
B5: MDG | E5: 44996 | F5: Debt | G5: 8.95 | H5: =H4+G5 -> 37.33 | J5: ='08) Drop Down Menus'!A4 -> Gas | K5: =SUMIF($F$4:$F$19,$J5,$G$4:$G$19) -> 26.24
B6: Wal-Mart | E6: 44999 | F6: Groceries | G6: 125.87 | H6: =H5+G6 -> 163.2 | J6: ='08) Drop Down Menus'!A5 -> Entertainment | K6: =SUMIF($F$4:$F$19,$J6,$G$4:$G$19) -> 30.89
B7: Steam (Game) | E7: 45000 | F7: Entertainment | G7: 20.99 | H7: =H6+G7 -> 184.19 | J7: ='08) Drop Down Menus'!A6 -> Medical | K7: =SUMIF($F$4:$F$19,$J7,$G$4:$G$19) -> 0
B8: Albion Online | E8: 45001 | F8: Entertainment | G8: 4.95 | H8: =H7+G8 -> 189.14 | J8: ='08) Drop Down Menus'!A7 -> Vehicle | K8: =SUMIF($F$4:$F$19,$J8,$G$4:$G$19) -> 0
B9: Kwik-Trip | E9: 45002 | F9: Cigarettes | G9: 18.47 | H9: =H8+G9 -> 207.61 | J9: ='08) Drop Down Menus'!A8 -> Maintenance | K9: =SUMIF($F$4:$F$19,$J9,$G$4:$G$19) -> 0
B10: BP Gas Station | E10: 45002 | F10: Gas | G10: 26.24 | H10: =H9+G10 -> 233.85 | J10: ='08) Drop Down Menus'!A9 -> Debt | K10: =SUMIF($F$4:$F$19,$J10,$G$4:$G$19) -> 8.95
B11: Albion Online | E11: 45008 | F11: Entertainment | G11: 4.95 | H11: =H10+G11 -> 238.8
B12: Scott's Vending | E12: 45008 | F12: Groceries | G12: 3.05 | H12: =H11+G12 -> 241.85 | J12: Catagory YTD Totals | L12: Average (05/26)
G13: 0 | H13: =H12+G13 -> 241.85 | J13: ='08) Drop Down Menus'!A2 -> Groceries | K13: =K3+'2023 Expences - 02242023'!K13 -> 890.86 | L13: =K13/5 -> 178.172
G14: 0 | H14: =H13+G14 -> 241.85 | J14: ='08) Drop Down Menus'!A3 -> Cigarettes | K14: =K4+'2023 Expences - 02242023'!K14 -> 209.03 | L14: =K14/5 -> 41.806
G15: 0 | H15: =H14+G15 -> 241.85 | J15: ='08) Drop Down Menus'!A4 -> Gas | K15: =K5+'2023 Expences - 02242023'!K15 -> 151.66 | L15: =K15/5 -> 30.332
G16: 0 | H16: =H15+G16 -> 241.85 | J16: ='08) Drop Down Menus'!A5 -> Entertainment | K16: =K6+'2023 Expences - 02242023'!K16 -> 308.39 | L16: =K16/5 -> 61.678
G17: 0 | H17: =H16+G17 -> 241.85 | J17: ='08) Drop Down Menus'!A6 -> Medical | K17: =K7+'2023 Expences - 02242023'!K17 -> 55.76 | L17: =K17/5 -> 11.152
G18: 0 | H18: =H17+G18 -> 241.85 | J18: ='08) Drop Down Menus'!A7 -> Vehicle | K18: =K8+'2023 Expences - 02242023'!K18 -> 115.47 | L18: =K18/5 -> 23.094
G19: 0 | H19: =H18+G19 -> 241.85 | J19: ='08) Drop Down Menus'!A8 -> Maintenance | K19: =K9+'2023 Expences - 02242023'!K19 -> 288.71 | L19: =K19/5 -> 57.742
B20: Expence Grand Total | G20: =H19 -> 241.85 | J20: ='08) Drop Down Menus'!A9 -> Debt | K20: =K10+'2023 Expences - 02242023'!K20 -> 314.86 | L20: =K20/5 -> 62.972

Sheet 2023 Expences - 03242023
B2: Expences for Paycheck 3/24/2023 | J2: Catagory Totals
B3: Expence | E3: Date | F3: Catagory | G3: Cost | H3: Total | J3: ='08) Drop Down Menus'!A2 -> Groceries | K3: =SUMIF($F$4:$F$19,$J3,$G$4:$G$19) -> 195.9
B4: Kwik-Trip | E4: 45009 | F4: Cigarettes | G4: 28.38 | H4: =G4 -> 28.38 | J4: ='08) Drop Down Menus'!A3 -> Cigarettes | K4: =SUMIF($F$4:$F$19,$J4,$G$4:$G$19) -> 58.64
B5: Kwik-Trip | E5: 45021 | F5: Cigarettes | G5: 3.24 | H5: =H4+G5 -> 31.62 | J5: ='08) Drop Down Menus'!A4 -> Gas | K5: =SUMIF($F$4:$F$19,$J5,$G$4:$G$19) -> 33.88
B6: Albion Online | E6: 45016 | F6: Entertainment | G6: 4.95 | H6: =H5+G6 -> 36.57 | J6: ='08) Drop Down Menus'!A5 -> Entertainment | K6: =SUMIF($F$4:$F$19,$J6,$G$4:$G$19) -> 4.95
B7: CVS Pharmacy (Vyvanse, Venlafaxine, Minipress) | E7: 45014 | F7: Medical | G7: 70 | H7: =H6+G7 -> 106.57 | J7: ='08) Drop Down Menus'!A6 -> Medical | K7: =SUMIF($F$4:$F$19,$J7,$G$4:$G$19) -> 70
B8: Citgo | E8: 45014 | F8: Gas | G8: 33.88 | H8: =H7+G8 -> 140.45 | J8: ='08) Drop Down Menus'!A7 -> Vehicle | K8: =SUMIF($F$4:$F$19,$J8,$G$4:$G$19) -> 0
B9: Citgo | E9: 45014 | F9: Cigarettes | G9: 27.02 | H9: =H8+G9 -> 167.47 | J9: ='08) Drop Down Menus'!A8 -> Maintenance | K9: =SUMIF($F$4:$F$19,$J9,$G$4:$G$19) -> 0
B10: Wal-Mart | E10: 45011 | F10: Groceries | G10: 195.9 | H10: =H9+G10 -> 363.37 | J10: ='08) Drop Down Menus'!A9 -> Debt | K10: =SUMIF($F$4:$F$19,$J10,$G$4:$G$19) -> 0
G11: 0 | H11: =H10+G11 -> 363.37
G12: 0 | H12: =H11+G12 -> 363.37 | J12: Catagory YTD Totals | L12: Average (06/26)
G13: 0 | H13: =H12+G13 -> 363.37 | J13: ='08) Drop Down Menus'!A2 -> Groceries | K13: =K3+'2023 Expences - 03102023'!K13 -> 1086.76 | L13: =K13/6 -> 181.12667
G14: 0 | H14: =H13+G14 -> 363.37 | J14: ='08) Drop Down Menus'!A3 -> Cigarettes | K14: =K4+'2023 Expences - 03102023'!K14 -> 267.67 | L14: =K14/6 -> 44.611667
G15: 0 | H15: =H14+G15 -> 363.37 | J15: ='08) Drop Down Menus'!A4 -> Gas | K15: =K5+'2023 Expences - 03102023'!K15 -> 185.54 | L15: =K15/6 -> 30.923333
G16: 0 | H16: =H15+G16 -> 363.37 | J16: ='08) Drop Down Menus'!A5 -> Entertainment | K16: =K6+'2023 Expences - 03102023'!K16 -> 313.34 | L16: =K16/6 -> 52.223333
G17: 0 | H17: =H16+G17 -> 363.37 | J17: ='08) Drop Down Menus'!A6 -> Medical | K17: =K7+'2023 Expences - 03102023'!K17 -> 125.76 | L17: =K17/6 -> 20.96
G18: 0 | H18: =H17+G18 -> 363.37 | J18: ='08) Drop Down Menus'!A7 -> Vehicle | K18: =K8+'2023 Expences - 03102023'!K18 -> 115.47 | L18: =K18/6 -> 19.245
G19: 0 | H19: =H18+G19 -> 363.37 | J19: ='08) Drop Down Menus'!A8 -> Maintenance | K19: =K9+'2023 Expences - 03102023'!K19 -> 288.71 | L19: =K19/6 -> 48.118333
B20: Expence Grand Total | G20: =H19 -> 363.37 | J20: ='08) Drop Down Menus'!A9 -> Debt | K20: =K10+'2023 Expences - 03102023'!K20 -> 314.86 | L20: =K20/6 -> 52.476667

Sheet 2023 Expences - 04072023
B2: Expences for Paycheck 4/07/2023 | J2: Catagory Totals
B3: Expence | E3: Date | F3: Catagory | G3: Cost | H3: Total | J3: ='08) Drop Down Menus'!A2 -> Groceries | K3: =SUMIF($F$4:$F$17,$J3,$G$4:$G$17) -> 360.82
B4: MDG | E4: 45024 | F4: Entertainment | G4: 8.95 | H4: =G4 -> 8.95 | J4: ='08) Drop Down Menus'!A3 -> Cigarettes | K4: =SUMIF($F$4:$F$17,$J4,$G$4:$G$17) -> 62.59
B5: Wal-Mart | E5: 45024 | F5: Groceries | G5: 227.85 | H5: =H4+G5 -> 236.8 | J5: ='08) Drop Down Menus'!A4 -> Gas | K5: =SUMIF($F$4:$F$17,$J5,$G$4:$G$17) -> 34.28
B6: Wal-Mart | E6: 45024 | F6: Groceries | G6: 1.66 | H6: =H5+G6 -> 238.46 | J6: ='08) Drop Down Menus'!A5 -> Entertainment | K6: =SUMIF($F$4:$F$17,$J6,$G$4:$G$17) -> 79.67
B7: Kwik-Trip | E7: 45024 | F7: Cigarettes | G7: 25.27 | H7: =H6+G7 -> 263.73 | J7: ='08) Drop Down Menus'!A6 -> Medical | K7: =SUMIF($F$4:$F$17,$J7,$G$4:$G$17) -> 0
B8: Great Clips | E8: 45029 | F8: Maintenance | G8: 27 | H8: =H7+G8 -> 290.73 | J8: ='08) Drop Down Menus'!A7 -> Vehicle | K8: =SUMIF($F$4:$F$17,$J8,$G$4:$G$17) -> 0
B9: McDonalds | E9: 45030 | F9: Groceries | G9: 6.1 | H9: =H8+G9 -> 296.83 | J9: ='08) Drop Down Menus'!A8 -> Maintenance | K9: =SUMIF($F$4:$F$17,$J9,$G$4:$G$17) -> 62.36
B10: BP Gas Station (Wild Rose) | E10: 45030 | F10: Cigarettes | G10: 22.79 | H10: =H9+G10 -> 319.62 | J10: ='08) Drop Down Menus'!A9 -> Debt | K10: =SUMIF($F$4:$F$17,$J10,$G$4:$G$17) -> 0
B11: Wal-Mart | E11: 45031 | F11: Maintenance | G11: 35.36 | H11: =H10+G11 -> 354.98
B12: Kwik-Trip | E12: 45032 | F12: Gas | G12: 34.28 | H12: =H11+G12 -> 389.26 | J12: Catagory YTD Totals | L12: Average (07/26)
B13: Steam | E13: 45035 | F13: Entertainment | G13: 15.74 | H13: =H12+G13 -> 405 | J13: ='08) Drop Down Menus'!A2 -> Groceries | K13: =K3+'2023 Expences - 03242023'!K13 -> 1447.58 | L13: =K13/7 -> 206.79714
B14: FFXIV | E14: 45035 | F14: Entertainment | G14: =39.99+14.99 -> 54.98 | H14: =H13+G14 -> 459.98 | J14: ='08) Drop Down Menus'!A3 -> Cigarettes | K14: =K4+'2023 Expences - 03242023'!K14 -> 330.26 | L14: =K14/7 -> 47.18
B15: Wal-Mart | E15: 45035 | F15: Groceries | G15: 125.21 | H15: =H14+G15 -> 585.19 | J15: ='08) Drop Down Menus'!A4 -> Gas | K15: =K5+'2023 Expences - 03242023'!K15 -> 219.82 | L15: =K15/7 -> 31.402857
B16: Kwik-Trip | E16: 45034 | F16: Cigarettes | G16: 14.53 | H16: =H15+G16 -> 599.72 | J16: ='08) Drop Down Menus'!A5 -> Entertainment | K16: =K6+'2023 Expences - 03242023'!K16 -> 393.01 | L16: =K16/7 -> 56.144286
G17: 0 | H17: =H16+G17 -> 599.72 | J17: ='08) Drop Down Menus'!A6 -> Medical | K17: =K7+'2023 Expences - 03242023'!K17 -> 125.76 | L17: =K17/7 -> 17.965714
B18: Expence Grand Total | G18: =H17 -> 599.72 | J18: ='08) Drop Down Menus'!A7 -> Vehicle | K18: =K8+'2023 Expences - 03242023'!K18 -> 115.47 | L18: =K18/7 -> 16.495714
J19: ='08) Drop Down Menus'!A8 -> Maintenance | K19: =K9+'2023 Expences - 03242023'!K19 -> 351.07 | L19: =K19/7 -> 50.152857
J20: ='08) Drop Down Menus'!A9 -> Debt | K20: =K10+'2023 Expences - 03242023'!K20 -> 314.86 | L20: =K20/7 -> 44.98

Sheet 2023 Expences - 04212023
B2: Expences for Paycheck 4/21/2023 | J2: Catagory Totals
B3: Expence | E3: Date | F3: Catagory | G3: Cost | H3: Total | J3: ='08) Drop Down Menus'!A2 -> Groceries | K3: =SUMIF($F$4:$F$17,$J3,$G$4:$G$17) -> 138.79
B4: Kwik Trip | E4: 45048 | F4: Cigarettes | G4: 14.53 | H4: =G4 -> 14.53 | J4: ='08) Drop Down Menus'!A3 -> Cigarettes | K4: =SUMIF($F$4:$F$17,$J4,$G$4:$G$17) -> 14.53
B5: Scott's Vending | E5: 45048 | F5: Groceries | G5: 3.68 | H5: =H4+G5 -> 18.21 | J5: ='08) Drop Down Menus'!A4 -> Gas | K5: =SUMIF($F$4:$F$17,$J5,$G$4:$G$17) -> 0
B6: Wal-Mart | E6: 45044 | F6: Groceries | G6: 135.11 | H6: =H5+G6 -> 153.32 | J6: ='08) Drop Down Menus'!A5 -> Entertainment | K6: =SUMIF($F$4:$F$17,$J6,$G$4:$G$17) -> 0
G7: 0 | H7: =H6+G7 -> 153.32 | J7: ='08) Drop Down Menus'!A6 -> Medical | K7: =SUMIF($F$4:$F$17,$J7,$G$4:$G$17) -> 0
G8: 0 | H8: =H7+G8 -> 153.32 | J8: ='08) Drop Down Menus'!A7 -> Vehicle | K8: =SUMIF($F$4:$F$17,$J8,$G$4:$G$17) -> 0
G9: 0 | H9: =H8+G9 -> 153.32 | J9: ='08) Drop Down Menus'!A8 -> Maintenance | K9: =SUMIF($F$4:$F$17,$J9,$G$4:$G$17) -> 0
G10: 0 | H10: =H9+G10 -> 153.32 | J10: ='08) Drop Down Menus'!A9 -> Debt | K10: =SUMIF($F$4:$F$17,$J10,$G$4:$G$17) -> 0
G11: 0 | H11: =H10+G11 -> 153.32
G12: 0 | H12: =H11+G12 -> 153.32 | J12: Catagory YTD Totals | L12: Average (08/26)
G13: 0 | H13: =H12+G13 -> 153.32 | J13: ='08) Drop Down Menus'!A2 -> Groceries | K13: =K3+'2023 Expences - 04072023'!K13 -> 1586.37 | L13: =K13/8 -> 198.29625
G14: 0 | H14: =H13+G14 -> 153.32 | J14: ='08) Drop Down Menus'!A3 -> Cigarettes | K14: =K4+'2023 Expences - 04072023'!K14 -> 344.79 | L14: =K14/8 -> 43.09875
G15: 0 | H15: =H14+G15 -> 153.32 | J15: ='08) Drop Down Menus'!A4 -> Gas | K15: =K5+'2023 Expences - 04072023'!K15 -> 219.82 | L15: =K15/8 -> 27.4775
G16: 0 | H16: =H15+G16 -> 153.32 | J16: ='08) Drop Down Menus'!A5 -> Entertainment | K16: =K6+'2023 Expences - 04072023'!K16 -> 393.01 | L16: =K16/8 -> 49.12625
G17: 0 | H17: =H16+G17 -> 153.32 | J17: ='08) Drop Down Menus'!A6 -> Medical | K17: =K7+'2023 Expences - 04072023'!K17 -> 125.76 | L17: =K17/8 -> 15.72
B18: Expence Grand Total | G18: =H17 -> 153.32 | J18: ='08) Drop Down Menus'!A7 -> Vehicle | K18: =K8+'2023 Expences - 04072023'!K18 -> 115.47 | L18: =K18/8 -> 14.43375
J19: ='08) Drop Down Menus'!A8 -> Maintenance | K19: =K9+'2023 Expences - 04072023'!K19 -> 351.07 | L19: =K19/8 -> 43.88375
J20: ='08) Drop Down Menus'!A9 -> Debt | K20: =K10+'2023 Expences - 04072023'!K20 -> 314.86 | L20: =K20/8 -> 39.3575

Sheet 2023 Expences - 05052023
B2: Expences for Paycheck 5/05/2023 | J2: Catagory Totals
B3: Expence | E3: Date | F3: Catagory | G3: Cost | H3: Total | J3: ='08) Drop Down Menus'!A2 -> Groceries | K3: =SUMIF($F$4:$F$17,$J3,$G$4:$G$17) -> 201.54
B4: Wal-Mart | E4: 45060 | F4: Groceries | G4: 45.18 | H4: =G4 -> 45.18 | J4: ='08) Drop Down Menus'!A3 -> Cigarettes | K4: =SUMIF($F$4:$F$17,$J4,$G$4:$G$17) -> 61.51
B5: Marathon | E5: 45059 | F5: Cigarettes | G5: 30.6 | H5: =H4+G5 -> 75.78 | J5: ='08) Drop Down Menus'!A4 -> Gas | K5: =SUMIF($F$4:$F$17,$J5,$G$4:$G$17) -> 36.79
B6: CVS | E6: 45057 | F6: Medical | G6: 6.46 | H6: =H5+G6 -> 82.24 | J6: ='08) Drop Down Menus'!A5 -> Entertainment | K6: =SUMIF($F$4:$F$17,$J6,$G$4:$G$17) -> 0
B7: Dairy Queen | E7: 45057 | F7: Groceries | G7: 6.5 | H7: =H6+G7 -> 88.74 | J7: ='08) Drop Down Menus'!A6 -> Medical | K7: =SUMIF($F$4:$F$17,$J7,$G$4:$G$17) -> 56.46
B8: Scott's Vending | E8: 45056 | F8: Groceries | G8: 2.05 | H8: =H7+G8 -> 90.79 | J8: ='08) Drop Down Menus'!A7 -> Vehicle | K8: =SUMIF($F$4:$F$17,$J8,$G$4:$G$17) -> 0
B9: Kwik Trip (Laundry Coins) | E9: 45055 | F9: Maintenance | G9: 12 | H9: =H8+G9 -> 102.79 | J9: ='08) Drop Down Menus'!A8 -> Maintenance | K9: =SUMIF($F$4:$F$17,$J9,$G$4:$G$17) -> 12
B10: CVS | E10: 45054 | F10: Medical | G10: 10 | H10: =H9+G10 -> 112.79 | J10: ='08) Drop Down Menus'!A9 -> Debt | K10: =SUMIF($F$4:$F$17,$J10,$G$4:$G$17) -> 0
B11: BP Gas Station | E11: 45053 | F11: Cigarettes | G11: 30.91 | H11: =H10+G11 -> 143.7
B12: BP Gas Station | E12: 45053 | F12: Gas | G12: 36.79 | H12: =H11+G12 -> 180.49 | J12: Catagory YTD Totals | L12: Average (09/26)
B13: Wal-Mart | E13: 45053 | F13: Groceries | G13: =145.42+2.39 -> 147.81 | H13: =H12+G13 -> 328.3 | J13: ='08) Drop Down Menus'!A2 -> Groceries | K13: =K3+'2023 Expences - 04072023'!K13 -> 1649.12 | L13: =K13/9 -> 183.23556
B14: CVS | E14: 45053 | F14: Medical | G14: 40 | H14: =H13+G14 -> 368.3 | J14: ='08) Drop Down Menus'!A3 -> Cigarettes | K14: =K4+'2023 Expences - 04072023'!K14 -> 391.77 | L14: =K14/9 -> 43.53
G15: 0 | H15: =H14+G15 -> 368.3 | J15: ='08) Drop Down Menus'!A4 -> Gas | K15: =K5+'2023 Expences - 04072023'!K15 -> 256.61 | L15: =K15/9 -> 28.512222
G16: 0 | H16: =H15+G16 -> 368.3 | J16: ='08) Drop Down Menus'!A5 -> Entertainment | K16: =K6+'2023 Expences - 04072023'!K16 -> 393.01 | L16: =K16/9 -> 43.667778
G17: 0 | H17: =H16+G17 -> 368.3 | J17: ='08) Drop Down Menus'!A6 -> Medical | K17: =K7+'2023 Expences - 04072023'!K17 -> 182.22 | L17: =K17/9 -> 20.246667
B18: Expence Grand Total | G18: =H17 -> 368.3 | J18: ='08) Drop Down Menus'!A7 -> Vehicle | K18: =K8+'2023 Expences - 04072023'!K18 -> 115.47 | L18: =K18/9 -> 12.83
J19: ='08) Drop Down Menus'!A8 -> Maintenance | K19: =K9+'2023 Expences - 04072023'!K19 -> 363.07 | L19: =K19/9 -> 40.341111
J20: ='08) Drop Down Menus'!A9 -> Debt | K20: =K10+'2023 Expences - 04072023'!K20 -> 314.86 | L20: =K20/9 -> 34.984444

Sheet 2023 Expences - 05192023
B2: Expences for Paycheck 5/19/2023 | J2: Catagory Totals
B3: Expence | E3: Date | F3: Catagory | G3: Cost | H3: Total | J3: ='08) Drop Down Menus'!A2 -> Groceries | K3: =SUMIF($F$4:$F$20,$J3,$G$4:$G$20) -> 329.54
B4: MDG | E4: 45065 | F4: Debt | G4: 8.94 | H4: =G4 -> 8.94 | J4: ='08) Drop Down Menus'!A3 -> Cigarettes | K4: =SUMIF($F$4:$F$20,$J4,$G$4:$G$20) -> 65.24
B5: Kwik Trip | E5: 45065 | F5: Cigarettes | G5: 14.53 | H5: =H4+G5 -> 23.47 | J5: ='08) Drop Down Menus'!A4 -> Gas | K5: =SUMIF($F$4:$F$20,$J5,$G$4:$G$20) -> 19.54
B6: Harbor Freight | E6: 45065 | F6: Maintenance | G6: 64.81 | H6: =H5+G6 -> 88.28 | J6: ='08) Drop Down Menus'!A5 -> Entertainment | K6: =SUMIF($F$4:$F$20,$J6,$G$4:$G$20) -> 10.49
B7: Car Wash | E7: 45067 | F7: Vehicle | G7: 15.5 | H7: =H6+G7 -> 103.78 | J7: ='08) Drop Down Menus'!A6 -> Medical | K7: =SUMIF($F$4:$F$20,$J7,$G$4:$G$20) -> 0
B8: Laundry Change | E8: 45067 | F8: Maintenance | G8: 20 | H8: =H7+G8 -> 123.78 | J8: ='08) Drop Down Menus'!A7 -> Vehicle | K8: =SUMIF($F$4:$F$20,$J8,$G$4:$G$20) -> 15.5
B9: Wal-Mart | E9: 45067 | F9: Groceries | G9: 157.58 | H9: =H8+G9 -> 281.36 | J9: ='08) Drop Down Menus'!A8 -> Maintenance | K9: =SUMIF($F$4:$F$20,$J9,$G$4:$G$20) -> 110.07
B10: Smart Style | E10: 45069 | F10: Maintenance | G10: 25.26 | H10: =H9+G10 -> 306.62 | J10: ='08) Drop Down Menus'!A9 -> Debt | K10: =SUMIF($F$4:$F$20,$J10,$G$4:$G$20) -> 8.94
B11: Wal-Mart | E11: 45069 | F11: Groceries | G11: 31.44 | H11: =H10+G11 -> 338.06
B12: Kwik Trip | E12: 45071 | F12: Gas | G12: 19.54 | H12: =H11+G12 -> 357.6 | J12: Catagory | K12: YTD Totals | L12: Average (10/26)
B13: Kwik Trip | E13: 45071 | F13: Cigarettes | G13: 24.53 | H13: =H12+G13 -> 382.13 | J13: ='08) Drop Down Menus'!A2 -> Groceries | K13: =K3+'2023 Expences - 05052023'!K13 -> 1978.66 | L13: =K13/10 -> 197.866
B14: Microsoft Game Pass | E14: 45073 | F14: Entertainment | G14: 10.49 | H14: =H13+G14 -> 392.62 | J14: ='08) Drop Down Menus'!A3 -> Cigarettes | K14: =K4+'2023 Expences - 05052023'!K14 -> 457.01 | L14: =K14/10 -> 45.701
B15: Kwik Trip | E15: 45075 | F15: Cigarettes | G15: 26.18 | H15: =H14+G15 -> 418.8 | J15: ='08) Drop Down Menus'!A4 -> Gas | K15: =K5+'2023 Expences - 05052023'!K15 -> 276.15 | L15: =K15/10 -> 27.615
B16: Wal-Mart | E16: 45075 | F16: Groceries | G16: 140.52 | H16: =H15+G16 -> 559.32 | J16: ='08) Drop Down Menus'!A5 -> Entertainment | K16: =K6+'2023 Expences - 05052023'!K16 -> 403.5 | L16: =K16/10 -> 40.35
G17: 0 | H17: =H16+G17 -> 559.32 | J17: ='08) Drop Down Menus'!A6 -> Medical | K17: =K7+'2023 Expences - 05052023'!K17 -> 182.22 | L17: =K17/10 -> 18.222
G18: 0 | H18: =H17+G18 -> 559.32 | J18: ='08) Drop Down Menus'!A7 -> Vehicle | K18: =K8+'2023 Expences - 05052023'!K18 -> 130.97 | L18: =K18/10 -> 13.097
G19: 0 | H19: =H18+G19 -> 559.32 | J19: ='08) Drop Down Menus'!A8 -> Maintenance | K19: =K9+'2023 Expences - 05052023'!K19 -> 473.14 | L19: =K19/10 -> 47.314
G20: 0 | H20: =H19+G20 -> 559.32 | J20: ='08) Drop Down Menus'!A9 -> Debt | K20: =K10+'2023 Expences - 05052023'!K20 -> 323.8 | L20: =K20/10 -> 32.38
B21: Expence Grand Total | G21: =H20 -> 559.32 | J21: TOTAL | K21: =SUM(K13:K20) -> 4225.45 | L21: =K21/10 -> 422.545

Sheet 2023 Expences - 06022023
B2: Expences for Paycheck 5/19/2023 | J2: Catagory Totals
B3: Expence | E3: Date | F3: Catagory | G3: Cost | H3: Total | J3: ='08) Drop Down Menus'!A2 -> Groceries | K3: =SUMIF($F$4:$F$20,$J3,$G$4:$G$20) -> 209.93
B4: MDG | E4: 45079 | F4: Debt | G4: 8.95 | H4: =G4 -> 8.95 | J4: ='08) Drop Down Menus'!A3 -> Cigarettes | K4: =SUMIF($F$4:$F$20,$J4,$G$4:$G$20) -> 48.28
B5: Wal Mart | E5: 45081 | F5: Groceries | G5: 154.11 | H5: =H4+G5 -> 163.06 | J5: ='08) Drop Down Menus'!A4 -> Gas | K5: =SUMIF($F$4:$F$20,$J5,$G$4:$G$20) -> 0
B6: Marathon | E6: 45081 | F6: Cigarettes | G6: 30.6 | H6: =H5+G6 -> 193.66 | J6: ='08) Drop Down Menus'!A5 -> Entertainment | K6: =SUMIF($F$4:$F$20,$J6,$G$4:$G$20) -> 0
B7: CVS (Vyvanse) | E7: 45085 | F7: Medical | G7: 30 | H7: =H6+G7 -> 223.66 | J7: ='08) Drop Down Menus'!A6 -> Medical | K7: =SUMIF($F$4:$F$20,$J7,$G$4:$G$20) -> 30
B8: Kwik-Trip | E8: 45087 | F8: Cigarettes | G8: 17.68 | H8: =H7+G8 -> 241.34 | J8: ='08) Drop Down Menus'!A7 -> Vehicle | K8: =SUMIF($F$4:$F$20,$J8,$G$4:$G$20) -> 13.35
B9: Kwik-Trip | E9: 45089 | F9: Vehicle | G9: 13.35 | H9: =H8+G9 -> 254.69 | J9: ='08) Drop Down Menus'!A8 -> Maintenance | K9: =SUMIF($F$4:$F$20,$J9,$G$4:$G$20) -> 0
B10: Wal Mart | E10: 45088 | F10: Groceries | G10: 55.82 | H10: =H9+G10 -> 310.51 | J10: ='08) Drop Down Menus'!A9 -> Debt | K10: =SUMIF($F$4:$F$20,$J10,$G$4:$G$20) -> 17.9
B11: MDG | E11: 45088 | F11: Debt | G11: 8.95 | H11: =H10+G11 -> 319.46
G12: 0 | H12: =H11+G12 -> 319.46 | J12: Catagory | K12: YTD Totals | L12: Average (11/26)
G13: 0 | H13: =H12+G13 -> 319.46 | J13: ='08) Drop Down Menus'!A2 -> Groceries | K13: =K3+'2023 Expences - 05192023'!K13 -> 2188.59 | L13: =K13/11 -> 198.96273
G14: 0 | H14: =H13+G14 -> 319.46 | J14: ='08) Drop Down Menus'!A3 -> Cigarettes | K14: =K4+'2023 Expences - 05192023'!K14 -> 505.29 | L14: =K14/11 -> 45.935455
G15: 0 | H15: =H14+G15 -> 319.46 | J15: ='08) Drop Down Menus'!A4 -> Gas | K15: =K5+'2023 Expences - 05192023'!K15 -> 276.15 | L15: =K15/11 -> 25.104545
G16: 0 | H16: =H15+G16 -> 319.46 | J16: ='08) Drop Down Menus'!A5 -> Entertainment | K16: =K6+'2023 Expences - 05192023'!K16 -> 403.5 | L16: =K16/11 -> 36.681818
G17: 0 | H17: =H16+G17 -> 319.46 | J17: ='08) Drop Down Menus'!A6 -> Medical | K17: =K7+'2023 Expences - 05192023'!K17 -> 212.22 | L17: =K17/11 -> 19.292727
G18: 0 | H18: =H17+G18 -> 319.46 | J18: ='08) Drop Down Menus'!A7 -> Vehicle | K18: =K8+'2023 Expences - 05192023'!K18 -> 144.32 | L18: =K18/11 -> 13.12
G19: 0 | H19: =H18+G19 -> 319.46 | J19: ='08) Drop Down Menus'!A8 -> Maintenance | K19: =K9+'2023 Expences - 05192023'!K19 -> 473.14 | L19: =K19/11 -> 43.012727
G20: 0 | H20: =H19+G20 -> 319.46 | J20: ='08) Drop Down Menus'!A9 -> Debt | K20: =K10+'2023 Expences - 05192023'!K20 -> 341.7 | L20: =K20/11 -> 31.063636
B21: Expence Grand Total | G21: =H20 -> 319.46 | J21: TOTAL | K21: =SUM(K13:K20) -> 4544.91 | L21: =K21/10 -> 454.491

Sheet 2023 Expences - 06162023
B2: Expences for Paycheck 6/16/2023 | J2: Catagory Totals
B3: Expence | E3: Date | F3: Catagory | G3: Cost | H3: Total | J3: ='08) Drop Down Menus'!A2 -> Groceries | K3: =SUMIF($F$4:$F$20,$J3,$G$4:$G$20) -> 478.33
B4: Wal-Mart | E4: 45094 | F4: Groceries | G4: 108.07 | H4: =G4 -> 108.07 | J4: ='08) Drop Down Menus'!A3 -> Cigarettes | K4: =SUMIF($F$4:$F$20,$J4,$G$4:$G$20) -> 37.68
B5: MDG | E5: 45094 | F5: Debt | G5: 8.95 | H5: =H4+G5 -> 117.02 | J5: ='08) Drop Down Menus'!A4 -> Gas | K5: =SUMIF($F$4:$F$20,$J5,$G$4:$G$20) -> 20.57
B6: Kwik-Trip | E6: 45096 | F6: Cigarettes | G6: 17.68 | H6: =H5+G6 -> 134.7 | J6: ='08) Drop Down Menus'!A5 -> Entertainment | K6: =SUMIF($F$4:$F$20,$J6,$G$4:$G$20) -> 73.49
B7: Diablo 4 | E7: 45098 | F7: Entertainment | G7: 73.49 | H7: =H6+G7 -> 208.19 | J7: ='08) Drop Down Menus'!A6 -> Medical | K7: =SUMIF($F$4:$F$20,$J7,$G$4:$G$20) -> 0
B8: Wal-Mart (Mouse / Broom) | E8: 45098 | F8: Maintenance | G8: 62.92 | H8: =H7+G8 -> 271.11 | J8: ='08) Drop Down Menus'!A7 -> Vehicle | K8: =SUMIF($F$4:$F$20,$J8,$G$4:$G$20) -> 0
B9: Festival | E9: 45102 | F9: Groceries | G9: 65.47 | H9: =H8+G9 -> 336.58 | J9: ='08) Drop Down Menus'!A8 -> Maintenance | K9: =SUMIF($F$4:$F$20,$J9,$G$4:$G$20) -> 127.52
B10: Wal-Mart | E10: 45102 | F10: Groceries | G10: 304.79 | H10: =H9+G10 -> 641.37 | J10: ='08) Drop Down Menus'!A9 -> Debt | K10: =SUMIF($F$4:$F$20,$J10,$G$4:$G$20) -> 8.95
B11: Wal-Mart (Light Bulbs) | E11: 45102 | F11: Maintenance | G11: 64.6 | H11: =H10+G11 -> 705.97
B12: Mobile | E12: 45101 | F12: Cigarettes | G12: 20 | H12: =H11+G12 -> 725.97 | J12: Catagory | K12: YTD | L12: Average
B13: Mobile | E13: 45101 | F13: Gas | G13: 20.57 | H13: =H12+G13 -> 746.54 | J13: ='08) Drop Down Menus'!A2 -> Groceries | K13: =K3+'2023 Expences - 06022023'!K13 -> 2666.92 | L13: =K13/L$21 -> 222.24333
G14: 0 | H14: =H13+G14 -> 746.54 | J14: ='08) Drop Down Menus'!A3 -> Cigarettes | K14: =K4+'2023 Expences - 06022023'!K14 -> 542.97 | L14: =K14/L$21 -> 45.2475
G15: 0 | H15: =H14+G15 -> 746.54 | J15: ='08) Drop Down Menus'!A4 -> Gas | K15: =K5+'2023 Expences - 06022023'!K15 -> 296.72 | L15: =K15/L$21 -> 24.726667
G16: 0 | H16: =H15+G16 -> 746.54 | J16: ='08) Drop Down Menus'!A5 -> Entertainment | K16: =K6+'2023 Expences - 06022023'!K16 -> 476.99 | L16: =K16/L$21 -> 39.749167
G17: 0 | H17: =H16+G17 -> 746.54 | J17: ='08) Drop Down Menus'!A6 -> Medical | K17: =K7+'2023 Expences - 06022023'!K17 -> 212.22 | L17: =K17/L$21 -> 17.685
G18: 0 | H18: =H17+G18 -> 746.54 | J18: ='08) Drop Down Menus'!A7 -> Vehicle | K18: =K8+'2023 Expences - 06022023'!K18 -> 144.32 | L18: =K18/L$21 -> 12.026667
G19: 0 | H19: =H17+G19 -> 746.54 | J19: ='08) Drop Down Menus'!A8 -> Maintenance | K19: =K9+'2023 Expences - 06022023'!K19 -> 600.66 | L19: =K19/L$21 -> 50.055
G20: 0 | H20: =H19+G20 -> 746.54 | J20: ='08) Drop Down Menus'!A9 -> Debt | K20: =K10+'2023 Expences - 06022023'!K20 -> 350.65 | L20: =K20/L$21 -> 29.220833
B21: Expence Grand Total | G21: =H20 -> 746.54 | J21: Paycheck Number | L21: 12

Sheet 2023 Expences - 06302023
B2: Expences for Paycheck 6/30/2023 | J2: Catagory Totals
B3: Expence | E3: Date | F3: Catagory | G3: Cost | H3: Total | J3: ='08) Drop Down Menus'!A2 -> Groceries | K3: =SUMIF($F$4:$F$20,$J3,$G$4:$G$20) -> 325.22
B4: Nexus Mods | E4: 45108 | F4: Entertainment | G4: 6.33 | H4: =G4 -> 6.33 | J4: ='08) Drop Down Menus'!A3 -> Cigarettes | K4: =SUMIF($F$4:$F$20,$J4,$G$4:$G$20) -> 64.81
B5: CVS (Venlafaxine, Hydroxizine) | E5: 45108 | F5: Medical | G5: 46.6 | H5: =H4+G5 -> 52.93 | J5: ='08) Drop Down Menus'!A4 -> Gas | K5: =SUMIF($F$4:$F$20,$J5,$G$4:$G$20) -> 31.14
B6: Kwik Trip | E6: 45108 | F6: Gas | G6: 31.14 | H6: =H5+G6 -> 84.07 | J6: ='08) Drop Down Menus'!A5 -> Entertainment | K6: =SUMIF($F$4:$F$20,$J6,$G$4:$G$20) -> 24.48
B7: Kwik Trip | E7: 45108 | F7: Cigarettes | G7: 28.73 | H7: =H6+G7 -> 112.8 | J7: ='08) Drop Down Menus'!A6 -> Medical | K7: =SUMIF($F$4:$F$20,$J7,$G$4:$G$20) -> 61.6
B8: Steam (Skyrim VR) | E8: 45109 | F8: Entertainment | G8: 18.15 | H8: =H7+G8 -> 130.95 | J8: ='08) Drop Down Menus'!A7 -> Vehicle | K8: =SUMIF($F$4:$F$20,$J8,$G$4:$G$20) -> 0
B9: Walmart | E9: 45109 | F9: Groceries | G9: 243.46 | H9: =H8+G9 -> 374.41 | J9: ='08) Drop Down Menus'!A8 -> Maintenance | K9: =SUMIF($F$4:$F$20,$J9,$G$4:$G$20) -> 0
B10: Kwik Trip | E10: 45113 | F10: Cigarettes | G10: 18.04 | H10: =H9+G10 -> 392.45 | J10: ='08) Drop Down Menus'!A9 -> Debt | K10: =SUMIF($F$4:$F$20,$J10,$G$4:$G$20) -> 0
B11: Dominoes | E11: 45113 | F11: Groceries | G11: 33.43 | H11: =H10+G11 -> 425.88
B12: CVS (Vyvanse) | E12: 45116 | F12: Medical | G12: 15 | H12: =H11+G12 -> 440.88 | J12: Catagory | K12: YTD | L12: Average
B13: Kwik Trip | E13: 45119 | F13: Cigarettes | G13: 18.04 | H13: =H12+G13 -> 458.92 | J13: ='08) Drop Down Menus'!A2 -> Groceries | K13: =K3+'2023 Expences - 06162023'!K13 -> 2992.14 | L13: =K13/L$21 -> 230.16462
B14: Walmart | E14: 45120 | F14: Groceries | G14: 48.33 | H14: =H13+G14 -> 507.25 | J14: ='08) Drop Down Menus'!A3 -> Cigarettes | K14: =K4+'2023 Expences - 06162023'!K14 -> 607.78 | L14: =K14/L$21 -> 46.752308
G15: 0 | H15: =H14+G15 -> 507.25 | J15: ='08) Drop Down Menus'!A4 -> Gas | K15: =K5+'2023 Expences - 06162023'!K15 -> 327.86 | L15: =K15/L$21 -> 25.22
G16: 0 | H16: =H15+G16 -> 507.25 | J16: ='08) Drop Down Menus'!A5 -> Entertainment | K16: =K6+'2023 Expences - 06162023'!K16 -> 501.47 | L16: =K16/L$21 -> 38.574615
G17: 0 | H17: =H16+G17 -> 507.25 | J17: ='08) Drop Down Menus'!A6 -> Medical | K17: =K7+'2023 Expences - 06162023'!K17 -> 273.82 | L17: =K17/L$21 -> 21.063077
G18: 0 | H18: =H17+G18 -> 507.25 | J18: ='08) Drop Down Menus'!A7 -> Vehicle | K18: =K8+'2023 Expences - 06162023'!K18 -> 144.32 | L18: =K18/L$21 -> 11.101538
G19: 0 | H19: =H17+G19 -> 507.25 | J19: ='08) Drop Down Menus'!A8 -> Maintenance | K19: =K9+'2023 Expences - 06162023'!K19 -> 600.66 | L19: =K19/L$21 -> 46.204615
G20: 0 | H20: =H19+G20 -> 507.25 | J20: ='08) Drop Down Menus'!A9 -> Debt | K20: =K10+'2023 Expences - 06162023'!K20 -> 350.65 | L20: =K20/L$21 -> 26.973077
B21: Expence Grand Total | G21: =H20 -> 507.25 | J21: Paycheck Number | L21: 13

Sheet 2023 Expences - 07142023
B2: Expences for Paycheck 7/14/2023 | J2: Catagory Totals
B3: Expence | E3: Date | F3: Catagory | G3: Cost | H3: Total | J3: ='08) Drop Down Menus'!A2 -> Groceries | K3: =SUMIF($F$4:$F$20,$J3,$G$4:$G$20) -> 262.07
B4: Hims | E4: 45122 | F4: Medical | G4: 65 | H4: =G4 -> 65 | J4: ='08) Drop Down Menus'!A3 -> Cigarettes | K4: =SUMIF($F$4:$F$20,$J4,$G$4:$G$20) -> 57.4
B5: Aurora | E5: 45124 | F5: Medical | G5: 50 | H5: =H4+G5 -> 115 | J5: ='08) Drop Down Menus'!A4 -> Gas | K5: =SUMIF($F$4:$F$20,$J5,$G$4:$G$20) -> 0
B6: ATM Withdrawl (Laundry Money) | E6: 45124 | F6: Maintenance | G6: 23 | H6: =H5+G6 -> 138 | J6: ='08) Drop Down Menus'!A5 -> Entertainment | K6: =SUMIF($F$4:$F$20,$J6,$G$4:$G$20) -> 5.57
B7: Wal-Mart (Groceries) | E7: 45124 | F7: Groceries | G7: 134.44 | H7: =H6+G7 -> 272.44 | J7: ='08) Drop Down Menus'!A6 -> Medical | K7: =SUMIF($F$4:$F$20,$J7,$G$4:$G$20) -> 115
B8: Wal-Mart (Furnishings) | E8: 45124 | F8: Maintenance | G8: 50 | H8: =H7+G8 -> 322.44 | J8: ='08) Drop Down Menus'!A7 -> Vehicle | K8: =SUMIF($F$4:$F$20,$J8,$G$4:$G$20) -> 0
B9: Smart-Style (Hair Cut) | E9: 45124 | F9: Maintenance | G9: 25.27 | H9: =H8+G9 -> 347.71 | J9: ='08) Drop Down Menus'!A8 -> Maintenance | K9: =SUMIF($F$4:$F$20,$J9,$G$4:$G$20) -> 182.83
B10: Citco | E10: 45124 | F10: Cigarettes | G10: 19.82 | H10: =H9+G10 -> 367.53 | J10: ='08) Drop Down Menus'!A9 -> Debt | K10: =SUMIF($F$4:$F$20,$J10,$G$4:$G$20) -> 0
B11: Harbor Freight | E11: 45127 | F11: Maintenance | G11: 10.49 | H11: =H10+G11 -> 378.02
B12: Kwik Trip | E12: 45128 | F12: Cigarettes | G12: 28.04 | H12: =H11+G12 -> 406.06 | J12: Catagory | K12: YTD | L12: Average
B13: Mega | E13: 45129 | F13: Entertainment | G13: 5.57 | H13: =H12+G13 -> 411.63 | J13: ='08) Drop Down Menus'!A2 -> Groceries | K13: =K3+'2023 Expences - 06162023'!K13 -> 2928.99 | L13: =K13/L$21 -> 209.21357
B14: Wal-Mart | E14: 45130 | F14: Groceries | G14: 78.08 | H14: =H13+G14 -> 489.71 | J14: ='08) Drop Down Menus'!A3 -> Cigarettes | K14: =K4+'2023 Expences - 06162023'!K14 -> 600.37 | L14: =K14/L$21 -> 42.883571
B15: Green Street | E15: 45131 | F15: Groceries | G15: 49.55 | H15: =H14+G15 -> 539.26 | J15: ='08) Drop Down Menus'!A4 -> Gas | K15: =K5+'2023 Expences - 06162023'!K15 -> 296.72 | L15: =K15/L$21 -> 21.194286
B16: Amazon (Watch Stuff) | E16: 45132 | F16: Maintenance | G16: 44.07 | H16: =H15+G16 -> 583.33 | J16: ='08) Drop Down Menus'!A5 -> Entertainment | K16: =K6+'2023 Expences - 06162023'!K16 -> 482.56 | L16: =K16/L$21 -> 34.468571
B17: Quik Trip | E17: 45133 | F17: Cigarettes | G17: 9.54 | H17: =H16+G17 -> 592.87 | J17: ='08) Drop Down Menus'!A6 -> Medical | K17: =K7+'2023 Expences - 06162023'!K17 -> 327.22 | L17: =K17/L$21 -> 23.372857
B18: ATM Withdrawl (Deanna) | E18: 45133 | F18: Maintenance | G18: 40 | H18: =H17+G18 -> 632.87 | J18: ='08) Drop Down Menus'!A7 -> Vehicle | K18: =K8+'2023 Expences - 06162023'!K18 -> 144.32 | L18: =K18/L$21 -> 10.308571
B19: Adjustment | E19: 45135 | F19: Maintenance | G19: -10 | H19: =H17+G19 -> 582.87 | J19: ='08) Drop Down Menus'!A8 -> Maintenance | K19: =K9+'2023 Expences - 06162023'!K19 -> 783.49 | L19: =K19/L$21 -> 55.963571
G20: 0 | H20: =H19+G20 -> 582.87 | J20: ='08) Drop Down Menus'!A9 -> Debt | K20: =K10+'2023 Expences - 06162023'!K20 -> 350.65 | L20: =K20/L$21 -> 25.046429
B21: Expence Grand Total | G21: =H20 -> 582.87 | J21: Paycheck Number | L21: 14

Sheet 2023 Expences - 07282023
B2: Expences for Paycheck 7/28/2023 | J2: Catagory Totals
B3: Expence | E3: Date | F3: Catagory | G3: Cost | H3: Total | J3: ='08) Drop Down Menus'!A2 -> Groceries | K3: =SUMIF($F$4:$F$20,$J3,$G$4:$G$20) -> 134.05
B4: Nexus Mods | E4: 45138 | F4: Entertainment | G4: 6.44 | H4: =G4 -> 6.44 | J4: ='08) Drop Down Menus'!A3 -> Cigarettes | K4: =SUMIF($F$4:$F$20,$J4,$G$4:$G$20) -> 68.73
B5: Kwik Trip | E5: 45136 | F5: Cigarettes | G5: 28.04 | H5: =H4+G5 -> 34.48 | J5: ='08) Drop Down Menus'!A4 -> Gas | K5: =SUMIF($F$4:$F$20,$J5,$G$4:$G$20) -> 0
B6: Blizzard Entertainment | E6: 45147 | F6: Entertainment | G6: 10.45 | H6: =H5+G6 -> 44.93 | J6: ='08) Drop Down Menus'!A5 -> Entertainment | K6: =SUMIF($F$4:$F$20,$J6,$G$4:$G$20) -> 16.89
B7: Kwik Trip | E7: 45146 | F7: Cigarettes | G7: 20.87 | H7: =H6+G7 -> 65.8 | J7: ='08) Drop Down Menus'!A6 -> Medical | K7: =SUMIF($F$4:$F$20,$J7,$G$4:$G$20) -> 0
B8: Citco | E8: 45141 | F8: Cigarettes | G8: 19.82 | H8: =H7+G8 -> 85.62 | J8: ='08) Drop Down Menus'!A7 -> Vehicle | K8: =SUMIF($F$4:$F$20,$J8,$G$4:$G$20) -> 0
B9: Walmart | E9: 45139 | F9: Groceries | G9: 134.05 | H9: =H8+G9 -> 219.67 | J9: ='08) Drop Down Menus'!A8 -> Maintenance | K9: =SUMIF($F$4:$F$20,$J9,$G$4:$G$20) -> 0
G10: 0 | H10: =H9+G10 -> 219.67 | J10: ='08) Drop Down Menus'!A9 -> Debt | K10: =SUMIF($F$4:$F$20,$J10,$G$4:$G$20) -> 0
G11: 0 | H11: =H10+G11 -> 219.67
G12: 0 | H12: =H11+G12 -> 219.67 | J12: Catagory | K12: YTD | L12: Average
G13: 0 | H13: =H12+G13 -> 219.67 | J13: ='08) Drop Down Menus'!A2 -> Groceries | K13: =K3+'2023 Expences - 06162023'!K13 -> 2800.97 | L13: =K13/L$21 -> 186.73133
G14: 0 | H14: =H13+G14 -> 219.67 | J14: ='08) Drop Down Menus'!A3 -> Cigarettes | K14: =K4+'2023 Expences - 06162023'!K14 -> 611.7 | L14: =K14/L$21 -> 40.78
G15: 0 | H15: =H14+G15 -> 219.67 | J15: ='08) Drop Down Menus'!A4 -> Gas | K15: =K5+'2023 Expences - 06162023'!K15 -> 296.72 | L15: =K15/L$21 -> 19.781333
G16: 0 | H16: =H15+G16 -> 219.67 | J16: ='08) Drop Down Menus'!A5 -> Entertainment | K16: =K6+'2023 Expences - 06162023'!K16 -> 493.88 | L16: =K16/L$21 -> 32.925333
G17: 0 | H17: =H16+G17 -> 219.67 | J17: ='08) Drop Down Menus'!A6 -> Medical | K17: =K7+'2023 Expences - 06162023'!K17 -> 212.22 | L17: =K17/L$21 -> 14.148
G18: 0 | H18: =H17+G18 -> 219.67 | J18: ='08) Drop Down Menus'!A7 -> Vehicle | K18: =K8+'2023 Expences - 06162023'!K18 -> 144.32 | L18: =K18/L$21 -> 9.6213333
G19: 0 | H19: =H17+G19 -> 219.67 | J19: ='08) Drop Down Menus'!A8 -> Maintenance | K19: =K9+'2023 Expences - 06162023'!K19 -> 600.66 | L19: =K19/L$21 -> 40.044
G20: 0 | H20: =H19+G20 -> 219.67 | J20: ='08) Drop Down Menus'!A9 -> Debt | K20: =K10+'2023 Expences - 06162023'!K20 -> 350.65 | L20: =K20/L$21 -> 23.376667
B21: Expence Grand Total | G21: =H20 -> 219.67 | J21: Paycheck Number | L21: 15

Sheet 2023 Expences - 08112023
B2: Expences for Paycheck 8/11/2023 | K2: Catagory Totals
B3: CC | C3: Expence | F3: Date | G3: Catagory | H3: Cost | I3: Total | K3: ='08) Drop Down Menus'!A2 -> Groceries | L3: =sumifs(H$4:H$26,G$4:G$26,K3,B$4:B$26,false) -> 99.78
B4: FALSE | C4: Deanne Payment | F4: 45149 | G4: Debt | H4: 82 | I4: =H4 -> 82 | K4: ='08) Drop Down Menus'!A3 -> Cigarettes | L4: =sumifs(H$4:H$26,G$4:G$26,K4,B$4:B$26,false) -> 48.79
B5: FALSE | C5: MDG | F5: 45149 | G5: Debt | H5: 8.95 | I5: =I4+H5 -> 90.95 | K5: ='08) Drop Down Menus'!A4 -> Gas | L5: =sumifs(H$4:H$26,G$4:G$26,K5,B$4:B$26,false) -> 40.69
B6: FALSE | C6: Dairy Queen | F6: 45149 | G6: Groceries | H6: 10.9 | I6: =I5+H6 -> 101.85 | K6: ='08) Drop Down Menus'!A5 -> Entertainment | L6: =sumifs(H$4:H$26,G$4:G$26,K6,B$4:B$26,false) -> 33.53
B7: FALSE | C7: CVS (Vyvance) | F7: 45149 | G7: Medical | H7: 15 | I7: =I6+H7 -> 116.85 | K7: ='08) Drop Down Menus'!A6 -> Medical | L7: =sumifs(H$4:H$26,G$4:G$26,K7,B$4:B$26,false) -> 15
B8: FALSE | C8: BP Gas Station | F8: 45149 | G8: Cigarettes | H8: 19.15 | I8: =I7+H8 -> 136 | K8: ='08) Drop Down Menus'!A7 -> Vehicle | L8: =sumifs(H$4:H$26,G$4:G$26,K8,B$4:B$26,false) -> 0
B9: FALSE | C9: Wal-Mart | F9: 45150 | G9: Groceries | H9: 88.88 | I9: =I8+H9 -> 224.88 | K9: ='08) Drop Down Menus'!A8 -> Maintenance | L9: =sumifs(H$4:H$26,G$4:G$26,K9,B$4:B$26,false) -> 0
B10: FALSE | C10: MEGA Sub | F10: 45152 | G10: Entertainment | H10: 11.03 | I10: =I9+H10 -> 235.91 | K10: ='08) Drop Down Menus'!A9 -> Debt | L10: =sumifs(H$4:H$26,G$4:G$26,K10,B$4:B$26,false) -> 128.59
B11: FALSE | C11: Mission Lane Credit Card | F11: 45152 | G11: Debt | H11: 37.64 | I11: =I10+H11 -> 273.55
B12: FALSE | C12: Kwik Trip | F12: 45153 | G12: Cigarettes | H12: 29.64 | I12: =I11+H12 -> 303.19 | K12: Catagory | L12: YTD | M12: Average
B13: FALSE | C13: Rusty's | F13: 45157 | G13: Entertainment | H13: 22.5 | I13: =I12+H13 -> 325.69 | K13: ='08) Drop Down Menus'!A2 -> Groceries | L13: =L3+'2023 Expences - 06162023'!K13 -> 2766.7 | M13: =L13/M$21 -> 172.91875
B14: FALSE | C14: Kwik Trip | F14: 45158 | G14: Gas | H14: 40.69 | I14: =I13+H14 -> 366.38 | K14: ='08) Drop Down Menus'!A3 -> Cigarettes | L14: =L4+'2023 Expences - 06162023'!K14 -> 591.76 | M14: =L14/M$21 -> 36.985
B15: FALSE | H15: 0 | I15: =I14+H15 -> 366.38 | K15: ='08) Drop Down Menus'!A4 -> Gas | L15: =L5+'2023 Expences - 06162023'!K15 -> 337.41 | M15: =L15/M$21 -> 21.088125
B16: FALSE | H16: 0 | I16: =I15+H16 -> 366.38 | K16: ='08) Drop Down Menus'!A5 -> Entertainment | L16: =L6+'2023 Expences - 06162023'!K16 -> 510.52 | M16: =L16/M$21 -> 31.9075
B17: FALSE | H17: 0 | I17: =I16+H17 -> 366.38 | K17: ='08) Drop Down Menus'!A6 -> Medical | L17: =L7+'2023 Expences - 06162023'!K17 -> 227.22 | M17: =L17/M$21 -> 14.20125
B18: FALSE | H18: 0 | I18: =I17+H18 -> 366.38 | K18: ='08) Drop Down Menus'!A7 -> Vehicle | L18: =L8+'2023 Expences - 06162023'!K18 -> 144.32 | M18: =L18/M$21 -> 9.02
B19: FALSE | H19: 0 | I19: =I18+H19 -> 366.38 | K19: ='08) Drop Down Menus'!A8 -> Maintenance | L19: =L9+'2023 Expences - 06162023'!K19 -> 600.66 | M19: =L19/M$21 -> 37.54125
B20: FALSE | H20: 0 | I20: =I19+H20 -> 366.38 | K20: ='08) Drop Down Menus'!A9 -> Debt | L20: =L10+'2023 Expences - 06162023'!K20 -> 479.24 | M20: =L20/M$21 -> 29.9525
B21: FALSE | H21: 0 | I21: =I20+H21 -> 366.38 | K21: Paycheck Number | M21: 16
B22: FALSE | H22: 0 | I22: =I21+H22 -> 366.38
B23: FALSE | H23: 0 | I23: =I22+H23 -> 366.38 | K23: Mission Lane Credit Card Information ($500 Limit)
B24: FALSE | H24: 0 | I24: =I23+H24 -> 366.38 | K24: Last Payment / Amount | L24: 45152 | M24: 37.64
B25: FALSE | H25: 0 | I25: =I24+H25 -> 366.38 | K25: Used This Period | L25: =SUMIF(B4:B26,true,$H$4:$H$24) -> 0
B26: FALSE | H26: 0 | I26: =I25+H26 -> 366.38 | K26: Available (Before / After) | L26: 249.44 | M26: =L26+M24-L25 -> 287.08
C27: Expence Grand Total | H27: =I26 -> 366.38 | K27: Balance to Pay | M27: =500-M26 -> 212.92
B29: Shopping List
B30: Tax | C30: Item | D30: Isle | E30: Category | F30: Amount | G30: Cost of One | H30: Total Cost
B31: FALSE | C31: Milk | D31: A-23 | E31: Groceries | F31: 2 | G31: 2.66 | H31: =IF( B31 = TRUE ,(G31*F31)*0.05+(G31*F31) , G31*F31 ) -> 5.32
B32: TRUE | C32: Toilet Bowl Cleaner | D32: J-11 | E32: Bathroom | F32: 1 | G32: 5.18 | H32: =IF( B32 = TRUE ,(G32*F32)*0.05+(G32*F32) , G32*F32 ) -> 5.439
B33: TRUE | C33: Hand Soap | D33: G-16 | E33: Bathroom | F33: 2 | G33: 2.47 | H33: =IF( B33 = TRUE ,(G33*F33)*0.05+(G33*F33) , G33*F33 ) -> 5.187
B34: TRUE | C34: Toilet Paper | D34: J-07 | E34: Bathroom | F34: 1 | G34: 6.98 | H34: =IF( B34 = TRUE ,(G34*F34)*0.05+(G34*F34) , G34*F34 ) -> 7.329
B35: FALSE | C35: Pop Tarts | D35: A-08 | E35: Groceries | F35: 1 | G35: 4.47 | H35: =IF( B35 = TRUE ,(G35*F35)*0.05+(G35*F35) , G35*F35 ) -> 4.47
B36: FALSE | C36: Zebra Cakes | D36: A-06 | E36: Groceries (Lunch) | F36: 4 | G36: 2.68 | H36: =IF( B36 = TRUE ,(G36*F36)*0.05+(G36*F36) , G36*F36 ) -> 10.72
B37: FALSE | C37: Oreos | D37: A-18 | E37: Groceries | F37: 1 | G37: 4.58 | H37: =IF( B37 = TRUE ,(G37*F37)*0.05+(G37*F37) , G37*F37 ) -> 4.58
B38: FALSE | C38: Soda | D38: A-20 | E38: Groceries | F38: 4 | G38: 3.88 | H38: =IF( B38 = TRUE ,(G38*F38)*0.05+(G38*F38) , G38*F38 ) -> 15.52
B39: FALSE | C39: Pizza | D39: A-04 | E39: Groceries | F39: 2 | G39: 3.98 | H39: =IF( B39 = TRUE ,(G39*F39)*0.05+(G39*F39) , G39*F39 ) -> 7.96
B40: FALSE | C40: Nutter Butters | D40: A-18 | E40: Groceries | F40: 1 | G40: 4.68 | H40: =IF( B40 = TRUE ,(G40*F40)*0.05+(G40*F40) , G40*F40 ) -> 4.68
B41: FALSE | G41: 0 | H41: =IF( B41 = TRUE ,(G41*F41)*0.05+(G41*F41) , G41*F41 ) -> 0
B42: FALSE | G42: 0 | H42: =IF( B42 = TRUE ,(G42*F42)*0.05+(G42*F42) , G42*F42 ) -> 0
B43: FALSE | G43: 0 | H43: =IF( B43 = TRUE ,(G43*F43)*0.05+(G43*F43) , G43*F43 ) -> 0
B44: FALSE | G44: 0 | H44: =IF( B44 = TRUE ,(G44*F44)*0.05+(G44*F44) , G44*F44 ) -> 0
B45: FALSE | G45: 0 | H45: =IF( B45 = TRUE ,(G45*F45)*0.05+(G45*F45) , G45*F45 ) -> 0
B46: FALSE | C46: Hydroxizine | D46: CVS | E46: Medical | F46: 1 | G46: 10 | H46: =IF( B46 = TRUE ,(G46*F46)*0.05+(G46*F46) , G46*F46 ) -> 10
B47: FALSE | G47: 0 | H47: =IF( B47 = TRUE ,(G47*F47)*0.05+(G47*F47) , G47*F47 ) -> 0
B48: FALSE | G48: 0 | H48: =IF( B48 = TRUE ,(G48*F48)*0.05+(G48*F48) , G48*F48 ) -> 0
B49: FALSE | G49: 0 | H49: =IF( B49 = TRUE ,(G49*F49)*0.05+(G49*F49) , G49*F49 ) -> 0
B50: FALSE | G50: 0 | H50: =IF( B50 = TRUE ,(G50*F50)*0.05+(G50*F50) , G50*F50 ) -> 0
B51: FALSE | G51: 0 | H51: =IF( B51 = TRUE ,(G51*F51)*0.05+(G51*F51) , G51*F51 ) -> 0
B52: FALSE | G52: 0 | H52: =IF( B52 = TRUE ,(G52*F52)*0.05+(G52*F52) , G52*F52 ) -> 0
B53: FALSE | G53: 0 | H53: =IF( B53 = TRUE ,(G53*F53)*0.05+(G53*F53) , G53*F53 ) -> 0
B54: FALSE | G54: 0 | H54: =IF( B54 = TRUE ,(G54*F54)*0.05+(G54*F54) , G54*F54 ) -> 0
B55: FALSE | G55: 0 | H55: =IF( B55 = TRUE ,(G55*F55)*0.05+(G55*F55) , G55*F55 ) -> 0
B56: FALSE | G56: 0 | H56: =IF( B56 = TRUE ,(G56*F56)*0.05+(G56*F56) , G56*F56 ) -> 0
B57: FALSE | G57: 0 | H57: =IF( B57 = TRUE ,(G57*F57)*0.05+(G57*F57) , G57*F57 ) -> 0
B58: FALSE | G58: 0 | H58: =IF( B58 = TRUE ,(G58*F58)*0.05+(G58*F58) , G58*F58 ) -> 0
... B79: FALSE | G79: 0 | H79: =IF( B79 = TRUE ,(G79*F79)*0.05+(G79*F79) , G79*F79 ) -> 0
C80: Total Cost (No Credit Card Use): | H80: =sum(H31:H79) -> 81.205
B81: Remaining Balance (With Credit Card Use): | H81: =sum(H31:H79)-L26 -> -168.235
B82: Remaining Balance: | H82: ='11) 2023 BudgetBill Breakdown'!H273-H80 -> -66.855

Sheet 2023 Expences - 08252023
B2: Expences for Paycheck 8/25/2023 | K2: Catagory Totals
B3: CC | C3: Expence | F3: Date | G3: Catagory | H3: Cost | I3: Total | K3: ='08) Drop Down Menus'!A2 -> Groceries | L3: =sumifs(H$4:H$26,G$4:G$26,K3,B$4:B$26,false) -> 50
B4: FALSE | C4: Kwik Trip | F4: 45164 | G4: Cigarettes | H4: 20.69 | I4: =H4 -> 20.69 | K4: ='08) Drop Down Menus'!A3 -> Cigarettes | L4: =sumifs(H$4:H$26,G$4:G$26,K4,B$4:B$26,false) -> 20.69
B5: FALSE | C5: Hims | F5: 45164 | G5: Medical | H5: 65 | I5: =I4+H5 -> 85.69 | K5: ='08) Drop Down Menus'!A4 -> Gas | L5: =sumifs(H$4:H$26,G$4:G$26,K5,B$4:B$26,false) -> 0
B6: FALSE | C6: Nexus Mods | F6: 45169 | G6: Entertainment | H6: 6.32 | I6: =I5+H6 -> 92.01 | K6: ='08) Drop Down Menus'!A5 -> Entertainment | L6: =sumifs(H$4:H$26,G$4:G$26,K6,B$4:B$26,false) -> 14.71
B7: FALSE | C7: Funimation (08/30/2023) | F7: 45168 | G7: Entertainment | H7: 8.39 | I7: =I6+H7 -> 100.4 | K7: ='08) Drop Down Menus'!A6 -> Medical | L7: =sumifs(H$4:H$26,G$4:G$26,K7,B$4:B$26,false) -> 65
B8: FALSE | C8: Walmart | F8: 45165 | G8: Groceries | H8: 50 | I8: =I7+H8 -> 150.4 | K8: ='08) Drop Down Menus'!A7 -> Vehicle | L8: =sumifs(H$4:H$26,G$4:G$26,K8,B$4:B$26,false) -> 0
B9: FALSE | H9: 0 | I9: =I8+H9 -> 150.4 | K9: ='08) Drop Down Menus'!A8 -> Maintenance | L9: =sumifs(H$4:H$26,G$4:G$26,K9,B$4:B$26,false) -> 0
B10: FALSE | H10: 0 | I10: =I9+H10 -> 150.4 | K10: ='08) Drop Down Menus'!A9 -> Debt | L10: =sumifs(H$4:H$26,G$4:G$26,K10,B$4:B$26,false) -> 0
B11: FALSE | H11: 0 | I11: =I10+H11 -> 150.4
B12: FALSE | H12: 0 | I12: =I11+H12 -> 150.4 | K12: Catagory | L12: YTD | M12: Average
B13: FALSE | H13: 0 | I13: =I12+H13 -> 150.4 | K13: ='08) Drop Down Menus'!A2 -> Groceries | L13: =L3+'2023 Expences - 06162023'!K13 -> 2716.92 | M13: =L13/M$21 -> 159.81882
B14: FALSE | H14: 0 | I14: =I13+H14 -> 150.4 | K14: ='08) Drop Down Menus'!A3 -> Cigarettes | L14: =L4+'2023 Expences - 06162023'!K14 -> 563.66 | M14: =L14/M$21 -> 33.156471
B15: FALSE | H15: 0 | I15: =I14+H15 -> 150.4 | K15: ='08) Drop Down Menus'!A4 -> Gas | L15: =L5+'2023 Expences - 06162023'!K15 -> 296.72 | M15: =L15/M$21 -> 17.454118
B16: FALSE | H16: 0 | I16: =I15+H16 -> 150.4 | K16: ='08) Drop Down Menus'!A5 -> Entertainment | L16: =L6+'2023 Expences - 06162023'!K16 -> 491.7 | M16: =L16/M$21 -> 28.923529
B17: FALSE | H17: 0 | I17: =I16+H17 -> 150.4 | K17: ='08) Drop Down Menus'!A6 -> Medical | L17: =L7+'2023 Expences - 06162023'!K17 -> 277.22 | M17: =L17/M$21 -> 16.307059
B18: FALSE | H18: 0 | I18: =I17+H18 -> 150.4 | K18: ='08) Drop Down Menus'!A7 -> Vehicle | L18: =L8+'2023 Expences - 06162023'!K18 -> 144.32 | M18: =L18/M$21 -> 8.4894118
B19: FALSE | H19: 0 | I19: =I18+H19 -> 150.4 | K19: ='08) Drop Down Menus'!A8 -> Maintenance | L19: =L9+'2023 Expences - 06162023'!K19 -> 600.66 | M19: =L19/M$21 -> 35.332941
B20: FALSE | H20: 0 | I20: =I19+H20 -> 150.4 | K20: ='08) Drop Down Menus'!A9 -> Debt | L20: =L10+'2023 Expences - 06162023'!K20 -> 350.65 | M20: =L20/M$21 -> 20.626471
B21: FALSE | H21: 0 | I21: =I20+H21 -> 150.4 | K21: Paycheck Number | M21: 17
B22: FALSE | H22: 0 | I22: =I21+H22 -> 150.4
B23: FALSE | H23: 0 | I23: =I22+H23 -> 150.4 | K23: Mission Lane Credit Card Information ($500 Limit)
B24: FALSE | H24: 0 | I24: =I23+H24 -> 150.4 | K24: Last Payment / Amount | M24: 0
B25: FALSE | H25: 0 | I25: =I24+H25 -> 150.4 | K25: Used This Period | L25: =SUMIF(B4:B26,true,$H$4:$H$24) -> 0
B26: FALSE | H26: 0 | I26: =I25+H26 -> 150.4 | K26: Available (Before / After) | L26: 143.83 | M26: =L26+M24-L25 -> 143.83
C27: Expence Grand Total | H27: =I26 -> 150.4 | K27: Balance to Pay | M27: =500-M26 -> 356.17
B29: Shopping List
B30: Tax | C30: Item | D30: Isle | E30: Category | F30: Amount | G30: Cost of One | H30: Total Cost
B31: FALSE | G31: 0 | H31: =IF( B31 = TRUE ,(G31*F31)*0.05+(G31*F31) , G31*F31 ) -> 0
B32: FALSE | G32: 0 | H32: =IF( B32 = TRUE ,(G32*F32)*0.05+(G32*F32) , G32*F32 ) -> 0
B33: FALSE | G33: 0 | H33: =IF( B33 = TRUE ,(G33*F33)*0.05+(G33*F33) , G33*F33 ) -> 0
B34: FALSE | G34: 0 | H34: =IF( B34 = TRUE ,(G34*F34)*0.05+(G34*F34) , G34*F34 ) -> 0
B35: FALSE | G35: 0 | H35: =IF( B35 = TRUE ,(G35*F35)*0.05+(G35*F35) , G35*F35 ) -> 0
B36: FALSE | G36: 0 | H36: =IF( B36 = TRUE ,(G36*F36)*0.05+(G36*F36) , G36*F36 ) -> 0
B37: FALSE | G37: 0 | H37: =IF( B37 = TRUE ,(G37*F37)*0.05+(G37*F37) , G37*F37 ) -> 0
B38: FALSE | G38: 0 | H38: =IF( B38 = TRUE ,(G38*F38)*0.05+(G38*F38) , G38*F38 ) -> 0
B39: FALSE | G39: 0 | H39: =IF( B39 = TRUE ,(G39*F39)*0.05+(G39*F39) , G39*F39 ) -> 0
B40: FALSE | G40: 0 | H40: =IF( B40 = TRUE ,(G40*F40)*0.05+(G40*F40) , G40*F40 ) -> 0
B41: FALSE | G41: 0 | H41: =IF( B41 = TRUE ,(G41*F41)*0.05+(G41*F41) , G41*F41 ) -> 0
B42: FALSE | G42: 0 | H42: =IF( B42 = TRUE ,(G42*F42)*0.05+(G42*F42) , G42*F42 ) -> 0
... B79: FALSE | G79: 0 | H79: =IF( B79 = TRUE ,(G79*F79)*0.05+(G79*F79) , G79*F79 ) -> 0
C80: Total Cost (No Credit Card Use): | H80: =sum(H31:H79) -> 0
B81: Remaining Balance (With Credit Card Use): | H81: =-(sum(H31:H79)-L26-'11) 2023 BudgetBill Breakdown'!H287) -> 144.8
B82: Remaining Balance (Without Credit Card Use): | H82: ='11) 2023 BudgetBill Breakdown'!H287-H80 -> 0.97
B83: All Possible Funds: | H83: =M26+'11) 2023 BudgetBill Breakdown'!H287 -> 144.8

Sheet 2023 Expences - 09082023
B2: Expences for Paycheck 9/08/2023 | K2: Catagory Totals
B3: CC | C3: Expence | F3: Date | G3: Catagory | H3: Cost | I3: Total | K3: ='08) Drop Down Menus'!A2 -> Groceries | L3: =sumifs(H$4:H$26,G$4:G$26,K3,B$4:B$26,false) -> 162.19
B4: FALSE | C4: MDG | F4: 45177 | G4: Debt | H4: 8.95 | I4: =H4 -> 8.95 | K4: ='08) Drop Down Menus'!A3 -> Cigarettes | L4: =sumifs(H$4:H$26,G$4:G$26,K4,B$4:B$26,false) -> 80.73
B5: FALSE | C5: Marathon | F5: 45177 | G5: Cigarettes | H5: 21.07 | I5: =I4+H5 -> 30.02 | K5: ='08) Drop Down Menus'!A4 -> Gas | L5: =sumifs(H$4:H$26,G$4:G$26,K5,B$4:B$26,false) -> 0
B6: FALSE | C6: Rusty's (ATM Withdrawl) | F6: 45178 | G6: Entertainment | H6: 42.5 | I6: =I5+H6 -> 72.52 | K6: ='08) Drop Down Menus'!A5 -> Entertainment | L6: =sumifs(H$4:H$26,G$4:G$26,K6,B$4:B$26,false) -> 57.54
B7: FALSE | C7: Wal-Mart | F7: 45179 | G7: Groceries | H7: 119.4 | I7: =I6+H7 -> 191.92 | K7: ='08) Drop Down Menus'!A6 -> Medical | L7: =sumifs(H$4:H$26,G$4:G$26,K7,B$4:B$26,false) -> 0
B8: FALSE | C8: Subscription - Video | F8: 45179 | G8: Entertainment | H8: 15.04 | I8: =I7+H8 -> 206.96 | K8: ='08) Drop Down Menus'!A7 -> Vehicle | L8: =sumifs(H$4:H$26,G$4:G$26,K8,B$4:B$26,false) -> 12
B9: FALSE | C9: KwikTrip | F9: 45182 | G9: Cigarettes | H9: 30.69 | I9: =I8+H9 -> 237.65 | K9: ='08) Drop Down Menus'!A8 -> Maintenance | L9: =sumifs(H$4:H$26,G$4:G$26,K9,B$4:B$26,false) -> 0
B10: FALSE | C10: Vending Machine | F10: 45184 | G10: Groceries | H10: 1.25 | I10: =I9+H10 -> 238.9 | K10: ='08) Drop Down Menus'!A9 -> Debt | L10: =sumifs(H$4:H$26,G$4:G$26,K10,B$4:B$26,false) -> 8.95
B11: FALSE | C11: Shell | F11: 45188 | G11: Cigarettes | H11: 28.97 | I11: =I10+H11 -> 267.87
B12: FALSE | C12: KwikTrip (Car Wash) | F12: 45188 | G12: Vehicle | H12: 12 | I12: =I11+H12 -> 279.87 | K12: Catagory | L12: YTD | M12: Average
B13: FALSE | C13: Meijer | F13: 45186 | G13: Groceries | H13: 41.54 | I13: =I12+H13 -> 321.41 | K13: ='08) Drop Down Menus'!A2 -> Groceries | L13: =L3+'2023 Expences - 06162023'!K13 -> 2829.11 | M13: =L13/M$21 -> 157.17278
B14: FALSE | H14: 0 | I14: =I13+H14 -> 321.41 | K14: ='08) Drop Down Menus'!A3 -> Cigarettes | L14: =L4+'2023 Expences - 06162023'!K14 -> 623.7 | M14: =L14/M$21 -> 34.65
B15: FALSE | H15: 0 | I15: =I14+H15 -> 321.41 | K15: ='08) Drop Down Menus'!A4 -> Gas | L15: =L5+'2023 Expences - 06162023'!K15 -> 296.72 | M15: =L15/M$21 -> 16.484444
B16: FALSE | H16: 0 | I16: =I15+H16 -> 321.41 | K16: ='08) Drop Down Menus'!A5 -> Entertainment | L16: =L6+'2023 Expences - 06162023'!K16 -> 534.53 | M16: =L16/M$21 -> 29.696111
B17: FALSE | H17: 0 | I17: =I16+H17 -> 321.41 | K17: ='08) Drop Down Menus'!A6 -> Medical | L17: =L7+'2023 Expences - 06162023'!K17 -> 212.22 | M17: =L17/M$21 -> 11.79
B18: FALSE | H18: 0 | I18: =I17+H18 -> 321.41 | K18: ='08) Drop Down Menus'!A7 -> Vehicle | L18: =L8+'2023 Expences - 06162023'!K18 -> 156.32 | M18: =L18/M$21 -> 8.6844444
B19: FALSE | H19: 0 | I19: =I18+H19 -> 321.41 | K19: ='08) Drop Down Menus'!A8 -> Maintenance | L19: =L9+'2023 Expences - 06162023'!K19 -> 600.66 | M19: =L19/M$21 -> 33.37
B20: FALSE | H20: 0 | I20: =I19+H20 -> 321.41 | K20: ='08) Drop Down Menus'!A9 -> Debt | L20: =L10+'2023 Expences - 06162023'!K20 -> 359.6 | M20: =L20/M$21 -> 19.977778
B21: FALSE | H21: 0 | I21: =I20+H21 -> 321.41 | K21: Paycheck Number | M21: 18
B22: FALSE | H22: 0 | I22: =I21+H22 -> 321.41
B23: FALSE | H23: 0 | I23: =I22+H23 -> 321.41 | K23: Mission Lane Credit Card Information ($500 Limit)
B24: FALSE | H24: 0 | I24: =I23+H24 -> 321.41 | K24: Last Payment / Amount | L24: 45180 | M24: 25
B25: FALSE | H25: 0 | I25: =I24+H25 -> 321.41 | K25: Used This Period | L25: =SUMIF(B4:B26,true,$H$4:$H$24) -> 0
B26: FALSE | H26: 0 | I26: =I25+H26 -> 321.41 | K26: Available (Before / After) | L26: =68.74-25 -> 43.74 | M26: =L26+M24-L25 -> 68.74
C27: Expence Grand Total | H27: =I26 -> 321.41 | K27: Balance to Pay | M27: =500-M26 -> 431.26
B29: Shopping List
B30: Tax | C30: Item | D30: Isle | E30: Category | F30: Amount | G30: Cost of One | H30: Total Cost
B31: FALSE | G31: 0 | H31: =IF( B31 = TRUE ,(G31*F31)*0.05+(G31*F31) , G31*F31 ) -> 0
B32: FALSE | G32: 0 | H32: =IF( B32 = TRUE ,(G32*F32)*0.05+(G32*F32) , G32*F32 ) -> 0
B33: FALSE | G33: 0 | H33: =IF( B33 = TRUE ,(G33*F33)*0.05+(G33*F33) , G33*F33 ) -> 0
B34: FALSE | G34: 0 | H34: =IF( B34 = TRUE ,(G34*F34)*0.05+(G34*F34) , G34*F34 ) -> 0
B35: FALSE | G35: 0 | H35: =IF( B35 = TRUE ,(G35*F35)*0.05+(G35*F35) , G35*F35 ) -> 0
B36: FALSE | G36: 0 | H36: =IF( B36 = TRUE ,(G36*F36)*0.05+(G36*F36) , G36*F36 ) -> 0
B37: FALSE | G37: 0 | H37: =IF( B37 = TRUE ,(G37*F37)*0.05+(G37*F37) , G37*F37 ) -> 0
B38: FALSE | G38: 0 | H38: =IF( B38 = TRUE ,(G38*F38)*0.05+(G38*F38) , G38*F38 ) -> 0
B39: FALSE | G39: 0 | H39: =IF( B39 = TRUE ,(G39*F39)*0.05+(G39*F39) , G39*F39 ) -> 0
B40: FALSE | G40: 0 | H40: =IF( B40 = TRUE ,(G40*F40)*0.05+(G40*F40) , G40*F40 ) -> 0
B41: FALSE | G41: 0 | H41: =IF( B41 = TRUE ,(G41*F41)*0.05+(G41*F41) , G41*F41 ) -> 0
B42: FALSE | G42: 0 | H42: =IF( B42 = TRUE ,(G42*F42)*0.05+(G42*F42) , G42*F42 ) -> 0
... B79: FALSE | G79: 0 | H79: =IF( B79 = TRUE ,(G79*F79)*0.05+(G79*F79) , G79*F79 ) -> 0
C80: Total Cost (No Credit Card Use): | H80: =sum(H31:H79) -> 0
B81: Remaining Balance (With Credit Card Use): | H81: =sum(H31:H79)-M26 -> -68.74
B82: Remaining Balance: | H82: ='11) 2023 BudgetBill Breakdown'!H306-H80 -> 53.82

Sheet 2023 Expences - 09222023
B2: Expences for Paycheck 9/22/2023 | K2: Catagory Totals
B3: CC | C3: Expence | F3: Date | G3: Catagory | H3: Cost | I3: Total | K3: ='08) Drop Down Menus'!A2 -> Groceries | L3: =sumifs(H$4:H$26,G$4:G$26,K3,B$4:B$26,false) -> 225.38
B4: FALSE | C4: Vending Machine | F4: 45191 | G4: Groceries | H4: =1.25+2.25 -> 3.5 | I4: =H4 -> 3.5 | K4: ='08) Drop Down Menus'!A3 -> Cigarettes | L4: =sumifs(H$4:H$26,G$4:G$26,K4,B$4:B$26,false) -> 70.33
B5: FALSE | C5: Hims | F5: 45194 | G5: Medical | H5: 65 | I5: =I4+H5 -> 68.5 | K5: ='08) Drop Down Menus'!A4 -> Gas | L5: =sumifs(H$4:H$26,G$4:G$26,K5,B$4:B$26,false) -> 40.4
B6: FALSE | C6: Funimation | F6: 45198 | G6: Entertainment | H6: 8.39 | I6: =I5+H6 -> 76.89 | K6: ='08) Drop Down Menus'!A5 -> Entertainment | L6: =sumifs(H$4:H$26,G$4:G$26,K6,B$4:B$26,false) -> 29.56
B7: FALSE | C7: Kwik-Trip | F7: 45194 | G7: Cigarettes | H7: 30.69 | I7: =I6+H7 -> 107.58 | K7: ='08) Drop Down Menus'!A6 -> Medical | L7: =sumifs(H$4:H$26,G$4:G$26,K7,B$4:B$26,false) -> 144
B8: FALSE | C8: Kwik-Trip | F8: 45194 | G8: Gas | H8: 40.4 | I8: =I7+H8 -> 147.98 | K8: ='08) Drop Down Menus'!A7 -> Vehicle | L8: =sumifs(H$4:H$26,G$4:G$26,K8,B$4:B$26,false) -> 107.47
B9: FALSE | C9: Wal-Mart | F9: 45193 | G9: Groceries | H9: 149.06 | I9: =I8+H9 -> 297.04 | K9: ='08) Drop Down Menus'!A8 -> Maintenance | L9: =sumifs(H$4:H$26,G$4:G$26,K9,B$4:B$26,false) -> 0
B10: FALSE | C10: CVS (Venlafaxine and Vyvanse) | F10: 45192 | G10: Medical | H10: 40 | I10: =I9+H10 -> 337.04 | K10: ='08) Drop Down Menus'!A9 -> Debt | L10: =sumifs(H$4:H$26,G$4:G$26,K10,B$4:B$26,false) -> -0.02
B11: FALSE | C11: Meijer | F11: 45201 | G11: Groceries | H11: 72.82 | I11: =I10+H11 -> 409.86
B12: FALSE | C12: Nexus Mods | F12: 45201 | G12: Entertainment | H12: 6.13 | I12: =I11+H12 -> 415.99 | K12: Catagory | L12: YTD | M12: Average
B13: FALSE | C13: Planet Fitness (Annual Fee) | F13: 45201 | G13: Medical | H13: 39 | I13: =I12+H13 -> 454.99 | K13: ='08) Drop Down Menus'!A2 -> Groceries | L13: =L3+'2023 Expences - 06162023'!K13 -> 2892.3 | M13: =L13/M$21 -> 152.22632
B14: FALSE | C14: DMV (Car Registration) | F14: 45202 | G14: Vehicle | H14: 107.47 | I14: =I13+H14 -> 562.46 | K14: ='08) Drop Down Menus'!A3 -> Cigarettes | L14: =L4+'2023 Expences - 06162023'!K14 -> 613.3 | M14: =L14/M$21 -> 32.278947
B15: FALSE | C15: Kwik-Trip | F15: 45199 | G15: Cigarettes | H15: 39.64 | I15: =I14+H15 -> 602.1 | K15: ='08) Drop Down Menus'!A4 -> Gas | L15: =L5+'2023 Expences - 06162023'!K15 -> 337.12 | M15: =L15/M$21 -> 17.743158
B16: FALSE | C16: Bank Dividend | F16: 45200 | G16: Debt | H16: -0.02 | I16: =I15+H16 -> 602.08 | K16: ='08) Drop Down Menus'!A5 -> Entertainment | L16: =L6+'2023 Expences - 06162023'!K16 -> 506.55 | M16: =L16/M$21 -> 26.660526
B17: FALSE | C17: Subscription - Video | F17: 45200 | G17: Entertainment | H17: 15.04 | I17: =I16+H17 -> 617.12 | K17: ='08) Drop Down Menus'!A6 -> Medical | L17: =L7+'2023 Expences - 06162023'!K17 -> 356.22 | M17: =L17/M$21 -> 18.748421
B18: FALSE | H18: 0 | I18: =I17+H18 -> 617.12 | K18: ='08) Drop Down Menus'!A7 -> Vehicle | L18: =L8+'2023 Expences - 06162023'!K18 -> 251.79 | M18: =L18/M$21 -> 13.252105
B19: FALSE | H19: 0 | I19: =I18+H19 -> 617.12 | K19: ='08) Drop Down Menus'!A8 -> Maintenance | L19: =L9+'2023 Expences - 06162023'!K19 -> 600.66 | M19: =L19/M$21 -> 31.613684
B20: FALSE | H20: 0 | I20: =I19+H20 -> 617.12 | K20: ='08) Drop Down Menus'!A9 -> Debt | L20: =L10+'2023 Expences - 06162023'!K20 -> 350.63 | M20: =L20/M$21 -> 18.454211
B21: FALSE | H21: 0 | I21: =I20+H21 -> 617.12 | K21: Paycheck Number | M21: 19
B22: FALSE | H22: 0 | I22: =I21+H22 -> 617.12
B23: FALSE | H23: 0 | I23: =I22+H23 -> 617.12 | K23: Mission Lane Credit Card Information ($500 Limit)
B24: FALSE | H24: 0 | I24: =I23+H24 -> 617.12 | K24: Last Payment / Amount | L24: 45192 | M24: 50
B25: FALSE | H25: 0 | I25: =I24+H25 -> 617.12 | K25: Used This Period | L25: 0
B26: FALSE | H26: 0 | I26: =I25+H26 -> 617.12 | K26: Available (Before / After) | L26: 68.74 | M26: =L26+M24-L25 -> 118.74
C27: Expence Grand Total | H27: =I26 -> 617.12 | K27: Balance to Pay | M27: =500-M26 -> 381.26
B29: Shopping List
B30: Tax | C30: Item | D30: Isle | E30: Category | F30: Amount | G30: Cost of One | H30: Total Cost
B31: FALSE | G31: 0 | H31: =IF( B31 = TRUE ,(G31*F31)*0.05+(G31*F31) , G31*F31 ) -> 0
B32: FALSE | G32: 0 | H32: =IF( B32 = TRUE ,(G32*F32)*0.05+(G32*F32) , G32*F32 ) -> 0
B33: FALSE | G33: 0 | H33: =IF( B33 = TRUE ,(G33*F33)*0.05+(G33*F33) , G33*F33 ) -> 0
B34: FALSE | G34: 0 | H34: =IF( B34 = TRUE ,(G34*F34)*0.05+(G34*F34) , G34*F34 ) -> 0
B35: FALSE | G35: 0 | H35: =IF( B35 = TRUE ,(G35*F35)*0.05+(G35*F35) , G35*F35 ) -> 0
B36: FALSE | G36: 0 | H36: =IF( B36 = TRUE ,(G36*F36)*0.05+(G36*F36) , G36*F36 ) -> 0
B37: FALSE | G37: 0 | H37: =IF( B37 = TRUE ,(G37*F37)*0.05+(G37*F37) , G37*F37 ) -> 0
B38: FALSE | G38: 0 | H38: =IF( B38 = TRUE ,(G38*F38)*0.05+(G38*F38) , G38*F38 ) -> 0
B39: FALSE | G39: 0 | H39: =IF( B39 = TRUE ,(G39*F39)*0.05+(G39*F39) , G39*F39 ) -> 0
B40: FALSE | G40: 0 | H40: =IF( B40 = TRUE ,(G40*F40)*0.05+(G40*F40) , G40*F40 ) -> 0
B41: FALSE | G41: 0 | H41: =IF( B41 = TRUE ,(G41*F41)*0.05+(G41*F41) , G41*F41 ) -> 0
B42: FALSE | G42: 0 | H42: =IF( B42 = TRUE ,(G42*F42)*0.05+(G42*F42) , G42*F42 ) -> 0
... B79: FALSE | G79: 0 | H79: =IF( B79 = TRUE ,(G79*F79)*0.05+(G79*F79) , G79*F79 ) -> 0
C80: Total Cost (No Credit Card Use): | H80: =sum(H31:H79) -> 0
B81: Remaining Balance (With Credit Card Use): | H81: =sum(H31:H79)-M26 -> -118.74
B82: Remaining Balance: | H82: ='11) 2023 BudgetBill Breakdown'!H321-H80 -> 613.27

Sheet 2023 Expences - 10062023
B2: Expences for Paycheck 9/22/2023 | K2: Catagory Totals
B3: CC | C3: Expence | F3: Date | G3: Catagory | H3: Cost | I3: Total | K3: ='08) Drop Down Menus'!A2 -> Groceries | L3: =sumifs(H$4:H$26,G$4:G$26,K3,B$4:B$26,false) -> 158.04
B4: FALSE | C4: MDG | F4: 45205 | G4: Debt | H4: 8.95 | I4: =H4 -> 8.95 | K4: ='08) Drop Down Menus'!A3 -> Cigarettes | L4: =sumifs(H$4:H$26,G$4:G$26,K4,B$4:B$26,false) -> 80.93
B5: FALSE | C5: Kwik-Trip | F5: 45205 | G5: Cigarettes | H5: 30.03 | I5: =I4+H5 -> 38.98 | K5: ='08) Drop Down Menus'!A4 -> Gas | L5: =sumifs(H$4:H$26,G$4:G$26,K5,B$4:B$26,false) -> 0
B6: FALSE | C6: Vending Machine | F6: 45213 | G6: Groceries | H6: 3.99 | I6: =I5+H6 -> 42.97 | K6: ='08) Drop Down Menus'!A5 -> Entertainment | L6: =sumifs(H$4:H$26,G$4:G$26,K6,B$4:B$26,false) -> -4.43
B7: FALSE | C7: Citco | F7: 45211 | G7: Cigarettes | H7: 19.82 | I7: =I6+H7 -> 62.79 | K7: ='08) Drop Down Menus'!A6 -> Medical | L7: =sumifs(H$4:H$26,G$4:G$26,K7,B$4:B$26,false) -> 0
B8: FALSE | C8: Mega | F8: 45208 | G8: Entertainment | H8: 10.61 | I8: =I7+H8 -> 73.4 | K8: ='08) Drop Down Menus'!A7 -> Vehicle | L8: =sumifs(H$4:H$26,G$4:G$26,K8,B$4:B$26,false) -> 0
B9: FALSE | C9: Wal-Mart | F9: 45207 | G9: Groceries | H9: 77.98 | I9: =I8+H9 -> 151.38 | K9: ='08) Drop Down Menus'!A8 -> Maintenance | L9: =sumifs(H$4:H$26,G$4:G$26,K9,B$4:B$26,false) -> 0
B10: FALSE | C10: Kwik-Trip | F10: 45216 | G10: Cigarettes | H10: 31.08 | I10: =I9+H10 -> 182.46 | K10: ='08) Drop Down Menus'!A9 -> Debt | L10: =sumifs(H$4:H$26,G$4:G$26,K10,B$4:B$26,false) -> 8.95
B11: FALSE | C11: Wal-Mart | F11: 45214 | G11: Groceries | H11: 76.07 | I11: =I10+H11 -> 258.53
B12: FALSE | C12: Amazon Return | F12: 45214 | G12: Entertainment | H12: -15.04 | I12: =I11+H12 -> 243.49 | K12: Catagory | L12: YTD | M12: Average
B13: FALSE | H13: 0 | I13: =I12+H13 -> 243.49 | K13: ='08) Drop Down Menus'!A2 -> Groceries | L13: =L3+'2023 Expences - 06162023'!K13 -> 2824.96 | M13: =L13/M$21 -> 141.248
B14: FALSE | H14: 0 | I14: =I13+H14 -> 243.49 | K14: ='08) Drop Down Menus'!A3 -> Cigarettes | L14: =L4+'2023 Expences - 06162023'!K14 -> 623.9 | M14: =L14/M$21 -> 31.195
B15: FALSE | H15: 0 | I15: =I14+H15 -> 243.49 | K15: ='08) Drop Down Menus'!A4 -> Gas | L15: =L5+'2023 Expences - 06162023'!K15 -> 296.72 | M15: =L15/M$21 -> 14.836
B16: FALSE | H16: 0 | I16: =I15+H16 -> 243.49 | K16: ='08) Drop Down Menus'!A5 -> Entertainment | L16: =L6+'2023 Expences - 06162023'!K16 -> 472.56 | M16: =L16/M$21 -> 23.628
B17: FALSE | H17: 0 | I17: =I16+H17 -> 243.49 | K17: ='08) Drop Down Menus'!A6 -> Medical | L17: =L7+'2023 Expences - 06162023'!K17 -> 212.22 | M17: =L17/M$21 -> 10.611
B18: FALSE | H18: 0 | I18: =I17+H18 -> 243.49 | K18: ='08) Drop Down Menus'!A7 -> Vehicle | L18: =L8+'2023 Expences - 06162023'!K18 -> 144.32 | M18: =L18/M$21 -> 7.216
B19: FALSE | H19: 0 | I19: =I18+H19 -> 243.49 | K19: ='08) Drop Down Menus'!A8 -> Maintenance | L19: =L9+'2023 Expences - 06162023'!K19 -> 600.66 | M19: =L19/M$21 -> 30.033
B20: FALSE | H20: 0 | I20: =I19+H20 -> 243.49 | K20: ='08) Drop Down Menus'!A9 -> Debt | L20: =L10+'2023 Expences - 06162023'!K20 -> 359.6 | M20: =L20/M$21 -> 17.98
B21: FALSE | H21: 0 | I21: =I20+H21 -> 243.49 | K21: Paycheck Number | M21: 20
B22: FALSE | H22: 0 | I22: =I21+H22 -> 243.49
B23: FALSE | H23: 0 | I23: =I22+H23 -> 243.49 | K23: Mission Lane Credit Card Information ($500 Limit)
B24: FALSE | H24: 0 | I24: =I23+H24 -> 243.49 | K24: Last Payment / Amount | M24: 0
B25: FALSE | H25: 0 | I25: =I24+H25 -> 243.49 | K25: Used This Period | L25: 0
B26: FALSE | H26: 0 | I26: =I25+H26 -> 243.49 | K26: Available (Before / After) | L26: 109.07 | M26: =L26+M24-L25 -> 109.07
C27: Expence Grand Total | H27: =I26 -> 243.49 | K27: Balance to Pay | M27: =500-M26 -> 390.93
B29: Shopping List
B30: Tax | C30: Item | D30: Isle | E30: Category | F30: Amount | G30: Cost of One | H30: Total Cost
B31: FALSE | G31: 0 | H31: =IF( B31 = TRUE ,(G31*F31)*0.05+(G31*F31) , G31*F31 ) -> 0
B32: FALSE | G32: 0 | H32: =IF( B32 = TRUE ,(G32*F32)*0.05+(G32*F32) , G32*F32 ) -> 0
B33: FALSE | G33: 0 | H33: =IF( B33 = TRUE ,(G33*F33)*0.05+(G33*F33) , G33*F33 ) -> 0
B34: FALSE | G34: 0 | H34: =IF( B34 = TRUE ,(G34*F34)*0.05+(G34*F34) , G34*F34 ) -> 0
B35: FALSE | G35: 0 | H35: =IF( B35 = TRUE ,(G35*F35)*0.05+(G35*F35) , G35*F35 ) -> 0
B36: FALSE | G36: 0 | H36: =IF( B36 = TRUE ,(G36*F36)*0.05+(G36*F36) , G36*F36 ) -> 0
B37: FALSE | G37: 0 | H37: =IF( B37 = TRUE ,(G37*F37)*0.05+(G37*F37) , G37*F37 ) -> 0
B38: FALSE | G38: 0 | H38: =IF( B38 = TRUE ,(G38*F38)*0.05+(G38*F38) , G38*F38 ) -> 0
B39: FALSE | G39: 0 | H39: =IF( B39 = TRUE ,(G39*F39)*0.05+(G39*F39) , G39*F39 ) -> 0
B40: FALSE | G40: 0 | H40: =IF( B40 = TRUE ,(G40*F40)*0.05+(G40*F40) , G40*F40 ) -> 0
B41: FALSE | G41: 0 | H41: =IF( B41 = TRUE ,(G41*F41)*0.05+(G41*F41) , G41*F41 ) -> 0
B42: FALSE | G42: 0 | H42: =IF( B42 = TRUE ,(G42*F42)*0.05+(G42*F42) , G42*F42 ) -> 0
... B79: FALSE | G79: 0 | H79: =IF( B79 = TRUE ,(G79*F79)*0.05+(G79*F79) , G79*F79 ) -> 0
C80: Total Cost (No Credit Card Use): | H80: =sum(H31:H79) -> 0
B81: Remaining Balance (With Credit Card Use): | H81: =sum(H31:H79)-M26 -> -109.07
B82: Remaining Balance: | H82: ='11) 2023 BudgetBill Breakdown'!H338-H80 -> 79.3

Sheet 2023 Expences - 10202023
B2: Expences for Paycheck 10/20/2023 | K2: Catagory Totals
B3: CC | C3: Expence | F3: Date | G3: Catagory | H3: Cost | I3: Total | K3: ='08) Drop Down Menus'!A2 -> Groceries | L3: =sumifs(H$4:H$26,G$4:G$26,K3,B$4:B$26,false) -> 138.29
B4: FALSE | C4: Wal-Mart | F4: 45220 | G4: Maintenance | H4: 101.91 | I4: =H4 -> 101.91 | K4: ='08) Drop Down Menus'!A3 -> Cigarettes | L4: =sumifs(H$4:H$26,G$4:G$26,K4,B$4:B$26,false) -> 49.08
B5: FALSE | C5: Smart-Style | F5: 45220 | G5: Maintenance | H5: 27.46 | I5: =I4+H5 -> 129.37 | K5: ='08) Drop Down Menus'!A4 -> Gas | L5: =sumifs(H$4:H$26,G$4:G$26,K5,B$4:B$26,false) -> 32.7
B6: FALSE | C6: Wal-Mart | F6: 45221 | G6: Groceries | H6: 72.33 | I6: =I5+H6 -> 201.7 | K6: ='08) Drop Down Menus'!A5 -> Entertainment | L6: =sumifs(H$4:H$26,G$4:G$26,K6,B$4:B$26,false) -> 34.44
B7: FALSE | C7: Wal-Mart (Vyvanse) | F7: 45222 | G7: Medical | H7: 10 | I7: =I6+H7 -> 211.7 | K7: ='08) Drop Down Menus'!A6 -> Medical | L7: =sumifs(H$4:H$26,G$4:G$26,K7,B$4:B$26,false) -> 27.97
B8: FALSE | C8: Shell | F8: 45221 | G8: Cigarettes | H8: 18.97 | I8: =I7+H8 -> 230.67 | K8: ='08) Drop Down Menus'!A7 -> Vehicle | L8: =sumifs(H$4:H$26,G$4:G$26,K8,B$4:B$26,false) -> 16.03
B9: FALSE | C9: Wal-Mart (Posture Brace) | F9: 45221 | G9: Medical | H9: 17.97 | I9: =I8+H9 -> 248.64 | K9: ='08) Drop Down Menus'!A8 -> Maintenance | L9: =sumifs(H$4:H$26,G$4:G$26,K9,B$4:B$26,false) -> 174.99
B10: FALSE | C10: Entertainment | F10: 45223 | G10: Entertainment | H10: 19.99 | I10: =I9+H10 -> 268.63 | K10: ='08) Drop Down Menus'!A9 -> Debt | L10: =sumifs(H$4:H$26,G$4:G$26,K10,B$4:B$26,false) -> 0
B11: FALSE | C11: Nexus Mods | F11: 45231 | G11: Entertainment | H11: 6.06 | I11: =I10+H11 -> 274.69
B12: FALSE | C12: Funimation | F12: 45230 | G12: Entertainment | H12: 8.39 | I12: =I11+H12 -> 283.08 | K12: Catagory | L12: YTD | M12: Average
B13: FALSE | C13: KwikTrip (Gas) | F13: 45228 | G13: Gas | H13: =43.7-11 -> 32.7 | I13: =I12+H13 -> 315.78 | K13: ='08) Drop Down Menus'!A2 -> Groceries | L13: =L3+'2023 Expences - 06162023'!K13 -> 2805.21 | M13: =L13/M$21 -> 133.58143
B14: FALSE | C14: Kwik Trip (Car Wash) | F14: 45228 | G14: Vehicle | H14: 11 | I14: =I13+H14 -> 326.78 | K14: ='08) Drop Down Menus'!A3 -> Cigarettes | L14: =L4+'2023 Expences - 06162023'!K14 -> 592.05 | M14: =L14/M$21 -> 28.192857
B15: FALSE | C15: Kwik Trip (Washer Fluid) | F15: 45228 | G15: Vehicle | H15: 5.03 | I15: =I14+H15 -> 331.81 | K15: ='08) Drop Down Menus'!A4 -> Gas | L15: =L5+'2023 Expences - 06162023'!K15 -> 329.42 | M15: =L15/M$21 -> 15.686667
B16: FALSE | C16: Meijer | F16: 45228 | G16: Groceries | H16: 65.96 | I16: =I15+H16 -> 397.77 | K16: ='08) Drop Down Menus'!A5 -> Entertainment | L16: =L6+'2023 Expences - 06162023'!K16 -> 511.43 | M16: =L16/M$21 -> 24.35381
B17: FALSE | C17: Menards (Door Knob, Take off Rent) | F17: 45228 | G17: Maintenance | H17: 35.14 | I17: =I16+H17 -> 432.91 | K17: ='08) Drop Down Menus'!A6 -> Medical | L17: =L7+'2023 Expences - 06162023'!K17 -> 240.19 | M17: =L17/M$21 -> 11.437619
B18: FALSE | C18: Lowes (Command Strips) | F18: 45228 | G18: Maintenance | H18: 10.48 | I18: =I17+H18 -> 443.39 | K18: ='08) Drop Down Menus'!A7 -> Vehicle | L18: =L8+'2023 Expences - 06162023'!K18 -> 160.35 | M18: =L18/M$21 -> 7.6357143
B19: FALSE | C19: Kwik Trip (Cigarettes) | F19: 45228 | G19: Cigarettes | H19: 30.11 | I19: =I18+H19 -> 473.5 | K19: ='08) Drop Down Menus'!A8 -> Maintenance | L19: =L9+'2023 Expences - 06162023'!K19 -> 775.65 | M19: =L19/M$21 -> 36.935714
B20: FALSE | H20: 0 | I20: =I19+H20 -> 473.5 | K20: ='08) Drop Down Menus'!A9 -> Debt | L20: =L10+'2023 Expences - 06162023'!K20 -> 350.65 | M20: =L20/M$21 -> 16.697619
B21: FALSE | H21: 0 | I21: =I20+H21 -> 473.5 | K21: Paycheck Number | M21: 21
B22: FALSE | H22: 0 | I22: =I21+H22 -> 473.5
B23: FALSE | H23: 0 | I23: =I22+H23 -> 473.5 | K23: Mission Lane Credit Card Information ($500 Limit)
B24: FALSE | H24: 0 | I24: =I23+H24 -> 473.5 | K24: Last Payment / Amount | L24: 45225 | M24: 50
B25: FALSE | H25: 0 | I25: =I24+H25 -> 473.5 | K25: Used This Period | L25: 0
B26: FALSE | H26: 0 | I26: =I25+H26 -> 473.5 | K26: Available (Before / After) | L26: 109.07 | M26: =L26+M24-L25 -> 159.07
C27: Expence Grand Total | H27: =I26 -> 473.5 | K27: Balance to Pay | M27: =500-M26 -> 340.93
B29: Shopping List
B30: Tax | C30: Item | D30: Isle | E30: Category | F30: Amount | G30: Cost of One | H30: Total Cost
B31: FALSE | G31: 0 | H31: =IF( B31 = TRUE ,(G31*F31)*0.05+(G31*F31) , G31*F31 ) -> 0
B32: FALSE | G32: 0 | H32: =IF( B32 = TRUE ,(G32*F32)*0.05+(G32*F32) , G32*F32 ) -> 0
B33: FALSE | G33: 0 | H33: =IF( B33 = TRUE ,(G33*F33)*0.05+(G33*F33) , G33*F33 ) -> 0
B34: FALSE | G34: 0 | H34: =IF( B34 = TRUE ,(G34*F34)*0.05+(G34*F34) , G34*F34 ) -> 0
B35: FALSE | G35: 0 | H35: =IF( B35 = TRUE ,(G35*F35)*0.05+(G35*F35) , G35*F35 ) -> 0
B36: FALSE | G36: 0 | H36: =IF( B36 = TRUE ,(G36*F36)*0.05+(G36*F36) , G36*F36 ) -> 0
B37: FALSE | G37: 0 | H37: =IF( B37 = TRUE ,(G37*F37)*0.05+(G37*F37) , G37*F37 ) -> 0
B38: FALSE | G38: 0 | H38: =IF( B38 = TRUE ,(G38*F38)*0.05+(G38*F38) , G38*F38 ) -> 0
B39: FALSE | G39: 0 | H39: =IF( B39 = TRUE ,(G39*F39)*0.05+(G39*F39) , G39*F39 ) -> 0
B40: FALSE | G40: 0 | H40: =IF( B40 = TRUE ,(G40*F40)*0.05+(G40*F40) , G40*F40 ) -> 0
B41: FALSE | G41: 0 | H41: =IF( B41 = TRUE ,(G41*F41)*0.05+(G41*F41) , G41*F41 ) -> 0
B42: FALSE | G42: 0 | H42: =IF( B42 = TRUE ,(G42*F42)*0.05+(G42*F42) , G42*F42 ) -> 0
... B79: FALSE | G79: 0 | H79: =IF( B79 = TRUE ,(G79*F79)*0.05+(G79*F79) , G79*F79 ) -> 0
C80: Total Cost (No Credit Card Use): | H80: =sum(H31:H79) -> 0
B81: Remaining Balance (With Credit Card Use): | H81: =sum(H31:H79)-M26 -> -159.07
B82: Remaining Balance: | H82: ='11) 2023 BudgetBill Breakdown'!H353-H80 -> 466.01

Sheet 2023 Expences - 11032023
B2: Expences for Paycheck 11/03/2023 | K2: Catagory Totals
B3: CC | C3: Expence | F3: Date | G3: Catagory | H3: Cost | I3: Total | K3: ='08) Drop Down Menus'!A2 -> Groceries | L3: =sumifs(H$4:H$26,G$4:G$26,K3,B$4:B$26,false) -> 293.64
B4: FALSE | C4: MDG | F4: 45233 | G4: Debt | H4: 8.95 | I4: =H4 -> 8.95 | K4: ='08) Drop Down Menus'!A3 -> Cigarettes | L4: =sumifs(H$4:H$26,G$4:G$26,K4,B$4:B$26,false) -> 35.9
B5: FALSE | C5: Citco | F5: 45240 | G5: Cigarettes | H5: 19.82 | I5: =I4+H5 -> 28.77 | K5: ='08) Drop Down Menus'!A4 -> Gas | L5: =sumifs(H$4:H$26,G$4:G$26,K5,B$4:B$26,false) -> 30.96
B6: FALSE | C6: WalGreens | F6: 45236 | G6: Medical | H6: 23.09 | I6: =I5+H6 -> 51.86 | K6: ='08) Drop Down Menus'!A5 -> Entertainment | L6: =sumifs(H$4:H$26,G$4:G$26,K6,B$4:B$26,false) -> 0
B7: FALSE | C7: WalMart | F7: 45235 | G7: Groceries | H7: 167.27 | I7: =I6+H7 -> 219.13 | K7: ='08) Drop Down Menus'!A6 -> Medical | L7: =sumifs(H$4:H$26,G$4:G$26,K7,B$4:B$26,false) -> 23.09
B8: FALSE | C8: BP | F8: 45233 | G8: Gas | H8: 30.96 | I8: =I7+H8 -> 250.09 | K8: ='08) Drop Down Menus'!A7 -> Vehicle | L8: =sumifs(H$4:H$26,G$4:G$26,K8,B$4:B$26,false) -> 0
B9: FALSE | C9: Laundry Withdrawl | F9: 45241 | G9: Maintenance | H9: 23.5 | I9: =I8+H9 -> 273.59 | K9: ='08) Drop Down Menus'!A8 -> Maintenance | L9: =sumifs(H$4:H$26,G$4:G$26,K9,B$4:B$26,false) -> 30.31
B10: FALSE | C10: Meijer | F10: 45241 | G10: Maintenance | H10: 6.81 | I10: =I9+H10 -> 280.4 | K10: ='08) Drop Down Menus'!A9 -> Debt | L10: =sumifs(H$4:H$26,G$4:G$26,K10,B$4:B$26,false) -> 8.95
B11: FALSE | C11: Meijer | F11: 45245 | G11: Groceries | H11: 126.37 | I11: =I10+H11 -> 406.77
B12: FALSE | C12: Kwik Trip | F12: 45245 | G12: Cigarettes | H12: 16.08 | I12: =I11+H12 -> 422.85 | K12: Catagory | L12: YTD | M12: Average
B13: FALSE | H13: 0 | I13: =I12+H13 -> 422.85 | K13: ='08) Drop Down Menus'!A2 -> Groceries | L13: =L3+'2023 Expences - 06162023'!K13 -> 2960.56 | M13: =L13/M$21 -> 134.57091
B14: FALSE | H14: 0 | I14: =I13+H14 -> 422.85 | K14: ='08) Drop Down Menus'!A3 -> Cigarettes | L14: =L4+'2023 Expences - 06162023'!K14 -> 578.87 | M14: =L14/M$21 -> 26.312273
B15: FALSE | H15: 0 | I15: =I14+H15 -> 422.85 | K15: ='08) Drop Down Menus'!A4 -> Gas | L15: =L5+'2023 Expences - 06162023'!K15 -> 327.68 | M15: =L15/M$21 -> 14.894545
B16: FALSE | H16: 0 | I16: =I15+H16 -> 422.85 | K16: ='08) Drop Down Menus'!A5 -> Entertainment | L16: =L6+'2023 Expences - 06162023'!K16 -> 476.99 | M16: =L16/M$21 -> 21.681364
B17: FALSE | H17: 0 | I17: =I16+H17 -> 422.85 | K17: ='08) Drop Down Menus'!A6 -> Medical | L17: =L7+'2023 Expences - 06162023'!K17 -> 235.31 | M17: =L17/M$21 -> 10.695909
B18: FALSE | H18: 0 | I18: =I17+H18 -> 422.85 | K18: ='08) Drop Down Menus'!A7 -> Vehicle | L18: =L8+'2023 Expences - 06162023'!K18 -> 144.32 | M18: =L18/M$21 -> 6.56
B19: FALSE | H19: 0 | I19: =I18+H19 -> 422.85 | K19: ='08) Drop Down Menus'!A8 -> Maintenance | L19: =L9+'2023 Expences - 06162023'!K19 -> 630.97 | M19: =L19/M$21 -> 28.680455
B20: FALSE | H20: 0 | I20: =I19+H20 -> 422.85 | K20: ='08) Drop Down Menus'!A9 -> Debt | L20: =L10+'2023 Expences - 06162023'!K20 -> 359.6 | M20: =L20/M$21 -> 16.345455
B21: FALSE | H21: 0 | I21: =I20+H21 -> 422.85 | K21: Paycheck Number | M21: 22
B22: FALSE | H22: 0 | I22: =I21+H22 -> 422.85
B23: FALSE | H23: 0 | I23: =I22+H23 -> 422.85 | K23: Mission Lane Credit Card Information ($500 Limit)
B24: FALSE | H24: 0 | I24: =I23+H24 -> 422.85 | K24: Last Payment / Amount | M24: 0
B25: FALSE | H25: 0 | I25: =I24+H25 -> 422.85 | K25: Used This Period | L25: 0
B26: FALSE | H26: 0 | I26: =I25+H26 -> 422.85 | K26: Available (Before / After) | L26: 149.49 | M26: =L26+M24-L25 -> 149.49
C27: Expence Grand Total | H27: =I26 -> 422.85 | K27: Balance to Pay | M27: =500-M26 -> 350.51
B29: Shopping List
B30: Tax | C30: Item | D30: Isle | E30: Category | F30: Amount | G30: Cost of One | H30: Total Cost
B31: FALSE | G31: 0 | H31: =IF( B31 = TRUE ,(G31*F31)*0.05+(G31*F31) , G31*F31 ) -> 0
B32: FALSE | G32: 0 | H32: =IF( B32 = TRUE ,(G32*F32)*0.05+(G32*F32) , G32*F32 ) -> 0
B33: FALSE | G33: 0 | H33: =IF( B33 = TRUE ,(G33*F33)*0.05+(G33*F33) , G33*F33 ) -> 0
B34: FALSE | G34: 0 | H34: =IF( B34 = TRUE ,(G34*F34)*0.05+(G34*F34) , G34*F34 ) -> 0
B35: FALSE | G35: 0 | H35: =IF( B35 = TRUE ,(G35*F35)*0.05+(G35*F35) , G35*F35 ) -> 0
B36: FALSE | G36: 0 | H36: =IF( B36 = TRUE ,(G36*F36)*0.05+(G36*F36) , G36*F36 ) -> 0
B37: FALSE | G37: 0 | H37: =IF( B37 = TRUE ,(G37*F37)*0.05+(G37*F37) , G37*F37 ) -> 0
B38: FALSE | G38: 0 | H38: =IF( B38 = TRUE ,(G38*F38)*0.05+(G38*F38) , G38*F38 ) -> 0
B39: FALSE | G39: 0 | H39: =IF( B39 = TRUE ,(G39*F39)*0.05+(G39*F39) , G39*F39 ) -> 0
B40: FALSE | G40: 0 | H40: =IF( B40 = TRUE ,(G40*F40)*0.05+(G40*F40) , G40*F40 ) -> 0
B41: FALSE | G41: 0 | H41: =IF( B41 = TRUE ,(G41*F41)*0.05+(G41*F41) , G41*F41 ) -> 0
B42: FALSE | G42: 0 | H42: =IF( B42 = TRUE ,(G42*F42)*0.05+(G42*F42) , G42*F42 ) -> 0
... B79: FALSE | G79: 0 | H79: =IF( B79 = TRUE ,(G79*F79)*0.05+(G79*F79) , G79*F79 ) -> 0
C80: Total Cost (No Credit Card Use): | H80: =sum(H31:H79) -> 0
B81: Remaining Balance (With Credit Card Use): | H81: =sum(H31:H79)-M26 -> -149.49
B82: Remaining Balance: | H82: ='11) 2023 BudgetBill Breakdown'!H371-H80 -> 57.06

Sheet 2023 Expences - 11172023
B2: Expences for Paycheck 11/17/2023 | K2: Catagory Totals
B3: CC | C3: Expence | F3: Date | G3: Catagory | H3: Cost | I3: Total | K3: ='08) Drop Down Menus'!A2 -> Groceries | L3: =sumifs(H$4:H$26,G$4:G$26,K3,B$4:B$26,false) -> 39.61
B4: FALSE | C4: Oculus Store (BoneLabs) | F4: 45254 | G4: Entertainment | H4: 25.19 | I4: =H4 -> 25.19 | K4: ='08) Drop Down Menus'!A3 -> Cigarettes | L4: =sumifs(H$4:H$26,G$4:G$26,K4,B$4:B$26,false) -> 59.99
B5: FALSE | C5: Wal-Mart (Vyvanse) | F5: 45252 | G5: Medical | H5: 10 | I5: =I4+H5 -> 35.19 | K5: ='08) Drop Down Menus'!A4 -> Gas | L5: =sumifs(H$4:H$26,G$4:G$26,K5,B$4:B$26,false) -> 0
B6: FALSE | C6: Quik-Trip | F6: 45251 | G6: Cigarettes | H6: 30.03 | I6: =I5+H6 -> 65.22 | K6: ='08) Drop Down Menus'!A5 -> Entertainment | L6: =sumifs(H$4:H$26,G$4:G$26,K6,B$4:B$26,false) -> 25.19
B7: FALSE | C7: Wal-Mart | F7: 45251 | G7: Groceries | H7: 39.61 | I7: =I6+H7 -> 104.83 | K7: ='08) Drop Down Menus'!A6 -> Medical | L7: =sumifs(H$4:H$26,G$4:G$26,K7,B$4:B$26,false) -> 10
B8: FALSE | C8: BP (Cigarettes) | F8: 45256 | G8: Cigarettes | H8: 29.96 | I8: =I7+H8 -> 134.79 | K8: ='08) Drop Down Menus'!A7 -> Vehicle | L8: =sumifs(H$4:H$26,G$4:G$26,K8,B$4:B$26,false) -> 0
B9: FALSE | H9: 0 | I9: =I8+H9 -> 134.79 | K9: ='08) Drop Down Menus'!A8 -> Maintenance | L9: =sumifs(H$4:H$26,G$4:G$26,K9,B$4:B$26,false) -> 0
B10: FALSE | H10: 0 | I10: =I9+H10 -> 134.79 | K10: ='08) Drop Down Menus'!A9 -> Debt | L10: =sumifs(H$4:H$26,G$4:G$26,K10,B$4:B$26,false) -> 0
B11: FALSE | H11: 0 | I11: =I10+H11 -> 134.79
B12: FALSE | H12: 0 | I12: =I11+H12 -> 134.79 | K12: Catagory | L12: YTD | M12: Average
B13: FALSE | H13: 0 | I13: =I12+H13 -> 134.79 | K13: ='08) Drop Down Menus'!A2 -> Groceries | L13: =L3+'2023 Expences - 06162023'!K13 -> 2706.53 | M13: =L13/M$21 -> 117.67522
B14: FALSE | H14: 0 | I14: =I13+H14 -> 134.79 | K14: ='08) Drop Down Menus'!A3 -> Cigarettes | L14: =L4+'2023 Expences - 06162023'!K14 -> 602.96 | M14: =L14/M$21 -> 26.215652
B15: FALSE | H15: 0 | I15: =I14+H15 -> 134.79 | K15: ='08) Drop Down Menus'!A4 -> Gas | L15: =L5+'2023 Expences - 06162023'!K15 -> 296.72 | M15: =L15/M$21 -> 12.90087
B16: FALSE | H16: 0 | I16: =I15+H16 -> 134.79 | K16: ='08) Drop Down Menus'!A5 -> Entertainment | L16: =L6+'2023 Expences - 06162023'!K16 -> 502.18 | M16: =L16/M$21 -> 21.833913
B17: FALSE | H17: 0 | I17: =I16+H17 -> 134.79 | K17: ='08) Drop Down Menus'!A6 -> Medical | L17: =L7+'2023 Expences - 06162023'!K17 -> 222.22 | M17: =L17/M$21 -> 9.6617391
B18: FALSE | H18: 0 | I18: =I17+H18 -> 134.79 | K18: ='08) Drop Down Menus'!A7 -> Vehicle | L18: =L8+'2023 Expences - 06162023'!K18 -> 144.32 | M18: =L18/M$21 -> 6.2747826
B19: FALSE | H19: 0 | I19: =I18+H19 -> 134.79 | K19: ='08) Drop Down Menus'!A8 -> Maintenance | L19: =L9+'2023 Expences - 06162023'!K19 -> 600.66 | M19: =L19/M$21 -> 26.115652
B20: FALSE | H20: 0 | I20: =I19+H20 -> 134.79 | K20: ='08) Drop Down Menus'!A9 -> Debt | L20: =L10+'2023 Expences - 06162023'!K20 -> 350.65 | M20: =L20/M$21 -> 15.245652
B21: FALSE | H21: 0 | I21: =I20+H21 -> 134.79 | K21: Paycheck Number | M21: 23
B22: FALSE | H22: 0 | I22: =I21+H22 -> 134.79
B23: FALSE | H23: 0 | I23: =I22+H23 -> 134.79 | K23: Mission Lane Credit Card Information ($500 Limit)
B24: FALSE | H24: 0 | I24: =I23+H24 -> 134.79 | K24: Last Payment / Amount | M24: 0
B25: FALSE | H25: 0 | I25: =I24+H25 -> 134.79 | K25: Used This Period | L25: 0
B26: FALSE | H26: 0 | I26: =I25+H26 -> 134.79 | K26: Available (Before / After) | L26: 174.49 | M26: =L26+M24-L25 -> 174.49
C27: Expence Grand Total | H27: =I26 -> 134.79 | K27: Balance to Pay | M27: =500-M26 -> 325.51
B29: Shopping List | K29: Amazon Credit Card Information ($400 Limit)
B30: Tax | C30: Item | D30: Isle | E30: Category | F30: Amount | G30: Cost of One | H30: Total Cost | K30: Last Payment / Amount | M30: 0
B31: FALSE | G31: 0 | H31: =IF( B31 = TRUE ,(G31*F31)*0.05+(G31*F31) , G31*F31 ) -> 0 | K31: Used This Period | L31: 0
B32: FALSE | G32: 0 | H32: =IF( B32 = TRUE ,(G32*F32)*0.05+(G32*F32) , G32*F32 ) -> 0 | K32: Available (Before / After) | L32: 167 | M32: =L32+M30-L31 -> 167
B33: FALSE | G33: 0 | H33: =IF( B33 = TRUE ,(G33*F33)*0.05+(G33*F33) , G33*F33 ) -> 0 | K33: Balance to Pay | M33: =400-M32 -> 233
B34: FALSE | G34: 0 | H34: =IF( B34 = TRUE ,(G34*F34)*0.05+(G34*F34) , G34*F34 ) -> 0
B35: FALSE | G35: 0 | H35: =IF( B35 = TRUE ,(G35*F35)*0.05+(G35*F35) , G35*F35 ) -> 0 | K35: Total Credit Available | L35: =M26+M32 -> 341.49
B36: FALSE | G36: 0 | H36: =IF( B36 = TRUE ,(G36*F36)*0.05+(G36*F36) , G36*F36 ) -> 0 | K36: Total Balance to Pay | L36: =-(M27+M33) -> -558.51
B37: FALSE | G37: 0 | H37: =IF( B37 = TRUE ,(G37*F37)*0.05+(G37*F37) , G37*F37 ) -> 0
B38: FALSE | G38: 0 | H38: =IF( B38 = TRUE ,(G38*F38)*0.05+(G38*F38) , G38*F38 ) -> 0
B39: FALSE | G39: 0 | H39: =IF( B39 = TRUE ,(G39*F39)*0.05+(G39*F39) , G39*F39 ) -> 0
B40: FALSE | G40: 0 | H40: =IF( B40 = TRUE ,(G40*F40)*0.05+(G40*F40) , G40*F40 ) -> 0
B41: FALSE | G41: 0 | H41: =IF( B41 = TRUE ,(G41*F41)*0.05+(G41*F41) , G41*F41 ) -> 0
B42: FALSE | G42: 0 | H42: =IF( B42 = TRUE ,(G42*F42)*0.05+(G42*F42) , G42*F42 ) -> 0
B43: FALSE | G43: 0 | H43: =IF( B43 = TRUE ,(G43*F43)*0.05+(G43*F43) , G43*F43 ) -> 0
B44: FALSE | G44: 0 | H44: =IF( B44 = TRUE ,(G44*F44)*0.05+(G44*F44) , G44*F44 ) -> 0
B45: FALSE | G45: 0 | H45: =IF( B45 = TRUE ,(G45*F45)*0.05+(G45*F45) , G45*F45 ) -> 0
B46: FALSE | G46: 0 | H46: =IF( B46 = TRUE ,(G46*F46)*0.05+(G46*F46) , G46*F46 ) -> 0
B47: FALSE | G47: 0 | H47: =IF( B47 = TRUE ,(G47*F47)*0.05+(G47*F47) , G47*F47 ) -> 0
B48: FALSE | G48: 0 | H48: =IF( B48 = TRUE ,(G48*F48)*0.05+(G48*F48) , G48*F48 ) -> 0
... B79: FALSE | G79: 0 | H79: =IF( B79 = TRUE ,(G79*F79)*0.05+(G79*F79) , G79*F79 ) -> 0
C80: Total Cost (No Credit Card Use): | H80: =sum(H31:H79) -> 0
B81: Remaining Balance (With Credit Card Use): | H81: =-sum(H31:H79)+L35+'11) 2023 BudgetBill Breakdown'!H389 -> 472.42
B82: Remaining Balance (Only Real Money): | H82: ='11) 2023 BudgetBill Breakdown'!H389-H80 -> 130.93

Sheet 2023 Expences - 12012023
B2: Expences for Paycheck 12/01/2023 | K2: Catagory Totals
B3: CC | C3: Expence | F3: Date | G3: Catagory | H3: Cost | I3: Total | K3: ='08) Drop Down Menus'!A2 -> Groceries | L3: =sumifs(H$4:H$30,G$4:G$30,K3,B$4:B$30,false) -> 137.55
B4: FALSE | C4: Kwik Trip | F4: 45262 | G4: Cigarettes | H4: 31.08 | I4: =H4 -> 31.08 | K4: ='08) Drop Down Menus'!A3 -> Cigarettes | L4: =sumifs(H$4:H$30,G$4:G$30,K4,B$4:B$30,false) -> 31.08
B5: FALSE | C5: Kwik Trip | F5: 45262 | G5: Gas | H5: 25.05 | I5: =I4+H5 -> 56.13 | K5: ='08) Drop Down Menus'!A4 -> Gas | L5: =sumifs(H$4:H$30,G$4:G$30,K5,B$4:B$30,false) -> 25.05
B6: FALSE | C6: Wal-Mart | F6: 45262 | G6: Groceries | H6: 137.55 | I6: =I5+H6 -> 193.68 | K6: ='08) Drop Down Menus'!A5 -> Entertainment | L6: =sumifs(H$4:H$30,G$4:G$30,K6,B$4:B$30,false) -> 0
B7: FALSE | H7: 0 | I7: =I6+H7 -> 193.68 | K7: ='08) Drop Down Menus'!A6 -> Medical | L7: =sumifs(H$4:H$30,G$4:G$30,K7,B$4:B$30,false) -> 0
B8: FALSE | K8: ='08) Drop Down Menus'!A7 -> Vehicle | L8: =sumifs(H$4:H$30,G$4:G$30,K8,B$4:B$30,false) -> 0
B9: FALSE | H9: 0 | I9: =I7+H9 -> 193.68 | K9: ='08) Drop Down Menus'!A8 -> Maintenance | L9: =sumifs(H$4:H$30,G$4:G$30,K9,B$4:B$30,false) -> 0
B10: FALSE | K10: ='08) Drop Down Menus'!A9 -> Debt | L10: =sumifs(H$4:H$30,G$4:G$30,K10,B$4:B$30,false) -> 0
B11: FALSE | H11: 0 | I11: =I9+H11 -> 193.68 | K11: ='08) Drop Down Menus'!A10 -> Holiday Gifts | L11: =sumifs(H$4:H$30,G$4:G$30,K11,B$4:B$30,false) -> 0
B12: FALSE | H12: 0 | I12: =I11+H12 -> 193.68 | K12: ='08) Drop Down Menus'!A11 -> Haircut | L12: =sumifs(H$4:H$30,G$4:G$30,K12,B$4:B$30,false) -> 0
B13: FALSE | H13: 0 | I13: =I12+H13 -> 193.68
B14: FALSE | H14: 0 | I14: =I13+H14 -> 193.68 | K14: Catagory | L14: YTD | M14: Average
B15: FALSE | H15: 0 | I15: =I14+H15 -> 193.68 | K15: ='08) Drop Down Menus'!A2 -> Groceries | L15: =L3+'2023 Expences - 11172023'!L17 -> 359.77 | M15: =L15/M$25 -> 14.990417
B16: FALSE | H16: 0 | I16: =I15+H16 -> 193.68 | K16: ='08) Drop Down Menus'!A3 -> Cigarettes | L16: =L4+'2023 Expences - 11172023'!L18 -> 175.4 | M16: =L16/M$25 -> 7.3083333
B17: FALSE | K17: ='08) Drop Down Menus'!A4 -> Gas | L17: =L5+'2023 Expences - 11172023'!L19 -> 625.71 | M17: =L17/M$25 -> 26.07125
B18: FALSE | K18: ='08) Drop Down Menus'!A5 -> Entertainment | L18: =L6+'2023 Expences - 11172023'!L20 -> 350.65 | M18: =L18/M$25 -> 14.610417
B19: FALSE | H19: 0 | I19: =I16+H19 -> 193.68 | K19: ='08) Drop Down Menus'!A6 -> Medical | L19: =L7+'2023 Expences - 11172023'!L21 -> 0 | M19: =L19/M$25 -> 0
B20: FALSE | H20: 0 | I20: =I19+H20 -> 193.68 | K20: ='08) Drop Down Menus'!A7 -> Vehicle | L20: =L8+'2023 Expences - 11172023'!L22 -> 0 | M20: =L20/M$25 -> 0
B21: FALSE | H21: 0 | I21: =I20+H21 -> 193.68 | K21: ='08) Drop Down Menus'!A8 -> Maintenance | L21: =L9+'2023 Expences - 11172023'!L23 -> 0 | M21: =L21/M$25 -> 0
B22: FALSE | H22: 0 | I22: =I21+H22 -> 193.68 | K22: ='08) Drop Down Menus'!A9 -> Debt | L22: =L10+'2023 Expences - 11172023'!L24 -> 0 | M22: =L22/M$25 -> 0
B23: FALSE | H23: 0 | I23: =I22+H23 -> 193.68 | K23: ='08) Drop Down Menus'!A10 -> Holiday Gifts | L23: =L11+'2023 Expences - 11172023'!L25 -> 0 | M23: =L23/M$25 -> 0
B24: FALSE | H24: 0 | I24: =I23+H24 -> 193.68 | K24: ='08) Drop Down Menus'!A11 -> Haircut | L24: =L12+'2023 Expences - 11172023'!L26 -> 174.49 | M24: =L24/M$25 -> 7.2704167
B25: FALSE | H25: 0 | I25: =I24+H25 -> 193.68 | K25: Paycheck Number | M25: 24
B26: FALSE | H26: 0 | I26: =I25+H26 -> 193.68
B27: FALSE | H27: 0 | I27: =I26+H27 -> 193.68 | K27: Mission Lane Credit Card Information ($500 Limit)
B28: FALSE | H28: 0 | I28: =I27+H28 -> 193.68 | K28: Last Payment / Amount | M28: 0
B29: FALSE | H29: 0 | I29: =I28+H29 -> 193.68 | K29: Used This Period | L29: 0
B30: FALSE | H30: 0 | I30: =I29+H30 -> 193.68 | K30: Available (Before / After) | L30: 149.49 | M30: =L30+M28-L29 -> 149.49
C31: Expence Grand Total | H31: =I30 -> 193.68 | K31: Balance to Pay | M31: =500-M30 -> 350.51
B33: Shopping List
B34: Tax | C34: Item | D34: Isle | E34: Category | F34: Amount | G34: Cost of One | H34: Total Cost
B35: FALSE | G35: 0 | H35: =IF( B35 = TRUE ,(G35*F35)*0.05+(G35*F35) , G35*F35 ) -> 0
B36: FALSE | G36: 0 | H36: =IF( B36 = TRUE ,(G36*F36)*0.05+(G36*F36) , G36*F36 ) -> 0
B37: FALSE | G37: 0 | H37: =IF( B37 = TRUE ,(G37*F37)*0.05+(G37*F37) , G37*F37 ) -> 0
B38: FALSE | G38: 0 | H38: =IF( B38 = TRUE ,(G38*F38)*0.05+(G38*F38) , G38*F38 ) -> 0
B39: FALSE | G39: 0 | H39: =IF( B39 = TRUE ,(G39*F39)*0.05+(G39*F39) , G39*F39 ) -> 0
B40: FALSE | G40: 0 | H40: =IF( B40 = TRUE ,(G40*F40)*0.05+(G40*F40) , G40*F40 ) -> 0
B41: FALSE | G41: 0 | H41: =IF( B41 = TRUE ,(G41*F41)*0.05+(G41*F41) , G41*F41 ) -> 0
B42: FALSE | G42: 0 | H42: =IF( B42 = TRUE ,(G42*F42)*0.05+(G42*F42) , G42*F42 ) -> 0
B43: FALSE | G43: 0 | H43: =IF( B43 = TRUE ,(G43*F43)*0.05+(G43*F43) , G43*F43 ) -> 0
B44: FALSE | G44: 0 | H44: =IF( B44 = TRUE ,(G44*F44)*0.05+(G44*F44) , G44*F44 ) -> 0
B45: FALSE | G45: 0 | H45: =IF( B45 = TRUE ,(G45*F45)*0.05+(G45*F45) , G45*F45 ) -> 0
B46: FALSE | G46: 0 | H46: =IF( B46 = TRUE ,(G46*F46)*0.05+(G46*F46) , G46*F46 ) -> 0
... B83: FALSE | G83: 0 | H83: =IF( B83 = TRUE ,(G83*F83)*0.05+(G83*F83) , G83*F83 ) -> 0
C84: Total Cost (No Credit Card Use): | H84: =sum(H35:H83) -> 0
B85: Remaining Balance (With Credit Card Use): | H85: =sum(H35:H83)-M30 -> -149.49
B86: Remaining Balance: | H86: ='11) 2023 BudgetBill Breakdown'!H371-H84 -> 57.06

Sheet 2023 Expences - 12152023
B2: Expences for Paycheck 12/15/2023 | K2: Catagory Totals
B3: CC | C3: Expence | F3: Date | G3: Catagory | H3: Cost | I3: Total | K3: ='08) Drop Down Menus'!A2 -> Groceries | L3: =sumifs(H$4:H$34,G$4:G$34,K3,B$4:B$34,false) -> 229.8
B4: FALSE | C4: Vending Machine | F4: 45275 | G4: Groceries | H4: 2.04 | I4: =H4 -> 2.04 | K4: ='08) Drop Down Menus'!A3 -> Cigarettes | L4: =sumifs(H$4:H$34,G$4:G$34,K4,B$4:B$34,false) -> 39.93
B5: FALSE | C5: Kwik Trip | F5: 45276 | G5: Groceries | H5: 15.81 | I5: =I4+H5 -> 17.85 | K5: ='08) Drop Down Menus'!A4 -> Gas | L5: =sumifs(H$4:H$34,G$4:G$34,K5,B$4:B$34,false) -> 0
B6: FALSE | C6: Citco | F6: 45276 | G6: Cigarettes | H6: 20.96 | I6: =I5+H6 -> 38.81 | K6: ='08) Drop Down Menus'!A5 -> Entertainment | L6: =sumifs(H$4:H$34,G$4:G$34,K6,B$4:B$34,false) -> 65.08
B7: FALSE | C7: Walmart | F7: 45276 | G7: Maintenance | H7: 200 | I7: =I6+H7 -> 238.81 | K7: ='08) Drop Down Menus'!A6 -> Medical | L7: =sumifs(H$4:H$34,G$4:G$34,K7,B$4:B$34,false) -> 65
B8: FALSE | C8: Walmart | F8: 45276 | G8: Groceries | H8: 188.21 | I8: =I7+H8 -> 427.02 | K8: ='08) Drop Down Menus'!A7 -> Vehicle | L8: =sumifs(H$4:H$34,G$4:G$34,K8,B$4:B$34,false) -> 0
B9: FALSE | C9: Steam (Cyberpunk 2077 XPack) | F9: 45277 | G9: Entertainment | H9: 31.49 | I9: =I8+H9 -> 458.51 | K9: ='08) Drop Down Menus'!A8 -> Maintenance | L9: =sumifs(H$4:H$34,G$4:G$34,K9,B$4:B$34,false) -> 200
B10: FALSE | C10: Lowes - Xmas | F10: 45283 | G10: Holiday Gifts | H10: 57.29 | I10: =I9+H10 -> 515.8 | K10: ='08) Drop Down Menus'!A9 -> Debt | L10: =sumifs(H$4:H$34,G$4:G$34,K10,B$4:B$34,false) -> 0
B11: FALSE | C11: T.J. Max - Xmas | F11: 45283 | G11: Holiday Gifts | H11: 38.82 | I11: =I10+H11 -> 554.62 | K11: ='08) Drop Down Menus'!A10 -> Holiday Gifts | L11: =sumifs(H$4:H$34,G$4:G$34,K11,B$4:B$34,false) -> 459.33
B12: FALSE | C12: Walmart - Xmas | F12: 45283 | G12: Holiday Gifts | H12: 22.01 | I12: =I11+H12 -> 576.63 | K12: ='08) Drop Down Menus'!A11 -> Haircut | L12: =sumifs(H$4:H$34,G$4:G$34,K12,B$4:B$34,false) -> 25.27
B13: FALSE | C13: Walmart - Xmas | F13: 45283 | G13: Holiday Gifts | H13: 138.09 | I13: =I12+H13 -> 714.72 | K13: ='08) Drop Down Menus'!A12 -> Subscription - Video | L13: =sumifs(H$4:H$34,G$4:G$34,K13,B$4:B$34,false) -> 0
B14: FALSE | C14: Walmart - Xmas | F14: 45283 | G14: Holiday Gifts | H14: 10 | I14: =I13+H14 -> 724.72 | K14: ='08) Drop Down Menus'!A13 -> Subscription - Game | L14: =sumifs(H$4:H$34,G$4:G$34,K14,B$4:B$34,false) -> 0
B15: FALSE | C15: Haircut | F15: 45283 | G15: Haircut | H15: 25.27 | I15: =I14+H15 -> 749.99
B16: FALSE | C16: Walmart - Xmas | F16: 45284 | G16: Holiday Gifts | H16: 46.28 | I16: =I15+H16 -> 796.27 | K16: Catagory | L16: YTD | M16: Average
B17: FALSE | C17: Walmart - Xmas | F17: 45284 | G17: Holiday Gifts | H17: 146.84 | I17: =I16+H17 -> 943.11 | K17: ='08) Drop Down Menus'!A2 -> Groceries | L17: =-(SUMIF('11) 2023 BudgetBill Breakdown'!B$1:B91,K17, '11) 2023 BudgetBill Breakdown'!F$1:F91)) -> 5125.26 | M17: =L17/M$29 -> 205.0104
B18: FALSE | C18: A&W | F18: 45284 | G18: Groceries | H18: 13.53 | I18: =I17+H18 -> 956.64 | K18: ='08) Drop Down Menus'!A3 -> Cigarettes | L18: =-(SUMIF('11) 2023 BudgetBill Breakdown'!B$1:B91,K18, '11) 2023 BudgetBill Breakdown'!F$1:F91)) -> 1304.4 | M18: =L18/M$29 -> 52.176
B19: FALSE | C19: Epoch | F19: 45286 | G19: Entertainment | H19: 19.95 | I19: =I18+H19 -> 976.59 | K19: ='08) Drop Down Menus'!A4 -> Gas | L19: =-(SUMIF('11) 2023 BudgetBill Breakdown'!B$1:B91,K19, '11) 2023 BudgetBill Breakdown'!F$1:F91)) -> 499.15 | M19: =L19/M$29 -> 19.966
B20: FALSE | C20: Vending Machine x 2 | F20: 45276 | G20: Groceries | H20: 4.08 | I20: =I19+H20 -> 980.67 | K20: ='08) Drop Down Menus'!A5 -> Entertainment | L20: =-(SUMIF('11) 2023 BudgetBill Breakdown'!B$1:B91,K20, '11) 2023 BudgetBill Breakdown'!F$1:F91)) -> 872.64 | M20: =L20/M$29 -> 34.9056
B21: FALSE | C21: Hims | F21: 45280 | G21: Medical | H21: 65 | I21: =I20+H21 -> 1045.67 | K21: ='08) Drop Down Menus'!A6 -> Medical | L21: =-(SUMIF('11) 2023 BudgetBill Breakdown'!B$1:B91,K21, '11) 2023 BudgetBill Breakdown'!F$1:F91)) -> 733.12 | M21: =L21/M$29 -> 29.3248
B22: FALSE | C22: Shell | F22: 45280 | G22: Cigarettes | H22: 18.97 | I22: =I21+H22 -> 1064.64 | K22: ='08) Drop Down Menus'!A7 -> Vehicle | L22: =-(SUMIF('11) 2023 BudgetBill Breakdown'!B$1:B91,K22, '11) 2023 BudgetBill Breakdown'!F$1:F91)) -> 496.5 | M22: =L22/M$29 -> 19.86
B23: FALSE | C23: Steam (Fallout 1st) | F23: 45281 | G23: Entertainment | H23: 13.64 | I23: =I22+H23 -> 1078.28 | K23: ='08) Drop Down Menus'!A8 -> Maintenance | L23: =-(SUMIF('11) 2023 BudgetBill Breakdown'!B$1:B91,K23, '11) 2023 BudgetBill Breakdown'!F$1:F91)) -> 1018.37 | M23: =L23/M$29 -> 40.7348
B24: FALSE | C24: Vending Machine x 2 | F24: 45284 | G24: Groceries | H24: =4.09+2.04 -> 6.13 | I24: =I23+H24 -> 1084.41 | K24: ='08) Drop Down Menus'!A9 -> Debt | L24: =-(SUMIF('11) 2023 BudgetBill Breakdown'!B$1:B91,K24, '11) 2023 BudgetBill Breakdown'!F$1:F91)) -> 673.69 | M24: =L24/M$29 -> 26.9476
B25: FALSE | H25: 0 | I25: =I24+H25 -> 1084.41 | K25: ='08) Drop Down Menus'!A10 -> Holiday Gifts | L25: =-(SUMIF('11) 2023 BudgetBill Breakdown'!B$1:B91,K25, '11) 2023 BudgetBill Breakdown'!F$1:F91)) -> 459.33 | M25: =L25/M$29 -> 18.3732
B26: FALSE | H26: 0 | I26: =I25+H26 -> 1084.41 | K26: ='08) Drop Down Menus'!A11 -> Haircut | L26: =-(SUMIF('11) 2023 BudgetBill Breakdown'!B$1:B91,K26, '11) 2023 BudgetBill Breakdown'!F$1:F91)) -> 25.27 | M26: =L26/M$29 -> 1.0108
B27: FALSE | H27: 0 | I27: =I26+H27 -> 1084.41 | K27: ='08) Drop Down Menus'!A12 -> Subscription - Video | L27: =-(SUMIF('11) 2023 BudgetBill Breakdown'!B$1:B91,K27, '11) 2023 BudgetBill Breakdown'!F$1:F91)) -> 131.93 | M27: =L27/M$29 -> 5.2772
B28: FALSE | H28: 0 | I28: =I27+H28 -> 1084.41 | K28: ='08) Drop Down Menus'!A13 -> Subscription - Game | L28: =-(SUMIF('11) 2023 BudgetBill Breakdown'!B$1:B91,K28, '11) 2023 BudgetBill Breakdown'!F$1:F91)) -> 125.38 | M28: =L28/M$29 -> 5.0152
B29: FALSE | H29: 0 | I29: =I28+H29 -> 1084.41 | K29: Paycheck Number | M29: 25
B30: FALSE | H30: 0 | I30: =I29+H30 -> 1084.41
B31: FALSE | H31: 0 | I31: =I30+H31 -> 1084.41 | K31: Mission Lane Credit Card Information ($400 Limit)
B32: FALSE | H32: 0 | I32: =I31+H32 -> 1084.41 | K32: Last Payment / Amount | L32: 45276 | M32: 50
B33: FALSE | H33: 0 | I33: =I32+H33 -> 1084.41 | K33: Limit | L33: 500
B34: FALSE | H34: 0 | I34: =I33+H34 -> 1084.41 | K34: Used This Period | L34: 0
C35: Expence Grand Total | H35: =I34 -> 1084.41 | K35: Available (Before / After) | L35: =215.57-50 -> 165.57 | M35: =L35+M32-L34 -> 215.57
K36: Balance to Pay | M36: =L33-M35 -> 284.43
B37: Shopping List
B38: Tax | C38: Item | D38: Isle | E38: Category | F38: Amount | G38: Cost of One | H38: Total Cost | K38: Amazon Credit Card Information ($400 Limit)
B39: FALSE | G39: 0 | H39: =IF( B39 = TRUE ,(G39*F39)*0.05+(G39*F39) , G39*F39 ) -> 0 | K39: Last Payment / Amount | L39: 45276 | M39: 50
B40: FALSE | G40: 0 | H40: =IF( B40 = TRUE ,(G40*F40)*0.05+(G40*F40) , G40*F40 ) -> 0 | K40: Limit | L40: 400
